Workbook
Name ajdic: '[1]Budget 2026'!#REF!
Name ajdic: '[1]Budget 2026'!#REF!
Name ajdic: 'REAL-BDGT2026'!#REF!
Name dic: '[1]Budget 2026'!#REF!
Name dic: '[1]Budget 2026'!#REF!
Name dic: 'REAL-BDGT2026'!#REF!
Name dolarbnaabr: '[1]Budget 2026'!#REF!
Name dolarbnaabr: '[1]Budget 2026'!#REF!
Name dolarbnaabr: 'REAL-BDGT2026'!#REF!
Name dolarbnaago: '[1]Budget 2026'!#REF!
Name dolarbnaago: '[1]Budget 2026'!#REF!
Name dolarbnaago: 'REAL-BDGT2026'!#REF!
Name dolarbnadic: '[1]Budget 2026'!#REF!
Name dolarbnadic: '[1]Budget 2026'!#REF!
Name dolarbnadic: 'REAL-BDGT2026'!#REF!
Name dolarbnaene: '[1]Budget 2026'!$I$219
Name dolarbnaene: '[1]Budget 2026'!$I$219
Name dolarbnaene: 'REAL-BDGT2026'!$I$203
Name dolarbnafeb: '[1]Budget 2026'!#REF!
Name dolarbnafeb: '[1]Budget 2026'!#REF!
Name dolarbnafeb: 'REAL-BDGT2026'!#REF!
Name dolarbnajul: '[1]Budget 2026'!#REF!
Name dolarbnajul: '[1]Budget 2026'!#REF!
Name dolarbnajul: 'REAL-BDGT2026'!#REF!
Name dolarbnajun: '[1]Budget 2026'!#REF!
Name dolarbnajun: '[1]Budget 2026'!#REF!
Name dolarbnajun: 'REAL-BDGT2026'!#REF!
Name dolarbnamar: '[1]Budget 2026'!#REF!
Name dolarbnamar: '[1]Budget 2026'!#REF!
Name dolarbnamar: 'REAL-BDGT2026'!#REF!
Name dolarbnamay: '[1]Budget 2026'!#REF!
Name dolarbnamay: '[1]Budget 2026'!#REF!
Name dolarbnamay: 'REAL-BDGT2026'!#REF!
Name dolarbnanov: '[1]Budget 2026'!#REF!
Name dolarbnanov: '[1]Budget 2026'!#REF!
Name dolarbnanov: 'REAL-BDGT2026'!#REF!
Name dolarbnaoct: '[1]Budget 2026'!#REF!
Name dolarbnaoct: '[1]Budget 2026'!#REF!
Name dolarbnaoct: 'REAL-BDGT2026'!#REF!
Name dolarbnasep: '[1]Budget 2026'!#REF!
Name dolarbnasep: '[1]Budget 2026'!#REF!
Name dolarbnasep: 'REAL-BDGT2026'!#REF!
Name dolarmepabr: '[1]Budget 2026'!#REF!
Name dolarmepabr: '[1]Budget 2026'!#REF!
Name dolarmepabr: 'REAL-BDGT2026'!#REF!
Name dolarmepago: '[1]Budget 2026'!#REF!
Name dolarmepago: '[1]Budget 2026'!#REF!
Name dolarmepago: 'REAL-BDGT2026'!#REF!
Name dolarmepdic: '[1]Budget 2026'!#REF!
Name dolarmepdic: '[1]Budget 2026'!#REF!
Name dolarmepdic: 'REAL-BDGT2026'!#REF!
Name dolarmepene: 'REAL-BDGT2026'!$I$202
Name dolarmepfeb: '[1]Budget 2026'!#REF!
Name dolarmepfeb: '[1]Budget 2026'!#REF!
Name dolarmepfeb: 'REAL-BDGT2026'!#REF!
Name dolarmepjul: '[1]Budget 2026'!#REF!
Name dolarmepjul: '[1]Budget 2026'!#REF!
Name dolarmepjul: 'REAL-BDGT2026'!#REF!
Name dolarmepjun: '[1]Budget 2026'!#REF!
Name dolarmepjun: '[1]Budget 2026'!#REF!

Sheet REAL-BDGT2026
V1: =(+V40-V14-V15)-((+V40-V14-V15)*5%) -> 3.013353e+09
I2: REAL | J2: REAL | K2: REAL | L2: REAL | M2: REAL | N2: REAL | O2: REAL | P2: REAL | Q2: REAL | R2: REAL | S2: REAL | T2: REAL | V2: REAL | X2: BDGT 2026 | Y2: BDGT 2026 | Z2: BDGT 2026 | AA2: BDGT 2026 | AB2: BDGT 2026 | AC2: BDGT 2026 | AD2: BDGT 2026 | AE2: BDGT 2026 | AF2: BDGT 2026 | AG2: BDGT 2026 | AH2: BDGT 2026 | AI2: BDGT 2026 | AK2: BDGT 2026 | AM2: GAP
V3: Acum May | AK3: =+V3 -> Acum May | AM3: =+AK3 -> Acum May
I4: Ene-26 | J4: 46078 | K4: 46106 | L4: Abr-26 | M4: 46167 | N4: 46198 | O4: 46228 | P4: 46259 | Q4: 46290 | R4: 46320 | S4: 46351 | T4: 46381 | V4: FY 2026 | X4: =+I4 -> Ene-26 | Y4: =+J4 -> 46078 | Z4: =+K4 -> 46106 | AA4: =+L4 -> Abr-26 | AB4: =+M4 -> 46167 | AC4: =+N4 -> 46198 | AD4: =+O4 -> 46228 | AE4: =+P4 -> 46259 | ... AI4: =+T4 -> 46381 | AK4: FY 2026 | AM4: FY 2026
B5: Ingresos por Venta de Servicios
C6: Clientes | L6: 0.05 | M6: 0.05 | N6: 0.05 | O6: 0.05 | P6: 0.05 | Q6: 0.05 | R6: 0.05 | S6: 0.05 | T6: 0.05
D7: Farmacias | I7: =SUM(I8:I19) -> 1.8917065e+09 | J7: =SUM(J8:J19) -> 1.7911763e+09 | K7: =SUM(K8:K19) -> 2.0365456e+09 | L7: =SUM(L8:L19) -> 2.0864244e+09 | M7: =SUM(M8:M19) -> 2.1281622e+09 | N7: =SUM(N8:N19) -> 0 | O7: =SUM(O8:O19) -> 0 | P7: =SUM(P8:P19) -> 0 | ... T7: =SUM(T8:T19) -> 0 | V7: =SUM(I7:M7) -> 9.934015e+09 | X7: 1.8131602e+09 | Y7: 1.6904679e+09 | Z7: 1.8510241e+09 | AA7: 1.9443481e+09 | AB7: 2.0626141e+09 | AC7: 2.0723756e+09 | AD7: 2.2962548e+09 | AE7: 2.2645018e+09 | AF7: 2.3857082e+09 | AG7: 2.4962105e+09 | AH7: 2.4331575e+09 | AI7: 2.5095454e+09 | AK7: =SUM(X7:AB7) -> 9.3616144e+09 | AM7: =+V7-AK7 -> 5.7240052e+08 | AN7: =+AM7/AK7 -> 0.061143356
A8: 2 | C8: Farmalink On Line Prepagas | E8: 5111 | I8: 2.5482214e+08 | J8: 2.2033022e+08 | K8: 2.8260867e+08 | L8: 2.886987e+08 | M8: 3.1376796e+08 | V8: =SUM(I8:M8) -> 1.3602277e+09 | X8: 2.2671581e+08 | Y8: 2.0933465e+08 | Z8: 2.3834042e+08 | AA8: 2.5489008e+08 | AB8: 2.7163249e+08 | AC8: 2.7305075e+08 | AD8: 2.9126764e+08 | AE8: 2.8758108e+08 | AF8: 2.9728318e+08 | AG8: 3.0439589e+08 | AH8: 2.8288845e+08 | AI8: 2.8713178e+08 | AK8: =SUM(X8:AB8) -> 1.2009134e+09
A9: 2 | C9: Farmalink On Line Apross | E9: 5111 | I9: 34319465 | J9: 33720492 | K9: 33758789 | L9: 42091264 | M9: 40180831 | V9: =SUM(I9:M9) -> 1.8407084e+08 | X9: 32504828 | Y9: 29340012 | Z9: 32659622 | AA9: 33997073 | AB9: 36403562 | AC9: 37854255 | AD9: 40093476 | AE9: 39347218 | AF9: 39932286 | AG9: 43485128 | AH9: 37731478 | AI9: 38297450 | AK9: =SUM(X9:AB9) -> 1.649051e+08
A10: 2 | C10: Farmalink On Line IOMA | E10: 5111 | I10: 1.2932564e+08 | J10: 1.420488e+08 | K10: 1.5145417e+08 | L10: 1.5695356e+08 | M10: 1.6574712e+08 | V10: =SUM(I10:M10) -> 7.455293e+08 | X10: 1.2537173e+08 | Y10: 1.2020175e+08 | Z10: 1.3213189e+08 | AA10: 1.405428e+08 | AB10: 1.4845625e+08 | AC10: 1.4989528e+08 | AD10: 1.6421312e+08 | AE10: 1.5896456e+08 | AF10: 1.6439587e+08 | AG10: 1.7079632e+08 | AH10: 1.5598071e+08 | AI10: 1.5832042e+08 | AK10: =SUM(X10:AB10) -> 6.6670442e+08
A11: 2 | C11: Farmalink Receta Electronica Prepagas | E11: 5111 | I11: 11823897 | J11: 14400808 | K11: 15955905 | L11: 16626577 | M11: 18614958 | V11: =SUM(I11:M11) -> 77422145 | X11: 9929897.1 | Y11: 9851405.1 | Z11: 11534954 | AA11: 12421706 | AB11: 13411096 | AC11: 13607751 | AD11: 14981324 | AE11: 15231149 | AF11: 15868240 | AG11: 16106264 | AH11: 13786168 | AI11: 13992960 | AK11: =SUM(X11:AB11) -> 57149059
A12: 2 | C12: Farmalink Receta Electronica Apross | E12: 5111 | I12: 2973743.1 | J12: 2532284.2 | K12: 2619109.9 | L12: 3360763.1 | M12: 3380091.3 | V12: =SUM(I12:M12) -> 14865992 | X12: 2601231.5 | Y12: 2347932.3 | Z12: 2614041.1 | AA12: 2720038.7 | AB12: 2914236.5 | AC12: 3029667.5 | AD12: 3209236.7 | AE12: 3149912.2 | AF12: 3195899.1 | AG12: 3243837.6 | AH12: 3018821.2 | AI12: 3064103.5 | AK12: =SUM(X12:AB12) -> 13197480
A13: 2 | C13: Farmalink Receta Electronica IOMA | E13: 5111 | I13: 3753069.9 | J13: 4916448 | K13: 5834881.9 | L13: 4463788.4 | M13: 5877637.1 | V13: =SUM(I13:M13) -> 24845825 | X13: 2894915.9 | Y13: 3065993.8 | Z13: 3447951 | AA13: 3581827.8 | AB13: 3984423.7 | AC13: 4087578.9 | AD13: 4662027.9 | AE13: 4743490.6 | AF13: 4965834.5 | AG13: 5040322 | AH13: 3975273.3 | AI13: 4034902.4 | AK13: =SUM(X13:AB13) -> 16975112
A14: 2 | C14: Farmalink On Line PAMI | E14: 5111 | I14: 1.4115059e+09 | J14: 1.3293495e+09 | K14: 1.501823e+09 | L14: 1.5255242e+09 | M14: 1.5312529e+09 | V14: =SUM(I14:M14) -> 7.2994555e+09 | X14: 1.3719931e+09 | Y14: 1.2767444e+09 | Z14: 1.3877895e+09 | AA14: 1.4172071e+09 | AB14: 1.4678905e+09 | AC14: 1.4405788e+09 | AD14: 1.574275e+09 | AE14: 1.5207368e+09 | AF14: 1.5766526e+09 | AG14: 1.6216858e+09 | AH14: 1.5728801e+09 | AI14: 1.5964733e+09 | AK14: =SUM(X14:AB14) -> 6.9216245e+09
A15: 2 | C15: Farmalink On Line PAMI Imposiciones | E15: 5111 | I15: 41967144 | J15: 42804261 | K15: 41062515 | L15: 47361867 | M15: 47869685 | V15: =SUM(I15:M15) -> 2.2106547e+08 | X15: 39904737 | Y15: 38337796 | Z15: 41261745 | AA15: 42256534 | AB15: 43226277 | AC15: 40927370 | AD15: 44765327 | AE15: 43295302 | AF15: 45556153 | AG15: 46239495 | AH15: 46898200 | AI15: 47601673 | AK15: =SUM(X15:AB15) -> 2.0498709e+08
A16: 2 | C16: Farmalink Presentaciones Digitales | E16: 5111 | I16: 0 | J16: 0 | K16: 0 | L16: 0 | V16: =SUM(I16:M16) -> 0 | X16: 0 | Y16: 0 | Z16: 0 | AA16: 35430177 | AB16: 73394523 | AC16: 1.0804341e+08 | AD16: 1.574275e+08 | AE16: 1.900921e+08 | AF16: 2.3649789e+08 | AG16: 2.8379502e+08 | AH16: 3.1457601e+08 | AI16: 3.5920648e+08 | AK16: =SUM(X16:AB16) -> 1.088247e+08
A17: 1 | C17: Provincia A.R.T. S.A. | E17: 5111 | I17: 1215432.5 | J17: 1073509.3 | K17: 1428548.4 | L17: 1343686 | M17: 1471007.2 | V17: =SUM(I17:M17) -> 6532183.4 | X17: 1243983.8 | Y17: 1243983.8 | Z17: 1243983.8 | AA17: 1300806.9 | AB17: 1300806.9 | AC17: 1300806.9 | AD17: 1360225.7 | AE17: 1360225.7 | AF17: 1360225.7 | AG17: 1422358.6 | AH17: 1422358.6 | AI17: 1422358.6 | AK17: =SUM(X17:AB17) -> 6333565.1
V18: =SUM(I18:M18) -> 0 | AK18: =SUM(X18:AB18) -> 0
V19: =SUM(I19:M19) -> 0 | AK19: =SUM(X19:AB19) -> 0
D20: Laboratorios | I20: =SUM(I21:I36) -> 1.3048782e+08 | J20: =SUM(J21:J36) -> 1.5448823e+08 | K20: =SUM(K21:K36) -> 1.2145758e+08 | L20: =SUM(L21:L36) -> 1.396693e+08 | M20: =SUM(M21:M36) -> 1.4989769e+08 | N20: =SUM(N21:N36) -> 0 | O20: =SUM(O21:O36) -> 0 | P20: =SUM(P21:P36) -> 0 | ... T20: =SUM(T21:T36) -> 0 | V20: =SUM(I20:M20) -> 6.9600062e+08 | X20: 1.3261321e+08 | Y20: 1.2981524e+08 | Z20: 1.2688779e+08 | AA20: 1.3626315e+08 | AB20: 1.3731988e+08 | AC20: 1.3841524e+08 | AD20: 1.4752257e+08 | AE20: 1.4905394e+08 | AF20: 1.5072312e+08 | AG20: 1.6143844e+08 | AH20: 1.6626184e+08 | AI20: 1.738785e+08 | AK20: =SUM(X20:AB20) -> 6.6289927e+08 | AM20: =+V20-AK20 -> 33101348 | AN20: =+AM20/AK20 -> 0.049934204
A21: 1 | C21: Astrazeneca S.A. | E21: 5111 | I21: 22166717 | J21: 20929744 | K21: 19689476 | L21: 22612629 | M21: 22186516 | V21: =SUM(I21:M21) -> 1.0758508e+08 | X21: 21263922 | Y21: 21543070 | Z21: 21826007 | AA21: 22112786 | AB21: 22403461 | AC21: 22698085 | AD21: 22996715 | AE21: 23299406 | AF21: 23606214 | AG21: 23917198 | AH21: 24232415 | AI21: 24551925 | AK21: =SUM(X21:AB21) -> 1.0914925e+08
A22: 1 | C22: Avanter S.R.L | D22: viejos labos | E22: 5111 | I22: 62130128 | J22: 48199032 | K22: 39454206 | L22: 45028730 | M22: 50861033 | V22: =SUM(I22:M22) -> 2.4567313e+08 | X22: 43139377 | Y22: 39544429 | Z22: 35949481 | AA22: 43230334 | AB22: 43230334 | AC22: 43230334 | AD22: 50177579 | AE22: 50177579 | AF22: 50177579 | AG22: 58398675 | AH22: 61179564 | AI22: 66741342 | AK22: =SUM(X22:AB22) -> 2.0509396e+08
A23: 1 | C23: Avanter S.R.L | D23: nuevos labos | E23: 5111 | I23: 0 | J23: 0 | K23: 0 | L23: 0 | V23: =SUM(I23:M23) -> 0 | X23: 270600 | Y23: 369600 | Z23: 379500 | AA23: 435600 | AB23: 471900 | AC23: 471900 | AD23: 495000 | AE23: 495000 | AF23: 495000 | AG23: 518100 | AH23: 518100 | AI23: 518100 | AK23: =SUM(X23:AB23) -> 1927200
A24: 1 | C24: Bayer Argentina S.A. | E24: 5111 | I24: 987716.02 | J24: 972221.92 | K24: 954267.72 | L24: 1044493.2 | M24: 1075303.7 | V24: =SUM(I24:M24) -> 5034002.6 | X24: 893794.9 | Y24: 907201.83 | Z24: 920809.85 | AA24: 934622 | AB24: 948641.33 | AC24: 962870.95 | AD24: 977314.02 | AE24: 991973.73 | AF24: 1006853.3 | AG24: 1021956.1 | AH24: 1037285.5 | AI24: 1052844.8 | AK24: =SUM(X24:AB24) -> 4605069.9
A25: 1 | C25: Ceoderma S.A. | E25: 5111 | I25: 567084.6 | J25: -407194.8 | K25: 0 | L25: 0 | V25: =SUM(I25:M25) -> 159889.8 | X25: 564624.94 | Y25: 564624.94 | Z25: 564624.94 | AA25: 590416.09 | AB25: 590416.09 | AC25: 590416.09 | AD25: 617385.33 | AE25: 617385.33 | AF25: 617385.33 | AG25: 645586.49 | AH25: 645586.49 | AI25: 645586.49 | AK25: =SUM(X25:AB25) -> 2874707
A26: 1 | C26: Iqvia Solutions Argentina | E26: 5111 | I26: 0 | J26: 40336839 | K26: =+J26/2 -> 20168419 | L26: 20168419 | M26: 20168419 | V26: =SUM(I26:M26) -> 1.008421e+08 | X26: 21256746 | Y26: 21256746 | Z26: 21256746 | AA26: 21256746 | AB26: 21256746 | AC26: 21256746 | AD26: 21256746 | AE26: 21256746 | AF26: 21256746 | AG26: 21256746 | AH26: 21256746 | AI26: 21256746 | AK26: =SUM(X26:AB26) -> 1.0628373e+08
A27: 1 | C27: Max Vision | E27: 5111 | I27: 1170304.5 | J27: 1313290.7 | K27: 1488814.9 | L27: 1368036.9 | M27: 1378201.6 | V27: =SUM(I27:M27) -> 6718648.6 | X27: 1213256.2 | Y27: 1213256.2 | Z27: 1213256.2 | AA27: 1268675.8 | AB27: 1268675.8 | AC27: 1268675.8 | AD27: 1326626.8 | AE27: 1326626.8 | AF27: 1326626.8 | AG27: 1387225 | AH27: 1387225 | AI27: 1387225 | AK27: =SUM(X27:AB27) -> 6177120.1
A28: 1 | C28: Panalab Argentina S.A. | D28: Manual | E28: 5111 | I28: 11044183 | J28: 8443666.5 | K28: 9320434.8 | L28: 9289060.3 | M28: 10793228 | V28: =SUM(I28:M28) -> 48890572 | X28: 10944530 | Y28: 9997828 | Z28: 9133015.9 | AA28: 8343010 | AB28: 7621339.7 | AC28: 6962093.8 | AD28: 6359872.7 | AE28: 5809743.7 | AF28: 5307200.9 | AG28: 4848128 | AH28: 4428764.9 | AI28: 4045676.7 | AK28: =SUM(X28:AB28) -> 46039723
A29: 1 | C29: Panalab Argentina S.A. | D29: Digital | E29: 5111 | I29: 26012630 | J29: 27248448 | K29: 30514692 | L29: 31709520 | M29: 36308194 | V29: =SUM(I29:M29) -> 1.5179348e+08 | X29: 24928651 | Y29: 26024300 | Z29: 27183791 | AA29: 28463775 | AB29: 29763372 | AC29: 31139780 | AD29: 32652897 | AE29: 34197940 | AF29: 35835467 | AG29: 37628912 | AH29: 39469556 | AI29: 41421630 | AK29: =SUM(X29:AB29) -> 1.3636389e+08
A30: 1 | C30: Sidus Dermocosmética S.A | E30: 5111 | I30: 2732192.8 | J30: 2975325 | K30: -4664299.4 | L30: 2929705.4 | M30: 3633862 | V30: =SUM(I30:M30) -> 7606785.7 | X30: 4272538.2 | Y30: 4317548.3 | Z30: 4363233.6 | AA30: 4467700.8 | AB30: 4514766.9 | AC30: 4562539 | AD30: 4671778.1 | AE30: 4720994.1 | AF30: 4770948.4 | AG30: 4885177.3 | AH30: 4936641.5 | AI30: 4988877.6 | AK30: =SUM(X30:AB30) -> 21935788
A31: 1 | C31: Sidus S.A. | E31: 5111 | I31: 1233443.7 | J31: 766721.67 | K31: 131940.99 | L31: 1766721.7 | M31: 766722 | V31: =SUM(I31:M31) -> 4665550 | X31: 1341762.9 | Y31: 1533443.3 | Z31: 1533443.3 | AA31: 1533443.3 | AB31: 1603488.5 | AC31: 1603488.5 | AD31: 1603488.5 | AE31: 1676733.3 | AF31: 1676733.3 | AG31: 1676733.3 | AH31: 1753323.7 | AI31: 1753323.7 | AK31: =SUM(X31:AB31) -> 7545581.4
A32: 1 | C32: Unyc S.A. | E32: 5111 | I32: 7990.89 | J32: 8033.18 | K32: 7296.03 | L32: 8321.72 | M32: 3404.34 | V32: =SUM(I32:M32) -> 35046.16 | X32: 11709.34 | Y32: 11709.34 | Z32: 12304.52 | AA32: 12304.52 | AB32: 12304.52 | AC32: 12866.571 | AD32: 12866.571 | AE32: 12866.571 | AF32: 13454.295 | AG32: 13454.295 | AH32: 13454.295 | AI32: 14068.865 | AK32: =SUM(X32:AB32) -> 60332.242 | AO32: =+L40*0.21 -> 4.7000695e+08
A33: 1 | C33: HEALTHCARE MARKETING GROUP S | E33: 5111 | I33: 396875.5 | J33: 971875.5 | K33: 1351875.5 | L33: 904782.22 | M33: 952203.02 | V33: =SUM(I33:M33) -> 4577611.7 | X33: 367193.57 | Y33: 367193.57 | Z33: 367193.57 | AA33: 383966.38 | AB33: 383966.38 | AC33: 383966.38 | AD33: 401505.34 | AE33: 401505.34 | AF33: 401505.34 | AG33: 419845.45 | AH33: 419845.45 | AI33: 419845.45 | AK33: =SUM(X33:AB33) -> 1869513.5
A34: 1 | C34: Colgate palmolive | E34: 5111 | I34: 2038550.1 | J34: 1730226.4 | K34: 2540459.7 | L34: 2338884.9 | M34: 1576522.4 | V34: =SUM(I34:M34) -> 10224644 | X34: 1319500 | Y34: 1339292.5 | Z34: 1359381.9 | AA34: 1379772.6 | AB34: 1400469.2 | AC34: 1421476.2 | AD34: 1442798.4 | AE34: 1464440.4 | AF34: 1486407 | AG34: 1508703.1 | AH34: 1531333.6 | AI34: 1554303.6 | AK34: =SUM(X34:AB34) -> 6798416.2
A35: 1 | C35: Nuevos labos - LAZAR | E35: 5111 | I35: =500000*0 -> 0 | J35: 1000000 | K35: 500000 | L35: 500000 | M35: 194079.51 | V35: =SUM(I35:M35) -> 2194079.5 | X35: 825000 | Y35: 825000 | Z35: 825000 | AA35: 1850000 | AB35: 1850000 | AC35: 1850000 | AD35: 2530000 | AE35: 2605000 | AF35: 2745000 | AG35: 3312000 | AH35: 3452000 | AI35: 3527000 | AK35: =SUM(X35:AB35) -> 6175000
A36: 1 | E36: 5111 | AK36: =SUM(X36:AB36) -> 0
D37: Medicina | I37: =SUM(I38:I39) -> 11164532 | J37: =SUM(J38:J39) -> 36974029 | K37: =SUM(K38:K39) -> -12034640 | L37: =SUM(L38:L39) -> 12034640 | M37: =SUM(M38:M39) -> 14317410 | N37: =SUM(N38:N39) -> 0 | O37: =SUM(O38:O39) -> 0 | P37: =SUM(P38:P39) -> 0 | ... T37: =SUM(T38:T39) -> 0 | V37: =SUM(I37:M37) -> 62455972 | X37: 11882737 | Y37: 11882737 | Z37: 11882737 | AA37: 12425521 | AB37: 12425521 | AC37: 12425521 | AD37: 12993099 | AE37: 12993099 | AF37: 12993099 | AG37: 13586602 | AH37: 13586602 | AI37: 13586602 | AK37: =SUM(X37:AB37) -> 60499253 | AM37: =+V37-AK37 -> 1956718.4 | AN37: =+AM37/AK37 -> 0.032342852
A38: 1 | C38: Obra Social de la Act. de Seguro | E38: 5111 | I38: 11164532 | J38: =12904748.89+(12034640*2) -> 36974029 | K38: -12034640 | L38: 12034640 | M38: 14317410 | V38: =SUM(I38:K38) -> 36103921 | X38: 11882737 | Y38: 11882737 | Z38: 11882737 | AA38: 12425521 | AB38: 12425521 | AC38: 12425521 | AD38: 12993099 | AE38: 12993099 | AF38: 12993099 | AG38: 13586602 | AH38: 13586602 | AI38: 13586602 | AK38: =SUM(X38:Z38) -> 35648211
C40: Subtotal Ingresos | I40: =+I37+I20+I7 -> 2.0333588e+09 | J40: =+J37+J20+J7 -> 1.9826386e+09 | K40: =+K37+K20+K7 -> 2.1459686e+09 | L40: =+L37+L20+L7 -> 2.2381283e+09 | M40: =+M37+M20+M7 -> 2.2923773e+09 | N40: =+N37+N20+N7 -> 0 | O40: =+O37+O20+O7 -> 0 | P40: =+P37+P20+P7 -> 0 | ... T40: =+T37+T20+T7 -> 0 | V40: =SUM(I40:M40) -> 1.0692472e+10 | X40: 1.9576561e+09 | Y40: 1.8321659e+09 | Z40: 1.9897946e+09 | AA40: 2.0930368e+09 | AB40: 2.2123595e+09 | AC40: 2.2232164e+09 | AD40: 2.4567705e+09 | AE40: 2.4265489e+09 | AF40: 2.5494244e+09 | AG40: 2.6712355e+09 | AH40: 2.613006e+09 | AI40: 2.6970105e+09 | AK40: =SUM(X40:AB40) -> 1.0085013e+10 | AM40: =+V40-AK40 -> 6.0745859e+08 | AN40: =+AM40/AK40 -> 0.060233794 | AO40: =+L40-AA40 -> 1.4509154e+08
C41: IIBB | E41: 5612 | I41: -1.2061955e+08 | J41: -124410617 | K41: -1.2598475e+08 | L41: -1.1082338e+08 | M41: -1.2180323e+08 | N41: =-N40*N6 -> 0 | O41: =-O40*O6 -> 0 | P41: =-P40*P6 -> 0 | Q41: =-Q40*Q6 -> 0 | R41: =-R40*R6 -> 0 | S41: =-S40*S6 -> 0 | T41: =-T40*T6 -> 0 | V41: =SUM(I41:M41) -> -6.0364153e+08 | X41: -97882807 | Y41: -91608295 | Z41: -99489730 | AA41: -1.0465184e+08 | AB41: -1.1061798e+08 | AC41: -1.1116082e+08 | AD41: -1.2283853e+08 | AE41: -1.2132744e+08 | AF41: -1.2747122e+08 | AG41: -1.3356178e+08 | AH41: -1.306503e+08 | AI41: -1.3485052e+08 | AK41: =SUM(X41:AB41) -> -5.0425065e+08
B42: Total Ingresos Netos | I42: =SUM(I40:I41) -> 1.9127393e+09 | J42: =SUM(J40:J41) -> 1.858228e+09 | K42: =SUM(K40:K41) -> 2.0199838e+09 | L42: =SUM(L40:L41) -> 2.1273049e+09 | M42: =SUM(M40:M41) -> 2.170574e+09 | N42: =SUM(N40:N41) -> 0 | O42: =SUM(O40:O41) -> 0 | P42: =SUM(P40:P41) -> 0 | ... T42: =SUM(T40:T41) -> 0 | V42: =SUM(V40:V41) -> 1.008883e+10 | X42: 1.8597733e+09 | Y42: 1.7405576e+09 | Z42: 1.8903049e+09 | AA42: 1.9883849e+09 | AB42: 2.1017416e+09 | AC42: 2.1120556e+09 | AD42: 2.333932e+09 | AE42: 2.3052214e+09 | AF42: 2.4219532e+09 | AG42: 2.5376737e+09 | AH42: 2.4823557e+09 | AI42: 2.56216e+09 | AK42: =SUM(X42:AB42) -> 9.5807623e+09 | AM42: =+V42-AK42 -> 5.0806771e+08 | AN42: =+AM42/AK42 -> 0.053029988 | AO42: incremento de la facturación vs la esperada en Bdgt
G43: Categoría P&L
B44: Egresos
C45: Proveedores | D45: Rubro | F45: Descripción
D46: Desarrollo | I46: =SUM(I47:I56) -> 37117401 | J46: =SUM(J47:J56) -> 36667764 | K46: =SUM(K47:K56) -> 35858135 | L46: =SUM(L47:L56) -> 39124931 | M46: =SUM(M47:M56) -> 26771244 | N46: =SUM(N47:N56) -> 0 | O46: =SUM(O47:O56) -> 0 | P46: =SUM(P47:P56) -> 0 | Q46: =SUM(Q47:Q57) -> 0 | R46: =SUM(R47:R57) -> 0 | S46: =SUM(S47:S57) -> 0 | T46: =SUM(T47:T57) -> 0 | V46: =SUM(I46:M46) -> 1.7553948e+08 | W46: =+V46/$V$171 -> 0.043314513 | X46: 41424383 | Y46: 41535814 | Z46: 41648917 | AA46: 43412268 | AB46: 43528789 | AC46: 43647058 | AD46: 32040967 | AE46: 32162810 | AF46: 32286482 | AG46: 33456579 | AH46: 33583988 | AI46: 33713309 | AK46: =SUM(X46:AB46) -> 2.1155017e+08 | AM46: =+V46-AK46 -> -36010695 | AN46: =+AM46/AK46 -> -0.17022296
C47: Acriter | D47: Desarrollo | E47: 5215 | F47: Manten. Licencias Abi | G47: Cost of sales | I47: 5783495.6 | J47: 5560417 | K47: 5554330 | L47: 5748397.4 | M47: 5649940.7 | V47: =SUM(I47:M47) -> 28296581 | X47: 5928750 | Y47: 6017681.2 | Z47: 6107946.5 | AA47: 6199565.7 | AB47: 6292559.2 | AC47: 6386947.5 | AD47: 6482751.8 | AE47: 6579993 | AF47: 6678692.9 | AG47: 6778873.3 | AH47: 6880556.4 | AI47: 6983764.8 | AK47: =SUM(X47:AB47) -> 30546503
C48: Acriter | D48: Desarrollo | E48: 5214 | F48: Desarrollo .Net (80 Horas) | G48: Professional Fees | I48: 5130000 | J48: 5130000 | K48: 5130000 | L48: 5581440 | M48: 5581440 | V48: =SUM(I48:M48) -> 26552880 | X48: 5057692.4 | Y48: 5057692.4 | Z48: 5057692.4 | AA48: 5288719.5 | AB48: 5288719.5 | AC48: 5288719.5 | AD48: 5530299.6 | AE48: 5530299.6 | AF48: 5530299.6 | AG48: 5782914.7 | AH48: 5782914.7 | AI48: 5782914.7 | AK48: =SUM(X48:AB48) -> 25750516
C49: Reserv (Fijo) | D49: Desarrollo | E49: 5214 | F49: Programador .NET (170 Hs) | G49: Professional Fees | I49: 9756908.9 | J49: 9756908.9 | K49: 9756908.9 | L49: 10615517 | M49: 0 | V49: =SUM(I49:M49) -> 39886244 | X49: 10394744 | Y49: 10394744 | Z49: 10394744 | AA49: 10923103 | AB49: 10923103 | AC49: 10923103 | AD49: 5711026.5 | AE49: 5711026.5 | AF49: 5711026.5 | AG49: 5971896.9 | AH49: 5971896.9 | AI49: 5971896.9 | AK49: =SUM(X49:AB49) -> 53030438
C50: Reserv (Fijo) | D50: Desarrollo | E50: 5214 | F50: Programador JAVA (170 Hs) | G50: Professional Fees | I50: 9756908.9 | J50: 9756908.9 | K50: 9756908.9 | L50: 10615517 | M50: 11185225 | V50: =SUM(I50:M50) -> 51071469 | X50: 10394744 | Y50: 10394744 | Z50: 10394744 | AA50: 10923103 | AB50: 10923103 | AC50: 10923103 | AD50: 5711026.5 | AE50: 5711026.5 | AF50: 5711026.5 | AG50: 5971896.9 | AH50: 5971896.9 | AI50: 5971896.9 | AK50: =SUM(X50:AB50) -> 53030438
C51: Reserv (Fijo) | D51: Desarrollo | E51: 5214 | F51: Q&A (40 Hs) | G51: Professional Fees | I51: 1999151.9 | J51: 1999151.9 | K51: 1999151.9 | L51: 2175077.2 | M51: 1145904 | V51: =SUM(I51:M51) -> 9318436.8 | X51: 2129841.9 | Y51: 2129841.9 | Z51: 2129841.9 | AA51: 2238100.7 | AB51: 2238100.7 | AC51: 2238100.7 | AD51: 1170166.7 | AE51: 1170166.7 | AF51: 1170166.7 | AG51: 1223618.1 | AH51: 1223618.1 | AI51: 1223618.1 | AK51: =SUM(X51:AB51) -> 10865727
C52: Reserv (Fijo) | D52: Desarrollo | E52: 5214 | F52: Analista Líder (20 Hs) | G52: Professional Fees | I52: =1220020.94-3000 -> 1217020.9 | J52: =1220020.94-3000 -> 1217020.9 | K52: =1220020.94-3000 -> 1217020.9 | L52: 1327382.8 | M52: 699310.01 | V52: =SUM(I52:M52) -> 5677755.6 | X52: 1299777 | Y52: 1299777 | Z52: 1299777 | AA52: 1365844 | AB52: 1365844 | AC52: 1365844 | AD52: 714116.78 | AE52: 714116.78 | AF52: 714116.78 | AG52: 746736.48 | AH52: 746736.48 | AI52: 746736.48 | AK52: =SUM(X52:AB52) -> 6631019.1
C53: Reserv (Variable) | D53: Desarrollo | E53: 5214 | F53: Variable pool hs (60) | G53: Professional Fees | I53: 2410530 | J53: 2183972 | K53: =1377430+3000 -> 1380430 | L53: 1998215 | M53: 1498661 | V53: =SUM(I53:M53) -> 9471808 | X53: 3668733.1 | Y53: 3668733.1 | Z53: 3668733.1 | AA53: 3855212.9 | AB53: 3855212.9 | AC53: 3855212.9 | AD53: 4031312.8 | AE53: 4031312.8 | AF53: 4031312.8 | AG53: 4215456.6 | AH53: 4215456.6 | AI53: 4215456.6 | AK53: =SUM(X53:AB53) -> 18716625
C54: Acriter | D54: Desarrollo | E54: 5514 | F54: 2 Lic ABI PAMI (amort mensual) | G54: Depreciation | I54: 1063384.3 | J54: 1063384.3 | K54: 1063384.3 | L54: 1063384.3 | M54: 1010763.9 | V54: =SUM(I54:M54) -> 5264301 | X54: 1050101 | Y54: 1050101 | Z54: 1050101 | AA54: 1050101 | AB54: 1050101 | AC54: 1050101 | AD54: 1050101 | AE54: 1050101 | AF54: 1050101 | AG54: 1050101 | AH54: 1050101 | AI54: 1050101 | AK54: =SUM(X54:AB54) -> 5250505
C55: Acriter | D55: Desarrollo | F55: Cloud | G55: Cost of sales | I55: 0 | J55: 0 | K55: 0 | V55: =SUM(I55:M55) -> 0 | X55: 1500000 | Y55: 1522500 | Z55: 1545337.5 | AA55: 1568517.6 | AB55: 1592045.3 | AC55: 1615926 | AD55: 1640164.9 | AE55: 1664767.4 | AF55: 1689738.9 | AG55: 1715085 | AH55: 1740811.2 | AI55: 1766923.4 | AK55: =SUM(X55:AB55) -> 7728400.4
V56: =SUM(I56:M56) -> 0
V57: =SUM(I57:M57) -> 0
D58: Servicios Plataforma | I58: =SUM(I59:I69) -> 3054636.7 | J58: =SUM(J59:J69) -> 2301096.6 | K58: =SUM(K59:K69) -> 3274903.3 | L58: =SUM(L59:L69) -> 3924224.4 | M58: =SUM(M59:M69) -> 12562006 | N58: =SUM(N59:N68) -> 0 | O58: =SUM(O59:O68) -> 0 | P58: =SUM(P59:P68) -> 0 | Q58: =SUM(Q59:Q68) -> 0 | R58: =SUM(R59:R68) -> 0 | S58: =SUM(S59:S68) -> 0 | T58: =SUM(T59:T68) -> 0 | V58: =SUM(I58:M58) -> 25116867 | W58: =+V58/$V$171 -> 0.006197608 | X58: 12225948 | Y58: 3965594.1 | Z58: 4017901.1 | AA58: 30639957 | AB58: 40904516 | AC58: 58284890 | AD58: 3.1565076e+08 | AE58: 99473506 | AF58: 1.2273489e+08 | AG58: 1.5603529e+08 | AH58: 1.6189357e+08 | AI58: 1.8426996e+08 | AK58: =SUM(X58:AB58) -> 91753917 | AM58: =+V58-AK58 -> -66637050 | AN58: =+AM58/AK58 -> -0.72625837
C59: Alfabeta | D59: Servicios Plataforma | E59: 5218 | F59: Manual Farmaceutico | G59: Cost of sales | I59: 477797 | J59: 477797 | K59: 477797 | L59: 477797 | M59: 477797 | V59: =SUM(I59:M59) -> 2388985 | X59: 478466.24 | Y59: 478466.24 | Z59: 478466.24 | AA59: 478466.24 | AB59: 478466.24 | AC59: 478466.24 | AD59: 528342.82 | AE59: 528342.82 | AF59: 528342.82 | AG59: 528342.82 | AH59: 528342.82 | AI59: 528342.82 | AK59: =SUM(X59:AB59) -> 2392331.2
C60: Atentus | D60: Servicios Plataforma | E60: 5213 | F60: Servicio de Monitoreo Web | G60: Cost of sales | I60: 879000 | J60: 801180 | K60: 849000 | L60: 855000 | M60: 858000 | V60: =SUM(I60:M60) -> 4242180 | X60: 900000 | Y60: 913500 | Z60: 927202.5 | AA60: 941110.54 | AB60: 955227.2 | AC60: 969555.6 | AD60: 984098.94 | AE60: 998860.42 | AF60: 1013843.3 | AG60: 1029051 | AH60: 1044486.7 | AI60: 1060154 | AK60: =SUM(X60:AB60) -> 4637040.2
C61: BGH Partner (Aeros) | D61: Servicios Plataforma | E61: 5215 | F61: Susc Lic Google Mens | G61: Cost of sales | I61: 568260 | J61: -30636 | K61: 698328 | L61: 679896 | M61: 718704 | V61: =SUM(I61:M61) -> 2634552 | X61: 653400 | Y61: 683298 | Z61: 693547.47 | AA61: 724655.11 | AB61: 735524.94 | AC61: 746557.81 | AD61: 757756.18 | AE61: 769122.52 | AF61: 780659.36 | AG61: 792369.25 | AH61: 804254.79 | AI61: 816318.61 | AK61: =SUM(X61:AB61) -> 3490425.5
C62: LP&A (IBM) | D62: Servicios Plataforma | E62: 5213 | F62: Asessment s/BD Informix (40Hs) | G62: Cost of sales | M62: 8204581 | V62: =SUM(I62:M62) -> 8204581 | X62: 8389500 | AA62: 8772718.7 | AD62: 9173442.3 | AG62: 9592470.2 | AK62: =SUM(X62:AB62) -> 17162219
C63: LP&A (Licenc. Informix) | D63: Servicios Plataforma | E63: 5213 | F63: Soporte y Mant de las Licencias Informix Anual (12 M) | G63: Cost of sales | V63: =SUM(I63:M63) -> 0 | AD63: 78698392 | AK63: =SUM(X63:AB63) -> 0
C64: Intertron | D64: Servicios Plataforma | E64: 5215 | F64: Suscripción 2 Lic Visio + 28 Lic microsoft 365 + 1 Power BI | G64: Cost of sales | I64: 633623.6 | J64: 579624.48 | K64: 599002 | L64: 614032.87 | M64: 697956.32 | V64: =SUM(I64:M64) -> 3124239.3 | X64: 717082.2 | Y64: 748454.91 | Z64: 759681.73 | AA64: 792316.57 | AB64: 804201.32 | AC64: 816264.34 | AD64: 828508.3 | AE64: 840935.93 | AF64: 853549.97 | AG64: 866353.22 | AH64: 879348.51 | AI64: 892538.74 | AK64: =SUM(X64:AB64) -> 3821736.7
C65: Nexsys | D65: Servicios Plataforma | E65: 5213 | F65: Producto CDC (data replication) | G65: Cost of sales | V65: =SUM(I65:M65) -> 0 | AD65: 1.4469535e+08 | AK65: =SUM(X65:AB65) -> 0
C66: Claude (Anthropic) | D66: Servicios Plataforma | E66: 5215 | F66: Suscripción Mensual | G66: Cost of sales | I66: 484228.78 | J66: 461403.78 | K66: 639049 | L66: 1285771.2 | M66: 1593240 | V66: =SUM(I66:M66) -> 4463692.8 | X66: 1087500 | Y66: 1141875 | Z66: 1159003.1 | AA66: 1215601.1 | AB66: 1233835.1 | AC66: 1252342.7 | AD66: 1271127.8 | AE66: 1290194.7 | AF66: 1309547.6 | AG66: 1329190.8 | AH66: 1349128.7 | AI66: 1369365.6 | AK66: =SUM(X66:AB66) -> 5837814.4
C67: SIGEDAD (Lanmed) | D67: Servicios Plataforma | F67: Servicio de captura transaccional | G67: Cost of sales | V67: =SUM(I67:M67) -> 0 | AA67: 17715088 | AB67: 36697262 | AC67: 54021703 | AD67: 78713748 | AE67: 95046050 | AF67: 1.1824895e+08 | AG67: 1.4189751e+08 | AH67: 1.5728801e+08 | AI67: 1.7960324e+08 | AK67: =SUM(X67:AB67) -> 54412350
C68: a definir | D68: Servicios Plataforma | F68: Desarrollo de Agentes | G68: Cost of sales | V68: =SUM(I68:M68) -> 0 | AA68: 0 | AB68: 0 | AC68: 0 | AD68: 0 | AE68: 0 | AF68: 0 | AG68: 0 | AH68: 0 | AI68: 0 | AK68: =SUM(X68:AB68) -> 0
C69: ADOBE | D69: Servicios Plataforma | F69: Licencia | G69: Cost of sales | I69: 11727.32 | J69: 11727.32 | K69: 11727.32 | L69: 11727.32 | M69: 11727.32 | V69: =SUM(I69:M69) -> 58636.6 | AK69: =SUM(X69:AB69) -> 0
D70: Servidores | I70: =SUM(I71:I72) -> 5323120.6 | J70: =SUM(J71:J72) -> 5323120.6 | K70: =SUM(K71:K72) -> 5323120.6 | L70: =SUM(L71:L72) -> 5323120.6 | M70: =SUM(M71:M72) -> 5323120.6 | N70: =SUM(N71:N72) -> 0 | O70: =SUM(O71:O72) -> 0 | P70: =SUM(P71:P72) -> 0 | ... T70: =SUM(T71:T72) -> 0 | V70: =SUM(I70:M70) -> 26615603 | W70: =+V70/$V$171 -> 0.0065674225 | X70: 5255006 | Y70: 5255006 | Z70: 5255006 | AA70: 5255006 | AB70: 5255006 | AC70: 5255006 | AD70: 5255006 | AE70: 5255006 | AF70: 5255006 | AG70: 5255006 | AH70: 5255006 | AI70: 5255006 | AK70: =SUM(X70:AB70) -> 26275030 | AM70: =+V70-AK70 -> 340573.2 | AN70: =+AM70/AK70 -> 0.012961858
C71: Servidores Lenovo | D71: Servidores | E71: 5516 | F71: Amortización (5 años) | G71: Depreciation | I71: 5323120.6 | J71: 5323120.6 | K71: 5323120.6 | L71: 5323120.6 | M71: 5323120.6 | V71: =SUM(I71:M71) -> 26615603 | X71: 5255006 | Y71: 5255006 | Z71: 5255006 | AA71: 5255006 | AB71: 5255006 | AC71: 5255006 | AD71: 5255006 | AE71: 5255006 | AF71: 5255006 | AG71: 5255006 | AH71: 5255006 | AI71: 5255006 | AK71: =SUM(X71:AB71) -> 26275030
V72: =SUM(I72:M72) -> 0
D73: Servicios Plataforma Clouhesive | I73: =SUM(I74) -> 0 | J73: =SUM(J74) -> 0 | K73: =SUM(K74) -> 0 | L73: =SUM(L74) -> 0 | M73: =SUM(M74) -> 9867000 | N73: =SUM(N74) -> 0 | O73: =SUM(O74) -> 0 | P73: =SUM(P74) -> 0 | ... T73: =SUM(T74) -> 0 | V73: =SUM(I73:M73) -> 9867000 | W73: =+V73/$V$171 -> 0.0024346905 | X73: 10350000 | Y73: 0 | Z73: 0 | AA73: 0 | AB73: 0 | AC73: 0 | AD73: 0 | AE73: 0 | AF73: 0 | AG73: 0 | AH73: 0 | AI73: 0 | AK73: =SUM(X73:AB73) -> 10350000 | AM73: =+V73-AK73 -> -483000 | AN73: =+AM73/AK73 -> -0.046666667
C74: Clouheside (DRS) | D74: Servicios Plataforma Clou | E74: 5213 | F74: Implementación 3er sitio | G74: Cost of sales | I74: 0 | J74: 0 | K74: 0 | L74: 0 | M74: 9867000 | V74: =SUM(I74:M74) -> 9867000 | X74: 10350000 | AK74: =SUM(X74:AB74) -> 10350000
D75: Soporte Operativo | I75: =SUM(I76:I80) -> 14752514 | J75: =SUM(J76:J80) -> 12629594 | K75: =SUM(K76:K80) -> 12792494 | L75: =SUM(L76:L80) -> 12762477 | M75: =SUM(M76:M80) -> 13805852 | N75: =SUM(N76:N80) -> 0 | O75: =SUM(O76:O80) -> 0 | P75: =SUM(P76:P80) -> 0 | ... T75: =SUM(T76:T80) -> 0 | V75: =SUM(I75:M75) -> 66742931 | W75: =+V75/$V$171 -> 0.016468874 | X75: 14488230 | Y75: 14646216 | Z75: 14805978 | AA75: 18300538 | AB75: 18497245 | AC75: 20665245 | AD75: 18897203 | AE75: 19100503 | AF75: 19306051 | AG75: 19513873 | AH75: 19723994 | AI75: 19936442 | AK75: =SUM(X75:AB75) -> 80738207 | AM75: =+V75-AK75 -> -13995277 | AN75: =+AM75/AK75 -> -0.17334143
C76: Bapro | D76: Soporte Operativo | E76: 5212 | F76: Call Center (Operadores) | G76: Cost of sales | I76: 12158900 | J76: 10500781 | K76: 10612000 | L76: 10581983 | M76: 11526916 | V76: =SUM(I76:M76) -> 55380581 | X76: 11867500 | Y76: 11986175 | Z76: 12106037 | AA76: 12227097 | AB76: 12349368 | AC76: 12472862 | AD76: 12597590 | AE76: 12723566 | AF76: 12850802 | AG76: 12979310 | AH76: 13109103 | AI76: 13240194 | AK76: =SUM(X76:AB76) -> 60536177
C77: IT FACTORY S.R.L | D77: Soporte Operativo | E77: 5215 | F77: Susc Anual Asist Remota Team Viewer | G77: Cost of sales | I77: 0 | J77: 0 | K77: 0 | L77: 0 | V77: =SUM(I77:M77) -> 0 | AC77: 1969119 | AK77: =SUM(X77:AB77) -> 0
C78: Logisis | D78: Soporte Operativo | E78: 5216 | F78: CRM Contact Center (15 Licencias) | G78: Cost of sales | I78: 2593614 | J78: 2128813 | K78: 2180494 | L78: 2180494 | M78: 2278935.4 | V78: =SUM(I78:M78) -> 11362350 | X78: 2620730 | Y78: 2660040.9 | Z78: 2699941.6 | AA78: 2740440.7 | AB78: 2781547.3 | AC78: 2823270.5 | AD78: 2865619.6 | AE78: 2908603.9 | AF78: 2952232.9 | AG78: 2996516.4 | AH78: 3041464.2 | AI78: 3087086.1 | AK78: =SUM(X78:AB78) -> 13502700
C79: Bapro | D79: Soporte Operativo | E79: 5212 | F79: Call Center Presentac Digitales | G79: Cost of sales | I79: 0 | J79: 0 | K79: 0 | L79: 0 | V79: =SUM(I79:M79) -> 0 | AA79: 3333000 | AB79: 3366330 | AC79: 3399993.3 | AD79: 3433993.2 | AE79: 3468333.2 | AF79: 3503016.5 | AG79: 3538046.7 | AH79: 3573427.1 | AI79: 3609161.4 | AK79: =SUM(X79:AB79) -> 6699330
V80: =SUM(I80:M80) -> 0
D81: Proyectos | I81: =SUM(I82:I86) -> 28501696 | J81: =SUM(J82:J86) -> 22597866 | K81: =SUM(K82:K86) -> 29327200 | L81: =SUM(L82:L86) -> 31280749 | M81: =SUM(M82:M86) -> 32015361 | N81: =SUM(N82:N86) -> 0 | O81: =SUM(O82:O86) -> 0 | P81: =SUM(P82:P86) -> 0 | ... T81: =SUM(T82:T86) -> 0 | V81: =SUM(I81:M81) -> 1.4372287e+08 | W81: =+V81/$V$171 -> 0.03546374 | X81: 28660712 | Y81: 28350657 | Z81: 28091577 | AA81: 27972996 | AB81: 27803771 | AC81: 27674450 | AD81: 27679834 | AE81: 27621091 | AF81: 27593875 | AG81: 27698199 | AH81: 27726958 | AI81: 27780912 | AK81: =SUM(X81:AB81) -> 1.4087971e+08 | AM81: =+V81-AK81 -> 2843159.6 | AN81: =+AM81/AK81 -> 0.020181469
C82: Avanter | D82: Astra-Sidus-Panalab-Biu | E82: 5216 | F82: Servicio CRM | G82: Cost of sales | I82: 11254627 | J82: 11947646 | K82: 12370016 | L82: 15338340 | M82: 15954805 | V82: =SUM(I82:M82) -> 66865434 | X82: 12519125 | Y82: 12695122 | Z82: 12874219 | AA82: 13150026 | AB82: 13335125 | AC82: 13523473 | AD82: 13812979 | AE82: 14007654 | AF82: 14205747 | AG82: 14509639 | AH82: 14714389 | AI82: 14922735 | AK82: =SUM(X82:AB82) -> 64573617
C83: Indicom | D83: Astrazenaca | E83: 5212 | F83: Call Center | G83: Cost of sales | I83: 6282208 | J83: 6282208 | K83: 6282208 | L83: 6461852.2 | M83: 6551585.3 | V83: =SUM(I83:M83) -> 31860061 | X83: 6042030.1 | Y83: 6102450.4 | Z83: 6163474.9 | AA83: 6225109.6 | AB83: 6287360.7 | AC83: 6350234.3 | AD83: 6413736.7 | AE83: 6477874 | AF83: 6542652.8 | AG83: 6608079.3 | AH83: 6674160.1 | AI83: 6740901.7 | AK83: =SUM(X83:AB83) -> 30820426
C84: Swhouse y Farmacias | D84: Iqvia | E84: 5218 | F84: Serv de capt y envio de Trx | G84: Cost of sales | I84: 4671375.8 | J84: 4285762 | K84: 3952439 | L84: 3786691.2 | M84: 4100692.1 | V84: =SUM(I84:M84) -> 20796960 | X84: 3781956.3 | Y84: 3781956.3 | Z84: 3781956.3 | AA84: 3781956.3 | AB84: 3781956.3 | AC84: 3781956.3 | AD84: 3781956.3 | AE84: 3781956.3 | AF84: 3781956.3 | AG84: 3781956.3 | AH84: 3781956.3 | AI84: 3781956.3 | AK84: =SUM(X84:AB84) -> 18909782
C85: Serdata | D85: Panalab | E85: 5219 | F85: Proc de Bonos Manuales | G85: Cost of sales | I85: 6293485.2 | J85: 82250 | K85: 5922537 | L85: 6012295.9 | M85: 5408278.6 | V85: =SUM(I85:M85) -> 23718847 | X85: 6317601.2 | Y85: 5771128.7 | Z85: 5271926 | AA85: 4815904.4 | AB85: 4399328.7 | AC85: 4018786.8 | AD85: 3671161.7 | AE85: 3353606.2 | AF85: 3063519.3 | AG85: 2798524.9 | AH85: 2556452.5 | AI85: 2335319.3 | AK85: =SUM(X85:AB85) -> 26575889
C86: Ageri | D86: Proyectos | F86: Desarrollo Token | G86: Cost of sales | K86: 800000 | L86: -318430 | V86: =SUM(I86:M86) -> 481570
D87: BZ | I87: =SUM(I88:I91) -> 1.197664e+08 | J87: =SUM(J88:J91) -> 119446680 | K87: =SUM(K88:K91) -> 119031843 | L87: =SUM(L88:L91) -> 1.1967541e+08 | M87: =SUM(M88:M91) -> 1.3460349e+08 | N87: =SUM(N88:N91) -> 0 | O87: =SUM(O88:O91) -> 0 | P87: =SUM(P88:P91) -> 0 | ... T87: =SUM(T88:T91) -> 0 | V87: =SUM(I87:M87) -> 6.1252382e+08 | W87: =+V87/$V$171 -> 0.15114077 | X87: 129818996 | Y87: 130430800 | Z87: 131053618 | AA87: 135563861 | AB87: 136284563 | AC87: 137593783 | AD87: 142332695 | AE87: 143013623 | AF87: 144879424 | AG87: 150390229 | AH87: 151594835 | AI87: 154029715 | AK87: =SUM(X87:AB87) -> 663151838 | AM87: =+V87-AK87 -> -50628018 | AN87: =+AM87/AK87 -> -0.076344534
C88: Bizland TSA Original | D88: BZ | E88: 5213 | F88: Manten y Soporte Plataforma | G88: Cost of sales | I88: 1.0593618e+08 | J88: 105616454 | K88: 105201617 | L88: 1.056451e+08 | M88: 1.2040707e+08 | V88: =SUM(I88:M88) -> 5.4280642e+08 | X88: 111560838 | Y88: 112172642 | Z88: 112795460 | AA88: 117305703 | AB88: 117951144 | AC88: 118608202 | AD88: 123347114 | AE88: 124028040 | AF88: 124721222 | AG88: 129700409 | AH88: 130418770 | AI88: 131150062 | AK88: =SUM(X88:AB88) -> 571785787
C89: Bizland TSA Deveng 2025 | D89: BZ | E89: 5213 | F89: Deveng One Shots 2025 | G89: Cost of sales | I89: 13830226 | J89: 13830226 | K89: 13830226 | L89: 13830226 | M89: 13658850 | V89: =SUM(I89:M89) -> 68979754 | X89: 13587912 | Y89: 13587912 | Z89: 13587912 | AA89: 13587912 | AB89: 13416538 | AC89: 12237692 | AD89: 12237692 | AE89: 12237694 | AF89: 9077549 | AG89: 7276382 | AH89: 5937379 | AI89: 0 | AK89: =SUM(X89:AB89) -> 67768186
C90: Bizland TSA Deveng 2026 | D90: BZ | E90: 5213 | F90: Deveng One Shots 2026 | G90: Cost of sales | I90: 0 | J90: 0 | K90: 0 | L90: 200077.89 | M90: 537571 | V90: =SUM(I90:M90) -> 737648.89 | X90: 4670246 | Y90: 4670246 | Z90: 4670246 | AA90: 4670246 | AB90: 4916881 | AC90: 6747889 | AD90: 6747889 | AE90: 6747889 | AF90: 11080653 | AG90: 13413438 | AH90: 15238686 | AI90: 22879653 | AK90: =SUM(X90:AB90) -> 23597865
V91: =SUM(I91:M91) -> 0
D93: Admin, Legales y Otros | I93: =SUM(I94:I104) -> 7371400 | J93: =SUM(J94:J104) -> 6523900 | K93: =SUM(K94:K104) -> 7686202 | L93: =SUM(L94:L102) -> 6978700 | M93: =SUM(M94:M102) -> 7382475 | N93: =SUM(N94:N102) -> 0 | O93: =SUM(O94:O102) -> 0 | P93: =SUM(P94:P102) -> 0 | Q93: =SUM(Q94:Q102) -> 0 | R93: =SUM(R94:R102) -> 0 | S93: =SUM(S94:S102) -> 0 | T93: =SUM(T94:T102) -> 0 | V93: =SUM(I93:M93) -> 35942677 | W93: =+V93/$V$171 -> 0.0088688858 | X93: 6703681 | Y93: 6508219.1 | Z93: 6812825.2 | AA93: 7009894.3 | AB93: 6805504 | AC93: 6810320.5 | AD93: 7330094.9 | AE93: 10643344 | AF93: 7679018.7 | AG93: 7664921.7 | AH93: 7441432.5 | AI93: 7446699.1 | AK93: =SUM(X93:AB93) -> 33840124 | AM93: =+V93-AK93 -> 2102553.5 | AN93: =+AM93/AK93 -> 0.062131967
C94: La Meridional Seguros | D94: Legales | E94: 5420 | F94: Seguro Directores y Apoderados | G94: Professional Fees | K94: 188902 | V94: =SUM(I94:M94) -> 188902 | AE94: 3526976.1 | AK94: =SUM(X94:AB94) -> 0
C95: Estudio Contable | D95: Administrativos | E95: 5415 | F95: Servicios Profesionales | G95: Professional Fees | I95: 6048000 | J95: 6048000 | K95: 7028000 | L95: 6620000 | M95: 6620000 | V95: =SUM(I95:M95) -> 32364000 | X95: 5960243.5 | Y95: 5960243.5 | Z95: 5960243.5 | AA95: 6232497.8 | AB95: 6232497.8 | AC95: 6232497.8 | AD95: 6517188.1 | AE95: 6517188.1 | AF95: 6517188.1 | AG95: 6814882.7 | AH95: 6814882.7 | AI95: 6814882.7 | AK95: =SUM(X95:AB95) -> 30345726
C96: Estudio Legal | D96: Legales | E96: 5415 | F96: Servicios Profesionales | G96: Professional Fees | I96: 450000 | J96: 200000 | K96: 200000 | L96: 90000 | V96: =SUM(I96:M96) -> 940000 | X96: 300000 | Y96: 304500 | Z96: 309067.5 | AA96: 313703.51 | AB96: 318409.07 | AC96: 323185.2 | AD96: 328032.98 | AE96: 332953.47 | AF96: 337947.78 | AG96: 343016.99 | AH96: 348162.25 | AI96: 353384.68 | AK96: =SUM(X96:AB96) -> 1545680.1
C97: Colppy | D97: Administrativos | E97: 5415 | F97: Sistema de Gestión Contable | G97: Professional Fees | I97: 240900 | J97: 240900 | K97: 257900 | L97: 257900 | M97: 257900 | V97: =SUM(I97:M97) -> 1255500 | X97: 240900 | Y97: 240900 | Z97: 240900 | AA97: 251903.92 | AB97: 251903.92 | AC97: 251903.92 | AD97: 263410.48 | AE97: 263410.48 | AF97: 263410.48 | AG97: 275442.65 | AH97: 275442.65 | AI97: 275442.65 | AK97: =SUM(X97:AB97) -> 1226507.8
C98: Escribania Barcia/Arronda | D98: Legales | E98: 5415 | F98: Servicios Profesionales | G98: Professional Fees | M98: 474575 | V98: =SUM(I98:M98) -> 474575 | X98: 200000 | AA98: 209135.67 | AD98: 218688.65 | AG98: 228678 | AK98: =SUM(X98:AB98) -> 409135.67
C99: a definir | D99: Administrativos | E99: 5418 | F99: Copiado libros contables | G99: Professional Fees | V99: =SUM(I99:M99) -> 0 | Z99: 300000 | AK99: =SUM(X99:AB99) -> 300000
C100: DocuSign | D100: Legales | F100: Suscripción firma digital | G100: Professional Fees | V100: =SUM(I100:M100) -> 0 | AF100: 557613.83 | AK100: =SUM(X100:AB100) -> 0
C101: LSD | D101: Administrativos | F101: Libros Sueldos Digital | G101: Other taxes | I101: 24000 | J101: 12000 | K101: 11400 | L101: 10800 | M101: 30000 | V101: =SUM(I101:M101) -> 88200 | X101: 2537.5 | Y101: 2575.5625 | Z101: 2614.1959 | AA101: 2653.4089 | AB101: 2693.21 | AC101: 2733.6082 | AD101: 2774.6123 | AE101: 2816.2315 | AF101: 2858.4749 | AG101: 2901.3521 | AH101: 2944.8723 | AI101: 2989.0454 | AK101: =SUM(X101:AB101) -> 13073.877
C102: Fragulia Cristina | D102: Administrativos | F102: Tramite Habilitación Municipalidad Vte Lopez | G102: Professional Fees | I102: 600000 | V102: =SUM(I102:M102) -> 600000 | AK102: =SUM(X102:AB102) -> 0
...

Sheet Trazabilidad
A1: TRAZABILIDAD — GOLD ECONÓMICO 2026 (Ene-Abr)
A2: Ingresá la fila y el mes para filtrar los movimientos del Mayor
A3: Fila Gold → | D3: Mes → | E3: Abr
A4: Concepto: | B4: {=IFERROR(INDEX('REAL-BDGT2026'!C:C,B3),"")} -> 0 | D4: Valor Gold: | E4: =IFERROR(IF(E3="Ene",INDEX('REAL-BDGT2026'!I:I,B3),IF(E3="Feb",INDEX('REAL-BDGT2026'!J:J,B3),IF(E3="Mar",INDEX('REAL-BDGT2026'!K:K,B3),IF(E3="Abr",INDEX('REAL-BDGT2026'!L:L,B3),IF(E3="May",INDEX('REAL-BDGT2026'!M:M,B3),""))))),"") -> Abr-26
B5: 0 | E5: REAL
A6: Mes | B6: 0 | C6: Concepto Gold | D6: Cód | F6: Detalle | G6: Débito | H6: Crédito | I6: Neto Mayor | J6: Valor Gold | K6: Diferencia
A7: Ene | B7: 8 | C7: Farmalink On Line Prepagas | D7: 5111 | E7: Farmalink S.A. | F7: Servicio Basico Online PREPAGAS - Noviembre 2025 | G7: 0 | H7: 2.3328759e+08 | I7: -2.3328759e+08
A8: Ene | B8: 8 | C8: Farmalink On Line Prepagas | D8: 5111 | F8: Disolución Previsión dic25 FLK Prepagas On Line | G8: 256042440 | H8: 0 | I8: 256042440
A9: Ene | B9: 8 | C9: Farmalink On Line Prepagas | D9: 5111 | F9: Disolución Previsión nov25 FLK Prepagas On Line | G9: 2.3328759e+08 | H9: 0 | I9: 2.3328759e+08
A10: Ene | B10: 8 | C10: Farmalink On Line Prepagas | D10: 5111 | F10: Constitución Previsión dic25 FLK Prepagas On Line | G10: 0 | H10: 2.5665427e+08 | I10: -2.5665427e+08
A11: Ene | B11: 8 | C11: Farmalink On Line Prepagas | D11: 5111 | F11: Constitución Previsión ene26 FLK Prepagas On Line | G11: 0 | H11: 2.542103e+08 | I11: -2.542103e+08
A12: Ene | B12: 8 | C12: Farmalink On Line Prepagas | D12: TOTAL | F12: Neto Mayor vs Valor Gold | G12: 4.8933003e+08 | H12: 7.4415217e+08 | I12: -2.5482214e+08 | J12: 2.5482214e+08 | K12: 0
A13: Ene | B13: 9 | C13: Farmalink On Line Apross | D13: 5111 | E13: Farmalink S.A. | F13: Servicio Basico Online APROSS - Noviembre 2025 | G13: 0 | H13: 30637826 | I13: -30637826
A14: Ene | B14: 9 | C14: Farmalink On Line Apross | D14: 5111 | F14: Disolución Previsión nov25 FLK Apross On Line | G14: 30637826 | H14: 0 | I14: 30637826
A15: Ene | B15: 9 | C15: Farmalink On Line Apross | D15: 5111 | F15: Disolución Previsión dic25 FLK Apross On Line | G15: 30875706 | H15: 0 | I15: 30875706
A16: Ene | B16: 9 | C16: Farmalink On Line Apross | D16: 5111 | F16: Constitución Previsión dic25 FLK Apross On Line | G16: 0 | H16: 34381801 | I16: -34381801
A17: Ene | B17: 9 | C17: Farmalink On Line Apross | D17: 5111 | F17: Constitución Previsión ene26 FLK Apross On Line | G17: 0 | H17: 30813370 | I17: -30813370
A18: Ene | B18: 9 | C18: Farmalink On Line Apross | D18: TOTAL | F18: Neto Mayor vs Valor Gold | G18: 61513532 | H18: 95832997 | I18: -34319465 | J18: 34319465 | K18: 0
A19: Ene | B19: 10 | C19: Farmalink On Line IOMA | D19: 5111 | E19: Farmalink S.A. | F19: Servicio Basico Online IOMA - Noviembre 2025 | G19: 0 | H19: 1.2962802e+08 | I19: -1.2962802e+08
A20: Ene | B20: 10 | C20: Farmalink On Line IOMA | D20: 5111 | F20: Disolución Previsión nov25 FLK IOMA On Line | G20: 1.2962802e+08 | H20: 0 | I20: 1.2962802e+08
A21: Ene | B21: 10 | C21: Farmalink On Line IOMA | D21: 5111 | F21: Disolución Previsión dic25 FLK IOMA On Line | G21: 140576859 | H21: 0 | I21: 140576859
A22: Ene | B22: 10 | C22: Farmalink On Line IOMA | D22: 5111 | F22: Constitución Previsión dic25 FLK IOMA On Line | G22: 0 | H22: 1.4355489e+08 | I22: -1.4355489e+08
A23: Ene | B23: 10 | C23: Farmalink On Line IOMA | D23: 5111 | F23: Constitución Previsión ene26 FLK IOMA On Line | G23: 0 | H23: 126347606 | I23: -126347606
A24: Ene | B24: 10 | C24: Farmalink On Line IOMA | D24: TOTAL | F24: Neto Mayor vs Valor Gold | G24: 2.7020488e+08 | H24: 3.9953052e+08 | I24: -1.2932564e+08 | J24: 1.2932564e+08 | K24: 0
A25: Ene | B25: 11 | C25: Farmalink Receta Electronica Prepagas | D25: 5111 | E25: Farmalink S.A. | F25: Servicio Basico Online - RECETA ELECTRONICA - PREPAGAS - Noviembre 2025 | G25: 0 | H25: 12858929 | I25: -12858929
A26: Ene | B26: 11 | C26: Farmalink Receta Electronica Prepagas | D26: 5111 | F26: Disolución Previsión dic25 FLK Prepagas Receta Electronica On Line | G26: 12648510 | H26: 0 | I26: 12648510
A27: Ene | B27: 11 | C27: Farmalink Receta Electronica Prepagas | D27: 5111 | F27: Disolución Previsión nov25 FLK Prepagas Receta Electronica On Line | G27: 12858929 | H27: 0 | I27: 12858929
A28: Ene | B28: 11 | C28: Farmalink Receta Electronica Prepagas | D28: 5111 | F28: Constitución Previsión dic25 FLK Prepagas Receta Electronica On Line | G28: 0 | H28: 14422466 | I28: -14422466
A29: Ene | B29: 11 | C29: Farmalink Receta Electronica Prepagas | D29: 5111 | F29: Constitución Previsión ene26 FLK Prepagas Receta Electronica On Line | G29: 0 | H29: 10049942 | I29: -10049942
A30: Ene | B30: 11 | C30: Farmalink Receta Electronica Prepagas | D30: TOTAL | F30: Neto Mayor vs Valor Gold | G30: 25507439 | H30: 37331336 | I30: -11823897 | J30: 11823897 | K30: -0.0063000005
A31: Ene | B31: 12 | C31: Farmalink Receta Electronica Apross | D31: 5111 | E31: Farmalink S.A. | F31: Servicio Basico Online - RECETA ELECTRONICA - APROSS - Noviembre 2025 | G31: 0 | H31: 2450645.9 | I31: -2450645.9
A32: Ene | B32: 12 | C32: Farmalink Receta Electronica Apross | D32: 5111 | F32: Disolución Previsión nov25 FLK Apross Receta Electronica On Line | G32: 2450645.9 | H32: 0 | I32: 2450645.9
A33: Ene | B33: 12 | C33: Farmalink Receta Electronica Apross | D33: 5111 | F33: Disolución Previsión dic25 FLK Apross Receta Electronica On Line | G33: 2409240 | H33: 0 | I33: 2409240
A34: Ene | B34: 12 | C34: Farmalink Receta Electronica Apross | D34: 5111 | F34: Constitución Previsión dic25 FLK Apross Receta Electronica On Line | G34: 0 | H34: 2750304.9 | I34: -2750304.9
A35: Ene | B35: 12 | C35: Farmalink Receta Electronica Apross | D35: 5111 | F35: Constitución Previsión ene26 FLK Apross Receta Electronica On Line | G35: 0 | H35: 2632678.3 | I35: -2632678.3
A36: Ene | B36: 12 | C36: Farmalink Receta Electronica Apross | D36: TOTAL | F36: Neto Mayor vs Valor Gold | G36: 4859885.9 | H36: 7833629 | I36: -2973743.1 | J36: 2973743.1 | K36: -0.0055
A37: Ene | B37: 13 | C37: Farmalink Receta Electronica IOMA | D37: 5111 | E37: Farmalink S.A. | F37: Servicio Basico Online - RECETA ELECTRONICA - IOMA - Noviembre 2025 | G37: 0 | H37: 4122534 | I37: -4122534
A38: Ene | B38: 13 | C38: Farmalink Receta Electronica IOMA | D38: 5111 | F38: Disolución Previsión nov25 FLK IOMA Receta Electronica On Line | G38: 4122534 | H38: 0 | I38: 4122534
A39: Ene | B39: 13 | C39: Farmalink Receta Electronica IOMA | D39: 5111 | F39: Disolución Previsión dic25 FLK IOMA Receta Electronica On Line | G39: 3901500 | H39: 0 | I39: 3901500
A40: Ene | B40: 13 | C40: Farmalink Receta Electronica IOMA | D40: 5111 | F40: Constitución Previsión dic25 FLK IOMA Receta Electronica On Line | G40: 0 | H40: 4722130.2 | I40: -4722130.2
A41: Ene | B41: 13 | C41: Farmalink Receta Electronica IOMA | D41: 5111 | F41: Constitución Previsión ene26 FLK IOMA Receta Electronica On Line | G41: 0 | H41: 2932439.7 | I41: -2932439.7
A42: Ene | B42: 13 | C42: Farmalink Receta Electronica IOMA | D42: TOTAL | F42: Neto Mayor vs Valor Gold | G42: 8024034 | H42: 11777104 | I42: -3753069.9 | J42: 3753069.9 | K42: -0.0070999996
A43: Ene | B43: 14 | C43: Farmalink On Line PAMI | D43: 5111 | E43: Farmalink S.A. | F43: Servicio Básico On Line - PAMI - Noviembre 2025 | G43: 0 | H43: 1268396661 | I43: -1268396661
A44: Ene | B44: 14 | C44: Farmalink On Line PAMI | D44: 5111 | F44: Disolución Previsión dic25 FLK PAMI On Line | G44: 1389546000 | H44: 0 | I44: 1389546000
A45: Ene | B45: 14 | C45: Farmalink On Line PAMI | D45: 5111 | F45: Disolución Previsión nov25 FLK PAMI On Line | G45: 1268396661 | H45: 0 | I45: 1268396661
A46: Ene | B46: 14 | C46: Farmalink On Line PAMI | D46: 5111 | F46: Constitución Previsión dic25 FLK PAMI On Line | G46: 0 | H46: 1.4049919e+09 | I46: -1.4049919e+09
A47: Ene | B47: 14 | C47: Farmalink On Line PAMI | D47: 5111 | F47: Constitución Previsión ene26 FLK PAMI On Line | G47: 0 | H47: 1396060029 | I47: -1396060029
A48: Ene | B48: 14 | C48: Farmalink On Line PAMI | D48: TOTAL | F48: Neto Mayor vs Valor Gold | G48: 2657942661 | H48: 4.0694486e+09 | I48: -1.4115059e+09 | J48: 1.4115059e+09 | K48: 0
A49: Ene | B49: 15 | C49: Farmalink On Line PAMI Imposiciones | D49: 5111 | E49: Farmalink S.A. | F49: Servicio Básico On Line - PAMI Imposiciones - Noviembre 2025 | G49: 0 | H49: 37492525 | I49: -37492525
A50: Ene | B50: 15 | C50: Farmalink On Line PAMI Imposiciones | D50: 5111 | F50: Disolución Previsión nov25 FLK PAMI Imposiciones On Line | G50: 37492525 | H50: 0 | I50: 37492525
A51: Ene | B51: 15 | C51: Farmalink On Line PAMI Imposiciones | D51: 5111 | F51: Disolución Previsión dic25 FLK PAMI Imposiciones On Line | G51: 37791000 | H51: 0 | I51: 37791000
A52: Ene | B52: 15 | C52: Farmalink On Line PAMI Imposiciones | D52: 5111 | F52: Constitución Previsión dic25 FLK PAMI Imposiciones On Line | G52: 0 | H52: 41086644 | I52: -41086644
A53: Ene | B53: 15 | C53: Farmalink On Line PAMI Imposiciones | D53: 5111 | F53: Constitución Previsión ene26 FLK PAMI Imposiciones On Line | G53: 0 | H53: 38671500 | I53: -38671500
A54: Ene | B54: 15 | C54: Farmalink On Line PAMI Imposiciones | D54: TOTAL | F54: Neto Mayor vs Valor Gold | G54: 75283525 | H54: 1.1725067e+08 | I54: -41967144 | J54: 41967144 | K54: 0
A55: Ene | B55: 17 | C55: Provincia A.R.T. S.A. | D55: 5111 | E55: Provincia A.R.T. S.A. | F55: Servicio de Validación en Linea - Diciembre 2025 OC 22420 | G55: 0 | H55: 1215432.5 | I55: -1215432.5
A56: Ene | B56: 17 | C56: Provincia A.R.T. S.A. | D56: 5111 | F56: Disolución Previsión dic25 Pcia ART | G56: 1000000 | H56: 0 | I56: 1000000
A57: Ene | B57: 17 | C57: Provincia A.R.T. S.A. | D57: 5111 | F57: Constitución Previsión ene26 Pcia ART | G57: 0 | H57: 1000000 | I57: -1000000
A58: Ene | B58: 17 | C58: Provincia A.R.T. S.A. | D58: TOTAL | F58: Neto Mayor vs Valor Gold | G58: 1000000 | H58: 2215432.5 | I58: -1215432.5 | J58: 1215432.5 | K58: 0
A59: Ene | B59: 21 | C59: Astrazeneca S.A. | D59: 5111 | E59: Astrazeneca S.A. | F59: Programa Elegir Salud - Diciembre 2025 OC 4550042040 PRID KQCV952 | G59: 0 | H59: 21166717 | I59: -21166717
A60: Ene | B60: 21 | C60: Astrazeneca S.A. | D60: 5111 | F60: Disolución Previsión dic25 Astrazeneca | G60: 20000000 | H60: 0 | I60: 20000000
A61: Ene | B61: 21 | C61: Astrazeneca S.A. | D61: 5111 | F61: Constitución Previsión ene26 Astrazeneca | G61: 0 | H61: 21000000 | I61: -21000000
A62: Ene | B62: 21 | C62: Astrazeneca S.A. | D62: TOTAL | F62: Neto Mayor vs Valor Gold | G62: 20000000 | H62: 42166717 | I62: -22166717 | J62: 22166717 | K62: 0
A63: Ene | B63: 22 | C63: Avanter S.R.L | D63: 5111 | E63: Avanter S.R.L | F63: Servicio Transaccional Bonos Diciembre 2025 | G63: 0 | H63: 10901569 | I63: -10901569
A64: Ene | B64: 22 | C64: Avanter S.R.L | D64: 5111 | E64: Avanter S.R.L | F64: Servicio Transaccional Dinámicas Diciembre 2025 | G64: 0 | H64: 33506155 | I64: -33506155
A65: Ene | B65: 22 | C65: Avanter S.R.L | D65: 5111 | E65: Avanter S.R.L | F65: Serv Progr de Pacientes Diciembre 2025 | G65: 0 | H65: 2722403.8 | I65: -2722403.8
A66: Ene | B66: 22 | C66: Avanter S.R.L | D66: 5111 | F66: Disolución Previsión dic25 Avanter | G66: 45000000 | H66: 0 | I66: 45000000
A67: Ene | B67: 22 | C67: Avanter S.R.L | D67: 5111 | F67: Constitución Previsión ene26 Avanter | G67: 0 | H67: 60000000 | I67: -60000000
A68: Ene | B68: 22 | C68: Avanter S.R.L | D68: TOTAL | F68: Neto Mayor vs Valor Gold | G68: 45000000 | H68: 1.0713013e+08 | I68: -62130128 | J68: 62130128 | K68: 0
A69: Ene | B69: 24 | C69: Bayer Argentina S.A. | D69: 5111 | E69: Bayer Argentina S.A. | F69: Programa Mas Simple Bayer - Diciembre 2025 - Pedido 750536559 | G69: 0 | H69: 987716.02 | I69: -987716.02
A70: Ene | B70: 24 | C70: Bayer Argentina S.A. | D70: 5111 | F70: Disolución Previsión dic25 Bayer Argentina S.A. | G70: 987000 | H70: 0 | I70: 987000
A71: Ene | B71: 24 | C71: Bayer Argentina S.A. | D71: 5111 | F71: Constitución Previsión ene26 Bayer Argentina S.A. | G71: 0 | H71: 987000 | I71: -987000
A72: Ene | B72: 24 | C72: Bayer Argentina S.A. | D72: TOTAL | F72: Neto Mayor vs Valor Gold | G72: 987000 | H72: 1974716 | I72: -987716.02 | J72: 987716.02 | K72: 0
A73: Ene | B73: 25 | C73: Ceoderma S.A. | D73: 5111 | E73: Ceoderma S.A. | F73: Servicio trx de acciones comerciales en farmacias Diciembre 2025 | G73: 0 | H73: 567084.6 | I73: -567084.6
A74: Ene | B74: 25 | C74: Ceoderma S.A. | D74: 5111 | F74: Disolución Previsión dic25 Ceoderma S.A. (Dermacare S.A) | G74: 567000 | H74: 0 | I74: 567000
A75: Ene | B75: 25 | C75: Ceoderma S.A. | D75: 5111 | F75: Constitución Previsión ene26 Ceoderma S.A. (Dermacare S.A) | G75: 0 | H75: 567000 | I75: -567000
A76: Ene | B76: 25 | C76: Ceoderma S.A. | D76: TOTAL | F76: Neto Mayor vs Valor Gold | G76: 567000 | H76: 1134084.6 | I76: -567084.6 | J76: 567084.6 | K76: 0
A77: Ene | B77: 27 | C77: Max Vision | D77: 5111 | E77: Max Vision SRL | F77: Servicio de Validación en linea de Bonos - Diciembre 2025 | G77: 0 | H77: 1170304.5 | I77: -1170304.5
A78: Ene | B78: 27 | C78: Max Vision | D78: 5111 | F78: Disolución Previsión dic25 Max Vision SRL | G78: 1000000 | H78: 0 | I78: 1000000
A79: Ene | B79: 27 | C79: Max Vision | D79: 5111 | F79: Constitución Previsión ene26 Max Vision SRL | G79: 0 | H79: 1000000 | I79: -1000000
A80: Ene | B80: 27 | C80: Max Vision | D80: TOTAL | F80: Neto Mayor vs Valor Gold | G80: 1000000 | H80: 2170304.5 | I80: -1170304.5 | J80: 1170304.5 | K80: 0
A81: Ene | B81: 28 | C81: Panalab Argentina S.A. | D81: 5111 | E81: Panalab Argentina S.A. | F81: Serv de Proc de Bonos de Descuento Manual - Diciembre 2025 OC 18719 | G81: 0 | H81: 11044183 | I81: -11044183
A82: Ene | B82: 28 | C82: Panalab Argentina S.A. | D82: TOTAL | F82: Neto Mayor vs Valor Gold | G82: 0 | H82: 11044183 | I82: -11044183 | J82: 11044183 | K82: 0
A83: Ene | B83: 29 | C83: Panalab Argentina S.A. | D83: 5111 | E83: Panalab Argentina S.A. | F83: Serv de Generac y Autoriz de Dispensa de Bonos Digitales - Diciembre 2025 OC 18719 | G83: 0 | H83: 26012630 | I83: -26012630
A84: Ene | B84: 29 | C84: Panalab Argentina S.A. | D84: 5111 | F84: Disolución Previsión dic25 Panalab | G84: 30000000 | H84: 0 | I84: 30000000
A85: Ene | B85: 29 | C85: Panalab Argentina S.A. | D85: 5111 | F85: Constitución Previsión ene26 Panalab | G85: 0 | H85: 30000000 | I85: -30000000
A86: Ene | B86: 29 | C86: Panalab Argentina S.A. | D86: TOTAL | F86: Neto Mayor vs Valor Gold | G86: 30000000 | H86: 56012630 | I86: -26012630 | J86: 26012630 | K86: 0
A87: Ene | B87: 30 | C87: Sidus Dermocosmética S.A | D87: 5111 | E87: Sidus Dermocosmética S.A | F87: Servicio de Validación de TRX - Diciembre 2025 OC 34193 | G87: 0 | H87: 2732192.8 | I87: -2732192.8
A88: Ene | B88: 30 | C88: Sidus Dermocosmética S.A | D88: 5111 | F88: Disolución Previsión dic25 Sidus Dermocosmetica | G88: 2300000 | H88: 0 | I88: 2300000
A89: Ene | B89: 30 | C89: Sidus Dermocosmética S.A | D89: 5111 | F89: Constitución Previsión ene26 Sidus Dermocosmetica | G89: 0 | H89: 2300000 | I89: -2300000
A90: Ene | B90: 30 | C90: Sidus Dermocosmética S.A | D90: TOTAL | F90: Neto Mayor vs Valor Gold | G90: 2300000 | H90: 5032192.8 | I90: -2732192.8 | J90: 2732192.8 | K90: 0
A91: Ene | B91: 31 | C91: Sidus S.A. | D91: 5111 | E91: Sidus S.A. | F91: Servicio de Validación en linea de Bonos Programa Convida Diciembre 2025 | G91: 0 | H91: 766721.67 | I91: -766721.67
A92: Ene | B92: 31 | C92: Sidus S.A. | D92: 5111 | F92: Disolución Previsión dic25 Sidus S.A. | G92: 300000 | H92: 0 | I92: 300000
A93: Ene | B93: 31 | C93: Sidus S.A. | D93: 5111 | F93: Constitución Previsión ene26 Sidus S.A. | G93: 0 | H93: 766722 | I93: -766722
A94: Ene | B94: 31 | C94: Sidus S.A. | D94: TOTAL | F94: Neto Mayor vs Valor Gold | G94: 300000 | H94: 1533443.7 | I94: -1233443.7 | J94: 1233443.7 | K94: 0
A95: Ene | B95: 32 | C95: Unyc S.A. | D95: 5111 | E95: Unyc S. A. | F95: Biu Cosmeceuticals Bonos - Diciembre 2025 | G95: 0 | H95: 7990.89 | I95: -7990.89
A96: Ene | B96: 32 | C96: Unyc S.A. | D96: 5111 | F96: Disolución Previsión dic25 Unyc S. A. | G96: 10000 | H96: 0 | I96: 10000
A97: Ene | B97: 32 | C97: Unyc S.A. | D97: 5111 | F97: Constitución Previsión ene26 Unyc S. A. | G97: 0 | H97: 10000 | I97: -10000
A98: Ene | B98: 32 | C98: Unyc S.A. | D98: TOTAL | F98: Neto Mayor vs Valor Gold | G98: 10000 | H98: 17990.89 | I98: -7990.89 | J98: 7990.89 | K98: 0
A99: Ene | B99: 33 | C99: HEALTHCARE MARKETING GROUP S | D99: 5111 | E99: HEALTHCARE MARKETING GROUP S | F99: Validación On Line Bonos Digitales - Diciembre 2025 | G99: 0 | H99: 371875.5 | I99: -371875.5
A100: Ene | B100: 33 | C100: HEALTHCARE MARKETING GROUP S | D100: 5111 | F100: Disolución Previsión dic25 Healthcare Marketing Group S.A. | G100: 345000 | H100: 0 | I100: 345000
...

Sheet Premisas
C2: (al 30/09/25) | I2: (al 30/09/25)
A4: Ventas | B4: Budget | C4: RFC | D4: % de | E4: inflación | F4: crecimiento | H4: Ventas | I4: RFC | J4: Budget | K4: % de | L4: inflación
A5: (sin incidencia IIBB) | B5: FY 2026 | C5: FY 2025 | D5: crecimiento | E5: estimada 2026 | F5: neto | H5: (sin incidencia IIBB) | I5: FY 2025 | J5: FY 2025 | K5: crecimiento | L5: proyectada 2025
A6: Farmacias | B6: =+'REAL-BDGT2026'!V7 -> 9.934015e+09 | C6: =+'REAL-BDGT2026'!#REF! -> #REF! | D6: =+B6/C6-1 -> #REF! | E6: 0.1956 | F6: =(+D6-$E$6) -> #REF! | H6: Farmacias | I6: =+C6 -> #REF! | J6: =+'REAL-BDGT2026'!#REF! -> #REF! | K6: =+I6/J6-1 -> #REF! | L6: 0.2982
A7: Laboratorios | B7: =+'REAL-BDGT2026'!V20 -> 6.9600062e+08 | C7: =+'REAL-BDGT2026'!#REF! -> #REF! | D7: =+B7/C7-1 -> #REF! | F7: =(+D7-$E$6) -> #REF! | H7: Laboratorios | I7: =+C7 -> #REF! | J7: =+'REAL-BDGT2026'!#REF! -> #REF! | K7: =+I7/J7-1 -> #REF!
A8: Medicina | B8: =+'REAL-BDGT2026'!V37 -> 62455972 | C8: =+'REAL-BDGT2026'!#REF! -> #REF! | D8: =+B8/C8-1 -> #REF! | F8: =(+D8-$E$6) -> #REF! | H8: Medicina | I8: =+C8 -> #REF! | J8: =+'REAL-BDGT2026'!#REF! -> #REF! | K8: =+I8/J8-1 -> #REF!
A9: Total Ventas | B9: =SUM(B6:B8) -> 1.0692472e+10 | C9: =SUM(C6:C8) -> #REF! | D9: =+B9/C9-1 -> #REF! | F9: =(+D9-$E$6) -> #REF! | H9: Total Ventas | I9: =SUM(I6:I8) -> #REF! | J9: =SUM(J6:J8) -> #REF! | K9: =+I9/J9-1 -> #REF!
A10: Costos | H10: Costos
A11: Desarrollo | B11: =+'REAL-BDGT2026'!V46 -> 1.7553948e+08 | C11: =+'REAL-BDGT2026'!#REF! -> #REF! | D11: =+B11/C11-1 -> #REF! | F11: =(+D11-$E$6) -> #REF! | H11: Desarrollo | I11: =+C11 -> #REF! | J11: =+'REAL-BDGT2026'!#REF! -> #REF! | K11: =+I11/J11-1 -> #REF!
A12: Servicios Plataforma | B12: =+'REAL-BDGT2026'!V58 -> 25116867 | C12: =+'REAL-BDGT2026'!#REF! -> #REF! | D12: =+B12/C12-1 -> #REF! | F12: =(+D12-$E$6) -> #REF! | H12: Servicios Plataforma | I12: =+C12 -> #REF! | J12: =+'REAL-BDGT2026'!#REF! -> #REF! | K12: =+I12/J12-1 -> #REF!
A13: Servidores | B13: =+'REAL-BDGT2026'!V70 -> 26615603 | C13: =+'REAL-BDGT2026'!#REF! -> #REF! | D13: =+B13/C13-1 -> #REF! | F13: =(+D13-$E$6) -> #REF! | H13: Servidores | I13: =+C13 -> #REF! | J13: =+'REAL-BDGT2026'!#REF! -> #REF! | K13: 1
A14: Servicios Plataforma Clouhesive | B14: =+'REAL-BDGT2026'!V73 -> 9867000 | C14: =+'REAL-BDGT2026'!#REF! -> #REF! | D14: =+B14/C14-1 -> #REF! | F14: =(+D14-$E$6) -> #REF! | H14: Servicios Plataforma Clouhesive | I14: =+C14 -> #REF! | J14: =+'REAL-BDGT2026'!#REF! -> #REF! | K14: 1
A15: Soporte Operativo | B15: =+'REAL-BDGT2026'!V75 -> 66742931 | C15: =+'REAL-BDGT2026'!#REF! -> #REF! | D15: =+B15/C15-1 -> #REF! | F15: =(+D15-$E$6) -> #REF! | H15: Soporte Operativo | I15: =+C15 -> #REF! | J15: =+'REAL-BDGT2026'!#REF! -> #REF! | K15: =+I15/J15-1 -> #REF!
A16: Proyectos | B16: =+'REAL-BDGT2026'!V81 -> 1.4372287e+08 | C16: =+'REAL-BDGT2026'!#REF! -> #REF! | D16: =+B16/C16-1 -> #REF! | F16: =(+D16-$E$6) -> #REF! | H16: Proyectos | I16: =+C16 -> #REF! | J16: =+'REAL-BDGT2026'!#REF! -> #REF! | K16: =+I16/J16-1 -> #REF!
A17: BZ | B17: =+'REAL-BDGT2026'!V87 -> 6.1252382e+08 | C17: =+'REAL-BDGT2026'!#REF! -> #REF! | D17: =+B17/C17-1 -> #REF! | F17: =(+D17-$E$6) -> #REF! | H17: BZ | I17: =+C17 -> #REF! | J17: =+'REAL-BDGT2026'!#REF! -> #REF! | K17: =+I17/J17-1 -> #REF!
A18: Admin, Legales y Otros | B18: =+'REAL-BDGT2026'!V93 -> 35942677 | C18: =+'REAL-BDGT2026'!#REF! -> #REF! | D18: =+B18/C18-1 -> #REF! | F18: =(+D18-$E$6) -> #REF! | H18: Admin, Legales y Otros | I18: =+C18 -> #REF! | J18: =+'REAL-BDGT2026'!#REF! -> #REF! | K18: =+I18/J18-1 -> #REF!
A19: Personal | B19: =+'REAL-BDGT2026'!V106 -> 7.5368101e+08 | C19: =+'REAL-BDGT2026'!#REF! -> #REF! | D19: =+B19/C19-1 -> #REF! | F19: =(+D19-$E$6) -> #REF! | H19: Personal | I19: =+C19 -> #REF! | J19: =+'REAL-BDGT2026'!#REF! -> #REF! | K19: =+I19/J19-1 -> #REF!
A20: Oficina | B20: =+'REAL-BDGT2026'!V128 -> 55829453 | C20: =+'REAL-BDGT2026'!#REF! -> #REF! | D20: =+B20/C20-1 -> #REF! | F20: =(+D20-$E$6) -> #REF! | H20: Oficina | I20: =+C20 -> #REF! | J20: =+'REAL-BDGT2026'!#REF! -> #REF! | K20: =+I20/J20-1 -> #REF!
A21: Gastos de Organización | B21: =+'REAL-BDGT2026'!V151 -> 69236198 | C21: =+'REAL-BDGT2026'!#REF! -> #REF! | D21: =+B21/C21-1 -> #REF! | F21: =(+D21-$E$6) -> #REF! | H21: Gastos de Organización | I21: =+C21 -> #REF! | J21: =+'REAL-BDGT2026'!#REF! -> #REF! | K21: 1
A22: Impuesto al débito y al crédito | B22: =+'REAL-BDGT2026'!V154 -> 27470199 | C22: =+'REAL-BDGT2026'!#REF! -> #REF! | H22: Impuesto al débito y al crédito | I22: =+C22 -> #REF! | J22: =+'REAL-BDGT2026'!#REF! -> #REF! | K22: =+I22/J22-1 -> #REF!
A23: Gastos Comercializacion | B23: =+'REAL-BDGT2026'!V157 -> 1.8661207e+09 | C23: =+'REAL-BDGT2026'!#REF! -> #REF! | D23: =+B23/C23-1 -> #REF! | F23: =(+D23-$E$6) -> #REF! | H23: Gastos Comercializacion | I23: =+C23 -> #REF! | J23: =+'REAL-BDGT2026'!#REF! -> #REF! | K23: =+I23/J23-1 -> #REF!
A24: Riesgo Técnico | B24: =+'REAL-BDGT2026'!V168 -> 0 | C24: =+'REAL-BDGT2026'!#REF! -> #REF! | H24: Riesgo Técnico | I24: =+C24 -> #REF! | J24: =+'REAL-BDGT2026'!#REF! -> #REF!
A25: Total Costos | B25: =SUM(B11:B24) -> 3868408831 | C25: =SUM(C11:C24) -> #REF! | D25: =+B25/C25-1 -> #REF! | F25: =(+D25-$E$6) -> #REF! | H25: Total Costos | I25: =SUM(I11:I24) -> #REF! | J25: =SUM(J11:J24) -> #REF! | K25: =+I25/J25-1 -> #REF!
A28: Premisas Presupuesto 2026
A30: Variables Económicas:
A31: Se asume una inflación del 1,5% mensual | E31: Inflación Anual 19,56%
A32: Se inicia con un dolar BNA enero 1500 y se ajusta el 1,5% mensual | E32: dolar BNA ene-26 | G32: =+dolarbnaene -> 1415 | H32: dolar BNA dic-26 | I32: =+usddic -> 1531.586
A33: El dolar Mep es el 2,5% por sobre el BNA | E33: dalor Mep ene-26 | G33: =+dolarmepene -> 1460.32 | H33: dolar Mep dic-26 | I33: =+'REAL-BDGT2026'!T202 -> 0
A35: RRHH:
A36: Se consideran 3 ingresos de recursos: 1 desarrollador (enero) + 1 operador (febrero) + 1 desarrollador (abril)
A37: se considera incremento salarial por performance en Enero del 6,5%
A38: se considera incremento salarial por ipc acumulado trimestral en Abril, Julio y Octubre
A40: Recambio Tecnológico:
A41: Se considera compra de notebook y monitor unicamente en los 3 casos de nuevos recursos
A42: Se considera recambio de celular 1 por mes
A44: Proveedores:
A45: Se prevee una reducción de la contratación del proveedor Reserv al 50% en todas sus lineas desde el mes de Julio2026

Sheet P&L2026
B1: REAL | C1: REAL | D1: REAL | E1: REAL | F1: REAL | G1: REAL | H1: REAL | I1: REAL | J1: REAL | K1: REAL | L1: REAL | M1: REAL | O1: REAL ACUM MAR | R1: BDGT | S1: BDGT | T1: BDGT | U1: BDGT | V1: BDGT | W1: BDGT | X1: BDGT | Y1: BDGT | Z1: BDGT | AA1: BDGT | AB1: BDGT | AC1: BDGT | AE1: BDGT ACUM MAR
A2: P&L | B2: 46023 | C2: 46055 | D2: 46084 | E2: 46116 | F2: 46147 | G2: 46179 | H2: 46210 | I2: 46242 | J2: =+I2+31 -> 46273 | K2: =+J2+31 -> 46304 | L2: =+K2+31 -> 46335 | M2: =+L2+31 -> 46366 | O2: 2026 | R2: 46023 | S2: 46055 | T2: 46084 | U2: 46116 | V2: 46147 | W2: 46179 | X2: 46210 | Y2: 46242 | Z2: 46273 | AA2: 46304 | AB2: 46335 | AC2: 46366 | AE2: 2026
A3: Revenue | B3: ='REAL-BDGT2026'!I40 -> 2.0333588e+09 | C3: ='REAL-BDGT2026'!J40 -> 1.9826386e+09 | D3: ='REAL-BDGT2026'!K40 -> 2.1459686e+09 | E3: ='REAL-BDGT2026'!L40 -> 2.2381283e+09 | F3: ='REAL-BDGT2026'!M40 -> 2.2923773e+09 | G3: ='REAL-BDGT2026'!N40 -> 0 | H3: ='REAL-BDGT2026'!O40 -> 0 | I3: ='REAL-BDGT2026'!P40 -> 0 | ... M3: ='REAL-BDGT2026'!T40 -> 0 | O3: =SUM(B3:F3) -> 1.0692472e+10 | R3: 1.9576561e+09 | S3: 1.8321659e+09 | T3: 1.9897946e+09 | U3: 2.0930368e+09 | V3: 2.2123595e+09 | W3: 2.2232164e+09 | X3: 2.4567705e+09 | Y3: 2.4265489e+09 | Z3: 2.5494244e+09 | AA3: 2.6712355e+09 | AB3: 2.613006e+09 | AC3: 2.6970105e+09 | AE3: =SUM(R3:V3) -> 1.0085013e+10
A4: Sales Tax | B4: ='REAL-BDGT2026'!I41 -> -1.2061955e+08 | C4: ='REAL-BDGT2026'!J41 -> -124410617 | D4: ='REAL-BDGT2026'!K41 -> -1.2598475e+08 | E4: ='REAL-BDGT2026'!L41 -> -1.1082338e+08 | F4: ='REAL-BDGT2026'!M41 -> -1.2180323e+08 | G4: ='REAL-BDGT2026'!N41 -> 0 | H4: ='REAL-BDGT2026'!O41 -> 0 | I4: ='REAL-BDGT2026'!P41 -> 0 | ... M4: ='REAL-BDGT2026'!T41 -> 0 | O4: =SUM(B4:F4) -> -6.0364153e+08 | R4: -97882807 | S4: -91608295 | T4: -99489730 | U4: -1.0465184e+08 | V4: -1.1061798e+08 | W4: -1.1116082e+08 | X4: -1.2283853e+08 | Y4: -1.2132744e+08 | Z4: -1.2747122e+08 | AA4: -1.3356178e+08 | AB4: -1.306503e+08 | AC4: -1.3485052e+08 | AE4: =SUM(R4:V4) -> -5.0425065e+08
A5: Cost of sales | B5: =-SUMIF('REAL-BDGT2026'!$G$43:$G$193,$A5,'REAL-BDGT2026'!I$43:I$193) -> -5.3567942e+08 | C5: =-SUMIF('REAL-BDGT2026'!$G$43:$G$193,$A5,'REAL-BDGT2026'!J$43:J$193) -> -5.164676e+08 | D5: =-SUMIF('REAL-BDGT2026'!$G$43:$G$193,$A5,'REAL-BDGT2026'!K$43:K$193) -> -5.5473174e+08 | E5: =-SUMIF('REAL-BDGT2026'!$G$43:$G$193,$A5,'REAL-BDGT2026'!L$43:L$193) -> -5.302564e+08 | F5: =-SUMIF('REAL-BDGT2026'!$G$43:$G$193,$A5,'REAL-BDGT2026'!M$43:M$193) -> -6.129442e+08 | G5: =-SUMIF('REAL-BDGT2026'!$G$43:$G$193,$A5,'REAL-BDGT2026'!N$43:N$193) -> 0 | H5: =-SUMIF('REAL-BDGT2026'!$G$43:$G$193,$A5,'REAL-BDGT2026'!O$43:O$193) -> 0 | I5: =-SUMIF('REAL-BDGT2026'!$G$43:$G$193,$A5,'REAL-BDGT2026'!P$43:P$193) -> 0 | ... M5: =-SUMIF('REAL-BDGT2026'!$G$43:$G$193,$A5,'REAL-BDGT2026'!T$43:T$193) -> 0 | O5: =SUM(B5:F5) -> -2.7500794e+09 | R5: -5.9572984e+08 | S5: -5.5437848e+08 | T5: -5.8393416e+08 | U5: -6.2675362e+08 | V5: -6.513464e+08 | W5: -6.6555387e+08 | X5: -9.6075565e+08 | Y5: -7.3262158e+08 | Z5: -7.7317055e+08 | AA5: -8.2446615e+08 | AB5: -8.2072176e+08 | AC5: -8.5269618e+08 | AE5: =SUM(R5:V5) -> -3.0121425e+09
A6: Gross margin | B6: =SUM(B3:B5) -> 1.3770598e+09 | C6: =SUM(C3:C5) -> 1.3417604e+09 | D6: =SUM(D3:D5) -> 1.4652521e+09 | E6: =SUM(E3:E5) -> 1.5970485e+09 | F6: =SUM(F3:F5) -> 1.5576298e+09 | G6: =SUM(G3:G5) -> 0 | H6: =SUM(H3:H5) -> 0 | I6: =SUM(I3:I5) -> 0 | ... M6: =SUM(M3:M5) -> 0 | O6: =SUM(B6:F6) -> 7.3387507e+09 | R6: 1.2640435e+09 | S6: 1.1861791e+09 | T6: 1.3063707e+09 | U6: 1.3616313e+09 | V6: 1.4503952e+09 | W6: 1.4465017e+09 | X6: 1.3731763e+09 | Y6: 1.5725998e+09 | Z6: 1.6487826e+09 | AA6: 1.7132076e+09 | AB6: 1.6616339e+09 | AC6: 1.7094638e+09 | AE6: =SUM(R6:V6) -> 6.5686198e+09
A7: % | B7: =B6/B3 -> 0.67723406 | C7: =C6/C3 -> 0.67675489 | D7: =D6/D3 -> 0.68279289 | E7: =E6/E3 -> 0.71356433 | F7: =F6/F3 -> 0.67948232 | G7: =G6/G3 -> #DIV/0! | H7: =H6/H3 -> #DIV/0! | I7: =I6/I3 -> #DIV/0! | ... M7: =M6/M3 -> #DIV/0! | O7: =O6/O3 -> 0.68634746 | R7: =R6/R3 -> 0.6456923 | S7: =S6/S3 -> 0.64741906 | T7: 0.65653546 | U7: 0.65055298 | V7: 0.65558745 | W7: 0.65063469 | X7: 0.55893553 | Y7: 0.64808085 | Z7: 0.64672741 | AA7: 0.641354 | AB7: 0.63590896 | AC7: 0.63383654 | AE7: =AE6/AE3 -> 0.65132488
A8: Salaries&Social Security | B8: =-SUMIF('REAL-BDGT2026'!$G$43:$G$193,$A8,'REAL-BDGT2026'!I$43:I$193) -> -1.4832938e+08 | C8: =-SUMIF('REAL-BDGT2026'!$G$43:$G$193,$A8,'REAL-BDGT2026'!J$43:J$193) -> -1.4584772e+08 | D8: =-SUMIF('REAL-BDGT2026'!$G$43:$G$193,$A8,'REAL-BDGT2026'!K$43:K$193) -> -3.1817162e+08 | E8: =-SUMIF('REAL-BDGT2026'!$G$43:$G$193,$A8,'REAL-BDGT2026'!L$43:L$193) -> -1.4927063e+08 | F8: =-SUMIF('REAL-BDGT2026'!$G$43:$G$193,$A8,'REAL-BDGT2026'!M$43:M$193) -> -1.5158914e+08 | G8: =-SUMIF('REAL-BDGT2026'!$G$43:$G$193,$A8,'REAL-BDGT2026'!N$43:N$193) -> 0 | H8: =-SUMIF('REAL-BDGT2026'!$G$43:$G$193,$A8,'REAL-BDGT2026'!O$43:O$193) -> 0 | I8: =-SUMIF('REAL-BDGT2026'!$G$43:$G$193,$A8,'REAL-BDGT2026'!P$43:P$193) -> 0 | ... M8: =-SUMIF('REAL-BDGT2026'!$G$43:$G$193,$A8,'REAL-BDGT2026'!T$43:T$193) -> 0 | O8: =SUM(B8:F8) -> -9.132085e+08 | R8: -1.7592659e+08 | S8: -1.8009192e+08 | T8: -1.8025972e+08 | U8: -1.9209483e+08 | V8: -1.9162161e+08 | W8: -1.9179708e+08 | X8: -1.9995305e+08 | Y8: -2.0013382e+08 | Z8: -2.0031731e+08 | AA8: -2.0783924e+08 | AB8: -2.0802828e+08 | AC8: -2.0822014e+08 | AE8: =SUM(R8:V8) -> -9.1999467e+08
A9: Office&office related | B9: =-SUMIF('REAL-BDGT2026'!$G$43:$G$193,$A9,'REAL-BDGT2026'!I$43:I$193) -> -9170663.2 | C9: =-SUMIF('REAL-BDGT2026'!$G$43:$G$193,$A9,'REAL-BDGT2026'!J$43:J$193) -> -10435567 | D9: =-SUMIF('REAL-BDGT2026'!$G$43:$G$193,$A9,'REAL-BDGT2026'!K$43:K$193) -> -9906459 | E9: =-SUMIF('REAL-BDGT2026'!$G$43:$G$193,$A9,'REAL-BDGT2026'!L$43:L$193) -> -10670610 | F9: =-SUMIF('REAL-BDGT2026'!$G$43:$G$193,$A9,'REAL-BDGT2026'!M$43:M$193) -> -11622974 | G9: =-SUMIF('REAL-BDGT2026'!$G$43:$G$193,$A9,'REAL-BDGT2026'!N$43:N$193) -> 0 | H9: =-SUMIF('REAL-BDGT2026'!$G$43:$G$193,$A9,'REAL-BDGT2026'!O$43:O$193) -> 0 | I9: =-SUMIF('REAL-BDGT2026'!$G$43:$G$193,$A9,'REAL-BDGT2026'!P$43:P$193) -> 0 | ... M9: =-SUMIF('REAL-BDGT2026'!$G$43:$G$193,$A9,'REAL-BDGT2026'!T$43:T$193) -> 0 | O9: =SUM(B9:F9) -> -51806273 | R9: -12582076 | S9: -12400446 | T9: -10625450 | U9: -12794270 | V9: -14325916 | W9: -11309375 | X9: -13960929 | Y9: -11671445 | Z9: -11845703 | AA9: -13045412 | AB9: -12225298 | AC9: -18388450 | AE9: =SUM(R9:V9) -> -62728159
A10: Professional fees | B10: =-SUMIF('REAL-BDGT2026'!$G$43:$G$171,$A10,'REAL-BDGT2026'!I$43:I$171) -> -39780586 | C10: =-SUMIF('REAL-BDGT2026'!$G$43:$G$171,$A10,'REAL-BDGT2026'!J$43:J$171) -> -38581588 | D10: =-SUMIF('REAL-BDGT2026'!$G$43:$G$171,$A10,'REAL-BDGT2026'!K$43:K$171) -> -44021552 | E10: =-SUMIF('REAL-BDGT2026'!$G$43:$G$171,$A10,'REAL-BDGT2026'!L$43:L$171) -> -51875614 | F10: =-SUMIF('REAL-BDGT2026'!$G$43:$G$171,$A10,'REAL-BDGT2026'!M$43:M$171) -> -28308510 | G10: =-SUMIF('REAL-BDGT2026'!$G$43:$G$171,$A10,'REAL-BDGT2026'!N$43:N$171) -> 0 | H10: =-SUMIF('REAL-BDGT2026'!$G$43:$G$171,$A10,'REAL-BDGT2026'!O$43:O$171) -> 0 | I10: =-SUMIF('REAL-BDGT2026'!$G$43:$G$171,$A10,'REAL-BDGT2026'!P$43:P$171) -> 0 | ... M10: =-SUMIF('REAL-BDGT2026'!$G$43:$G$171,$A10,'REAL-BDGT2026'!T$43:T$171) -> 0 | O10: =SUM(B10:F10) -> -2.0256785e+08 | R10: -45017725 | S10: -43827791 | T10: -40064810 | U10: -46990029 | V10: -41715304 | W10: -41724856 | X10: -30523302 | Y10: -33841431 | Z10: -30882057 | AA10: -31917557 | AB10: -31699169 | AC10: -31709614 | AE10: =SUM(R10:V10) -> -2.1761566e+08
A11: Travel | B11: =-SUMIF('REAL-BDGT2026'!$G$43:$G$171,$A11,'REAL-BDGT2026'!I$43:I$140) -> 0 | C11: =-SUMIF('REAL-BDGT2026'!$G$43:$G$171,$A11,'REAL-BDGT2026'!J$43:J$140) -> 0 | D11: =-SUMIF('REAL-BDGT2026'!$G$43:$G$193,$A11,'REAL-BDGT2026'!K$43:K$193) -> 0 | E11: =-SUMIF('REAL-BDGT2026'!$G$43:$G$193,$A11,'REAL-BDGT2026'!L$43:L$193) -> 0 | F11: =-SUMIF('REAL-BDGT2026'!$G$43:$G$193,$A11,'REAL-BDGT2026'!M$43:M$193) -> 0 | G11: =-SUMIF('REAL-BDGT2026'!$G$43:$G$193,$A11,'REAL-BDGT2026'!N$43:N$193) -> 0 | H11: =-SUMIF('REAL-BDGT2026'!$G$43:$G$193,$A11,'REAL-BDGT2026'!O$43:O$193) -> 0 | I11: =-SUMIF('REAL-BDGT2026'!$G$43:$G$193,$A11,'REAL-BDGT2026'!P$43:P$193) -> 0 | J11: =-SUMIF('REAL-BDGT2026'!$G$43:$G$193,$A11,'REAL-BDGT2026'!Q$43:Q$193) -> 0 | K11: =-SUMIF('REAL-BDGT2026'!$G$43:$G$193,$A11,'REAL-BDGT2026'!R$43:R$193) -> 0 | ... M11: =-SUMIF('REAL-BDGT2026'!$G$43:$G$193,$A11,'REAL-BDGT2026'!T$43:T$193) -> 0 | O11: =SUM(B11:F11) -> 0 | R11: 0 | S11: 0 | T11: 0 | U11: 0 | V11: 0 | W11: 0 | X11: 0 | Y11: 0 | Z11: 0 | AA11: 0 | AB11: 0 | AC11: 0 | AE11: =SUM(R11:V11) -> 0
A12: Marketing&Advertising | B12: =-SUMIF('REAL-BDGT2026'!$G$43:$G$171,$A12,'REAL-BDGT2026'!I$43:I$140) -> 0 | C12: =-SUMIF('REAL-BDGT2026'!$G$43:$G$171,$A12,'REAL-BDGT2026'!J$43:J$140) -> 0 | D12: =-SUMIF('REAL-BDGT2026'!$G$43:$G$193,$A12,'REAL-BDGT2026'!K$43:K$193) -> 0 | E12: =-SUMIF('REAL-BDGT2026'!$G$43:$G$193,$A12,'REAL-BDGT2026'!L$43:L$193) -> 0 | F12: =-SUMIF('REAL-BDGT2026'!$G$43:$G$193,$A12,'REAL-BDGT2026'!M$43:M$193) -> 0 | G12: =-SUMIF('REAL-BDGT2026'!$G$43:$G$193,$A12,'REAL-BDGT2026'!N$43:N$193) -> 0 | H12: =-SUMIF('REAL-BDGT2026'!$G$43:$G$193,$A12,'REAL-BDGT2026'!O$43:O$193) -> 0 | I12: =-SUMIF('REAL-BDGT2026'!$G$43:$G$193,$A12,'REAL-BDGT2026'!P$43:P$193) -> 0 | J12: =-SUMIF('REAL-BDGT2026'!$G$43:$G$193,$A12,'REAL-BDGT2026'!Q$43:Q$193) -> 0 | K12: =-SUMIF('REAL-BDGT2026'!$G$43:$G$193,$A12,'REAL-BDGT2026'!R$43:R$193) -> 0 | ... M12: =-SUMIF('REAL-BDGT2026'!$G$43:$G$193,$A12,'REAL-BDGT2026'!T$43:T$193) -> 0 | O12: =SUM(B12:F12) -> 0 | R12: 0 | S12: 0 | T12: 0 | U12: 0 | V12: 0 | W12: 0 | X12: 0 | Y12: 0 | Z12: 0 | AA12: 0 | AB12: 0 | AC12: 0 | AE12: =SUM(R12:V12) -> 0
A13: Other taxes | B13: =-SUMIF('REAL-BDGT2026'!$G$43:$G$193,$A13,'REAL-BDGT2026'!I$43:I$193) -> -15332426 | C13: =-SUMIF('REAL-BDGT2026'!$G$43:$G$193,$A13,'REAL-BDGT2026'!J$43:J$193) -> -12269412 | D13: =-SUMIF('REAL-BDGT2026'!$G$43:$G$193,$A13,'REAL-BDGT2026'!K$43:K$193) -> -6631113 | E13: =-SUMIF('REAL-BDGT2026'!$G$43:$G$193,$A13,'REAL-BDGT2026'!L$43:L$193) -> -2361718.3 | F13: =-SUMIF('REAL-BDGT2026'!$G$43:$G$193,$A13,'REAL-BDGT2026'!M$43:M$193) -> -29861802 | G13: =-SUMIF('REAL-BDGT2026'!$G$43:$G$193,$A13,'REAL-BDGT2026'!N$43:N$193) -> 0 | H13: =-SUMIF('REAL-BDGT2026'!$G$43:$G$193,$A13,'REAL-BDGT2026'!O$43:O$193) -> 0 | I13: =-SUMIF('REAL-BDGT2026'!$G$43:$G$193,$A13,'REAL-BDGT2026'!P$43:P$193) -> 0 | ... M13: =-SUMIF('REAL-BDGT2026'!$G$43:$G$193,$A13,'REAL-BDGT2026'!T$43:T$193) -> 0 | O13: =SUM(B13:F13) -> -66456471 | R13: -2537.5 | S13: -2575.5625 | T13: -2614.1959 | U13: -2653.4089 | V13: -15008709 | W13: -15115280 | X13: -17647020 | Y13: -16414920 | Z13: -17185561 | AA13: -18061815 | AB13: -17760834 | AC13: -18347103 | AE13: =SUM(R13:V13) -> -15019089
A14: Miscellaneous | B14: =-SUMIF('REAL-BDGT2026'!$G$43:$G$171,$A14,'REAL-BDGT2026'!I$43:I$140) -> 0 | C14: =-SUMIF('REAL-BDGT2026'!$G$43:$G$171,$A14,'REAL-BDGT2026'!J$43:J$140) -> 0 | D14: =-SUMIF('REAL-BDGT2026'!$G$43:$G$193,$A14,'REAL-BDGT2026'!K$43:K$193) -> 0 | E14: =-SUMIF('REAL-BDGT2026'!$G$43:$G$193,$A14,'REAL-BDGT2026'!L$43:L$193) -> 0 | F14: =-SUMIF('REAL-BDGT2026'!$G$43:$G$193,$A14,'REAL-BDGT2026'!M$43:M$193) -> 0 | G14: =-SUMIF('REAL-BDGT2026'!$G$43:$G$193,$A14,'REAL-BDGT2026'!N$43:N$193) -> 0 | H14: =-SUMIF('REAL-BDGT2026'!$G$43:$G$193,$A14,'REAL-BDGT2026'!O$43:O$193) -> 0 | I14: =-SUMIF('REAL-BDGT2026'!$G$43:$G$193,$A14,'REAL-BDGT2026'!P$43:P$193) -> 0 | J14: =-SUMIF('REAL-BDGT2026'!$G$43:$G$193,$A14,'REAL-BDGT2026'!Q$43:Q$193) -> 0 | K14: =-SUMIF('REAL-BDGT2026'!$G$43:$G$193,$A14,'REAL-BDGT2026'!R$43:R$193) -> 0 | ... M14: =-SUMIF('REAL-BDGT2026'!$G$43:$G$193,$A14,'REAL-BDGT2026'!T$43:T$193) -> 0 | O14: =SUM(B14:F14) -> 0 | R14: 0 | S14: 0 | T14: 0 | U14: 0 | V14: 0 | W14: 0 | X14: 0 | Y14: 0 | Z14: 0 | AA14: 0 | AB14: 0 | AC14: 0 | AE14: =SUM(R14:V14) -> 0
A15: EBITDA | B15: =SUM(B6:B14) -> 1.1644468e+09 | C15: =SUM(C6:C14) -> 1.1346261e+09 | D15: =SUM(D6:D14) -> 1.0865213e+09 | E15: =SUM(E6:E14) -> 1.38287e+09 | F15: =SUM(F6:F14) -> 1.3362474e+09 | G15: =SUM(G6:G14) -> #DIV/0! | H15: =SUM(H6:H14) -> #DIV/0! | I15: =SUM(I6:I14) -> #DIV/0! | ... M15: =SUM(M6:M14) -> #DIV/0! | O15: =SUM(B15:F15) -> 6.1047116e+09 | R15: 1.0305146e+09 | S15: 9.498564e+08 | T15: 1.0754181e+09 | U15: 1.1097495e+09 | V15: 1.1877236e+09 | W15: 1.1865551e+09 | X15: 1.111092e+09 | Y15: 1.3105382e+09 | Z15: 1.388552e+09 | AA15: 1.4423436e+09 | AB15: 1.3919203e+09 | AC15: 1.4327985e+09 | AE15: =SUM(R15:V15) -> 5.3532623e+09
A16: % | B16: =B15/B3 -> 0.57267157 | C16: =C15/C3 -> 0.57228084 | D16: =D15/D3 -> 0.50630813 | E16: =E15/E3 -> 0.61786894 | F16: =F15/F3 -> 0.58290903 | G16: =G15/G3 -> #DIV/0! | H16: =H15/H3 -> #DIV/0! | I16: =I15/I3 -> #DIV/0! | ... M16: =M15/M3 -> #DIV/0! | O16: =O15/O3 -> 0.5709355 | R16: =R15/R3 -> 0.52640223 | S16: =S15/S3 -> 0.51843362 | T16: 0.5404669 | U16: 0.53021024 | V16: 0.53685832 | W16: 0.53371103 | X16: 0.45225715 | Y16: 0.54008318 | Z16: 0.54465314 | AA16: 0.53995372 | AB16: 0.5326893 | AC16: 0.53125432 | AE16: =AE15/AE3 -> 0.53081362
A17: Exchange rate differences | B17: =-SUMIF('REAL-BDGT2026'!$G$43:$G$193,$A17,'REAL-BDGT2026'!I$43:I$140) -> -140088 | C17: =-SUMIF('REAL-BDGT2026'!$G$43:$G$193,$A17,'REAL-BDGT2026'!J$43:J$140) -> 4508 | D17: =-SUMIF('REAL-BDGT2026'!$G$43:$G$193,$A17,'REAL-BDGT2026'!K$43:K$193) -> 5728 | E17: =-SUMIF('REAL-BDGT2026'!$G$43:$G$193,$A17,'REAL-BDGT2026'!L$43:L$193) -> -47373.53 | F17: =-SUMIF('REAL-BDGT2026'!$G$43:$G$193,$A17,'REAL-BDGT2026'!M$43:M$193) -> -58840 | G17: =-SUMIF('REAL-BDGT2026'!$G$43:$G$193,$A17,'REAL-BDGT2026'!N$43:N$193) -> 0 | H17: =-SUMIF('REAL-BDGT2026'!$G$43:$G$193,$A17,'REAL-BDGT2026'!O$43:O$193) -> 0 | I17: =-SUMIF('REAL-BDGT2026'!$G$43:$G$193,$A17,'REAL-BDGT2026'!P$43:P$193) -> 0 | J17: =-SUMIF('REAL-BDGT2026'!$G$43:$G$193,$A17,'REAL-BDGT2026'!Q$43:Q$193) -> 0 | K17: =-SUMIF('REAL-BDGT2026'!$G$43:$G$193,$A17,'REAL-BDGT2026'!R$43:R$193) -> 0 | ... M17: =-SUMIF('REAL-BDGT2026'!$G$43:$G$193,$A17,'REAL-BDGT2026'!T$43:T$193) -> 0 | O17: =SUM(B17:F17) -> -236065.53 | R17: 0 | S17: 0 | T17: 0 | U17: 0 | V17: 0 | W17: 0 | X17: 0 | Y17: 0 | Z17: 0 | AA17: 0 | AB17: 0 | AC17: 0 | AE17: =SUM(R17:V17) -> 0
A18: Financing activities | B18: =SUMIF('REAL-BDGT2026'!$G$43:$G$193,$A18,'REAL-BDGT2026'!I$43:I$193)*-1 -> 2.3808781e+08 | C18: =SUMIF('REAL-BDGT2026'!$G$43:$G$193,$A18,'REAL-BDGT2026'!J$43:J$193)*-1 -> 218300896 | D18: =SUMIF('REAL-BDGT2026'!$G$43:$G$193,$A18,'REAL-BDGT2026'!K$43:K$193)*-1 -> 262865752 | E18: =SUMIF('REAL-BDGT2026'!$G$43:$G$193,$A18,'REAL-BDGT2026'!L$43:L$193)*-1 -> 85208676 | F18: =SUMIF('REAL-BDGT2026'!$G$43:$G$193,$A18,'REAL-BDGT2026'!M$43:M$193)*-1 -> 72294339 | G18: =SUMIF('REAL-BDGT2026'!$G$43:$G$193,$A18,'REAL-BDGT2026'!N$43:N$193)*-1 -> 0 | H18: =SUMIF('REAL-BDGT2026'!$G$43:$G$193,$A18,'REAL-BDGT2026'!O$43:O$193)*-1 -> 0 | I18: =SUMIF('REAL-BDGT2026'!$G$43:$G$193,$A18,'REAL-BDGT2026'!P$43:P$193)*-1 -> 0 | ... M18: =SUMIF('REAL-BDGT2026'!$G$43:$G$193,$A18,'REAL-BDGT2026'!T$43:T$193)*-1 -> 0 | O18: =SUM(B18:F18) -> 8.7675747e+08 | R18: 0 | S18: 0 | T18: 0 | U18: 0 | V18: 0 | W18: 0 | X18: 0 | Y18: 0 | Z18: 0 | AA18: 0 | AB18: 0 | AC18: 0 | AE18: =SUM(R18:V18) -> 0
A19: Interest | B19: =SUMIF('REAL-BDGT2026'!$G$43:$G$193,$A19,'REAL-BDGT2026'!I$43:I$193)*-1 -> 0 | C19: =SUMIF('REAL-BDGT2026'!$G$43:$G$193,$A19,'REAL-BDGT2026'!J$43:J$193)*-1 -> -3024427 | D19: =SUMIF('REAL-BDGT2026'!$G$43:$G$193,$A19,'REAL-BDGT2026'!K$43:K$193) -> 0 | E19: =SUMIF('REAL-BDGT2026'!$G$43:$G$193,$A19,'REAL-BDGT2026'!L$43:L$193)*-1 -> -27050.63 | F19: =SUMIF('REAL-BDGT2026'!$G$43:$G$193,$A19,'REAL-BDGT2026'!M$43:M$193)*-1 -> 0 | G19: =SUMIF('REAL-BDGT2026'!$G$43:$G$193,$A19,'REAL-BDGT2026'!N$43:N$193)*-1 -> 0 | H19: =SUMIF('REAL-BDGT2026'!$G$43:$G$193,$A19,'REAL-BDGT2026'!O$43:O$193)*-1 -> 0 | I19: =SUMIF('REAL-BDGT2026'!$G$43:$G$193,$A19,'REAL-BDGT2026'!P$43:P$193)*-1 -> 0 | J19: =SUMIF('REAL-BDGT2026'!$G$43:$G$193,$A19,'REAL-BDGT2026'!Q$43:Q$193)*-1 -> 0 | K19: =SUMIF('REAL-BDGT2026'!$G$43:$G$193,$A19,'REAL-BDGT2026'!R$43:R$193)*-1 -> 0 | L19: =SUMIF('REAL-BDGT2026'!$G$43:$G$193,$A19,'REAL-BDGT2026'!S$43:S$193)*-1 -> 0 | M19: =SUMIF('REAL-BDGT2026'!$G$43:$G$193,$A19,'REAL-BDGT2026'!T$43:T$193)*-1 -> 0 | O19: =SUM(B19:F19) -> -3051477.7 | R19: 0 | S19: 0 | T19: 0 | U19: 0 | V19: 0 | W19: 0 | X19: 0 | Y19: 0 | Z19: 0 | AA19: 0 | AB19: 0 | AC19: 0 | AE19: =SUM(R19:V19) -> 0
A20: Other income | B20: =-SUMIF('REAL-BDGT2026'!$G$43:$G$193,$A20,'REAL-BDGT2026'!I$43:I$193) -> -67750 | C20: =-SUMIF('REAL-BDGT2026'!$G$43:$G$193,$A20,'REAL-BDGT2026'!J$43:J$193) -> -49000 | D20: =-SUMIF('REAL-BDGT2026'!$G$43:$G$193,$A20,'REAL-BDGT2026'!K$43:K$193) -> -49000 | E20: =-SUMIF('REAL-BDGT2026'!$G$43:$G$193,$A20,'REAL-BDGT2026'!L$43:L$193) -> -49000 | F20: =-SUMIF('REAL-BDGT2026'!$G$43:$G$193,$A20,'REAL-BDGT2026'!M$43:M$193) -> -65000 | G20: =-SUMIF('REAL-BDGT2026'!$G$43:$G$193,$A20,'REAL-BDGT2026'!N$43:N$193) -> 0 | H20: =-SUMIF('REAL-BDGT2026'!$G$43:$G$193,$A20,'REAL-BDGT2026'!O$43:O$193) -> 0 | I20: =-SUMIF('REAL-BDGT2026'!$G$43:$G$193,$A20,'REAL-BDGT2026'!P$43:P$193) -> 0 | ... M20: =-SUMIF('REAL-BDGT2026'!$G$43:$G$193,$A20,'REAL-BDGT2026'!T$43:T$193) -> 0 | O20: =SUM(B20:F20) -> -279750 | R20: -70000 | S20: -70000 | T20: -70000 | U20: -70000 | V20: -70000 | W20: -70000 | X20: -70000 | Y20: -70000 | Z20: -70000 | AA20: -70000 | AB20: -70000 | AC20: -70000 | AE20: =SUM(R20:V20) -> -350000
A21: Depreciation | B21: =-SUMIF('REAL-BDGT2026'!$G$43:$G$193,$A21,'REAL-BDGT2026'!I$43:I$193) -> -20874038 | C21: =-SUMIF('REAL-BDGT2026'!$G$43:$G$193,$A21,'REAL-BDGT2026'!J$43:J$193) -> -20874038 | D21: =-SUMIF('REAL-BDGT2026'!$G$43:$G$193,$A21,'REAL-BDGT2026'!K$43:K$193) -> -21322923 | E21: =-SUMIF('REAL-BDGT2026'!$G$43:$G$193,$A21,'REAL-BDGT2026'!L$43:L$193) -> -21082522 | F21: =-SUMIF('REAL-BDGT2026'!$G$43:$G$193,$A21,'REAL-BDGT2026'!M$43:M$193) -> -20985760 | G21: =-SUMIF('REAL-BDGT2026'!$G$43:$G$193,$A21,'REAL-BDGT2026'!N$43:N$193) -> 0 | H21: =-SUMIF('REAL-BDGT2026'!$G$43:$G$193,$A21,'REAL-BDGT2026'!O$43:O$193) -> 0 | I21: =-SUMIF('REAL-BDGT2026'!$G$43:$G$193,$A21,'REAL-BDGT2026'!P$43:P$193) -> 0 | ... M21: =-SUMIF('REAL-BDGT2026'!$G$43:$G$193,$A21,'REAL-BDGT2026'!T$43:T$193) -> 0 | O21: =SUM(B21:F21) -> -1.0513928e+08 | R21: -20362316 | S21: -20362316 | T21: -20362316 | U21: -20362316 | V21: -20362316 | W21: -20362316 | X21: -20362316 | Y21: -20362316 | Z21: -20362316 | AA21: -20362316 | AB21: -20362316 | AC21: -20362316 | AE21: =SUM(R21:V21) -> -101811580
A22: Income tax | B22: =-SUMIF('REAL-BDGT2026'!$G$43:$G$193,$A22,'REAL-BDGT2026'!I$43:I$193) -> -4.8831943e+08 | C22: =-SUMIF('REAL-BDGT2026'!$G$43:$G$193,$A22,'REAL-BDGT2026'!J$43:J$193) -> -4.6233286e+08 | D22: =-SUMIF('REAL-BDGT2026'!$G$43:$G$193,$A22,'REAL-BDGT2026'!K$43:K$193) -> -4.7773254e+08 | E22: =-SUMIF('REAL-BDGT2026'!$G$43:$G$193,$A22,'REAL-BDGT2026'!L$43:L$193) -> -5.1250147e+08 | F22: =-SUMIF('REAL-BDGT2026'!$G$43:$G$193,$A22,'REAL-BDGT2026'!M$43:M$193) -> -2.7747104e+08 | G22: =-SUMIF('REAL-BDGT2026'!$G$43:$G$193,$A22,'REAL-BDGT2026'!N$43:N$193) -> 0 | H22: =-SUMIF('REAL-BDGT2026'!$G$43:$G$193,$A22,'REAL-BDGT2026'!O$43:O$193) -> 0 | I22: =-SUMIF('REAL-BDGT2026'!$G$43:$G$193,$A22,'REAL-BDGT2026'!P$43:P$193) -> 0 | ... M22: =-SUMIF('REAL-BDGT2026'!$G$43:$G$193,$A22,'REAL-BDGT2026'!T$43:T$193) -> 0 | O22: =SUM(B22:F22) -> -2.2183573e+09 | R22: -3.5355329e+08 | S22: -3.2532293e+08 | T22: -3.6926953e+08 | U22: -3.8128553e+08 | V22: -4.0857646e+08 | W22: -4.0816747e+08 | X22: -3.817554e+08 | Y22: -4.5156157e+08 | Z22: -4.7886639e+08 | AA22: -4.9769344e+08 | AB22: -4.8004531e+08 | AC22: -4.9435266e+08 | AE22: =SUM(R22:V22) -> -1.8380077e+09
A23: Net (loss) income | B23: =SUM(B15:B22) -> 8.931333e+08 | C23: =SUM(C15:C22) -> 8.6665115e+08 | D23: =SUM(D15:D22) -> 8.5028835e+08 | E23: =SUM(E15:E22) -> 9.3437123e+08 | F23: =SUM(F15:F22) -> 1.1099611e+09 | G23: =SUM(G15:G22) -> #DIV/0! | H23: =SUM(H15:H22) -> #DIV/0! | I23: =SUM(I15:I22) -> #DIV/0! | ... M23: =SUM(M15:M22) -> #DIV/0! | O23: =SUM(B23:F23) -> 4.6544051e+09 | R23: 6.5652896e+08 | S23: 6.0410116e+08 | T23: 6.8571628e+08 | U23: 7.080317e+08 | V23: 7.5871485e+08 | W23: 7.5795531e+08 | X23: 7.0890432e+08 | Y23: 8.3854434e+08 | Z23: 8.892533e+08 | AA23: 9.2421781e+08 | AB23: 8.9144271e+08 | AC23: 9.1801351e+08 | AE23: =SUM(R23:V23) -> 3.4130929e+09
A24: % | B24: =B23/(SUM(B3:B4)) -> 0.46693938 | C24: =C23/(SUM(C3:C4)) -> 0.46638581 | D24: =D23/(SUM(D3:D4)) -> 0.4209382 | E24: =E23/(SUM(E3:E4)) -> 0.43922769 | F24: =F23/(SUM(F3:F4)) -> 0.51136754 | G24: =G23/(SUM(G3:G4)) -> #DIV/0! | H24: =H23/(SUM(H3:H4)) -> #DIV/0! | I24: =I23/(SUM(I3:I4)) -> #DIV/0! | ... M24: =M23/(SUM(M3:M4)) -> #DIV/0! | O24: =O23/(SUM(O3:O4)) -> 0.46134241 | R24: =R23/(SUM(R3:R4)) -> 0.35301558 | S24: =S23/(SUM(S3:S4)) -> 0.34707335 | T24: 0.36275433 | U24: 0.35608382 | V24: 0.36099341 | W24: 0.35887091 | X24: 0.30373821 | Y24: 0.3637587 | Z24: 0.3671637 | AA24: 0.36419883 | AB24: 0.3591116 | AC24: 0.35829672 | AE24: =AE23/(SUM(AE3:AE4)) -> 0.3562444

Sheet Cuentas
A2: 5111 | B2: Ingresos por Venta de Servicios
A3: 5121 | B3: Diferencia de Cambio
A4: 5122 | B4: Resultados Financieros -
A5: 5123 | B5: Resultados por tenencia
A6: 5125 | B6: Resultados por tenencia FCI
A7: 5126 | B7: Intereses ganados préstamos accionistas
A8: 5211 | B8: Servicios Profesionales
A9: 5212 | B9: Servicios Call Center
A10: 5213 | B10: Mantenimiento y Soporte Plataforma
A11: 5214 | B11: Evolucion Desarrollo
A12: 5215 | B12: Mantenimiento de Licencias
A13: 5216 | B13: Servicios de CRM de llamadas telefonicas
... A44: 5711 | B44: Intereses Perdidos y Multas

Sheet RRHH-IngresVacyBonos
B1: Ingresos de Personal | H1: ipc estimado
G2: 1 | H2: 1
B3: Meses en los que se suma | G3: =+G2*H3 -> 1.023 | H3: 1.023 | I3: 45955
B4: 2 | C4: desarrolladores | D4: enero y abril | G4: =+G3*H4 -> 1.04346 | H4: 1.02 | I4: 45986
B5: 1 | C5: operaciones | D5: febrero | G5: =+G4*H5 -> 1.0643292 | H5: 1.02 | I5: dic-25
B7: ACTUALIZAR CANTIDAD DE LICENCIAS SEGUN INGRESOS
B10: Calculo Mensual de Vacaciones y Bono | J10: Monto Anual | K10: Prorrateo
G11: a definir por IA | K11: Mensual
F12: ajuste aplicado en cada mes | G12: =+G5 -> 1.0643292 | H12: =+'REAL-BDGT2026'!L198 -> 1.0948416 | I12: =+'REAL-BDGT2026'!O198 -> 1.0779248 | J12: =+'REAL-BDGT2026'!R198 -> 1.0895474
C13: Fuente: Mail Analia de Martin 20/11/2025 | G13: Ene-26 | H13: Abr-25 | I13: 46228 | J13: 46320
C15: Prov. Vacaciones | E15: base salarial dic2025 | F15: 47922601 | G15: =+F15*$G$12 -> 51005423 | H15: =+G15*$H$12 -> 55842859 | I15: =+H15*$I$12 -> 60194404 | J15: =+I15*$J$12 -> 65584656
C16: Prov. Vacaciones (Cargas sociales) | F16: 11501424 | G16: =+F16*$G$12 -> 12241302 | H16: =+G16*$H$12 -> 13402286 | I16: =+H16*$I$12 -> 14446657 | J16: =+I16*$J$12 -> 15740317
C17: Total Provi Vacaciones y Cs Sociales | F17: =SUM(F15:F16) -> 59424025 | G17: =SUM(G15:G16) -> 63246725 | H17: =SUM(H15:H16) -> 69245145 | I17: =SUM(I15:I16) -> 74641061 | J17: =SUM(J15:J16) -> 81324973 | K17: =+J17/12 -> 6777081.1 | L17: =+C15 -> Prov. Vacaciones
C19: Prov. Bono 75% | E19: base salarial dic2025 | F19: 1.3202459e+08 | G19: =+F19*$G$12 -> 1.4051763e+08 | H19: =+G19*$H$12 -> 1.5384454e+08 | I19: =+H19*$I$12 -> 1.6583285e+08 | J19: =+I19*$J$12 -> 1.8068275e+08
C20: Prov. Bono (Cargas sociales) | F20: 31685902 | G20: =+F20*$G$12 -> 33724230 | H20: =+G20*$H$12 -> 36922690 | I20: =+H20*$I$12 -> 39799885 | J20: =+I20*$J$12 -> 43363860
C21: Total Provi Bono y Cs Sociales | F21: =SUM(F19:F20) -> 1.6371049e+08 | G21: =SUM(G19:G20) -> 1.7424186e+08 | H21: =SUM(H19:H20) -> 1.9076723e+08 | I21: =SUM(I19:I20) -> 2.0563274e+08 | J21: =SUM(J19:J20) -> 2.2404661e+08 | K21: =+J21/12 -> 18670551 | L21: =+C19 -> Prov. Bono 75%
C23: multiplicador costo total empresa por sueldo bruto | F23: 1.26

Sheet Flk
A2: Dias hábiles 2025 | C2: 20 | D2: 18 | E2: 19 | F2: 21 | G2: 20 | H2: 22 | I2: 20 | J2: 22 | K2: 22 | L2: 19 | M2: 19
B4: REAL | C4: REAL | D4: REAL | E4: REAL | F4: REAL | G4: REAL | H4: REAL | I4: REAL | J4: REAL | K4: RFC | L4: RFC | M4: RFC
A5: REAL TRX 2025 | B5: 45658 | C5: 45689 | D5: 45747 | E5: =+D5+30 -> 45777 | F5: =+E5+30 -> 45807 | G5: =+F5+30 -> 45837 | H5: =+G5+30 -> 45867 | I5: =+H5+30 -> 45897 | J5: =+I5+30 -> 45927 | K5: =+J5+30 -> 45957 | L5: =+K5+30 -> 45987 | M5: =+L5+30 -> 46017
A6: Servicio Basico Online PREPAGAS | B6: 1490306 | C6: 1355716 | D6: 1520755 | E6: 1602317 | F6: 1682330 | G6: 1666122 | H6: 1751014 | I6: 1703302 | J6: 1734745 | K6: 1750000 | L6: 1602317 | M6: 1602317
A7: Servicio Basico Online APROSS | B7: 213669 | C7: 190015 | D7: 208388 | E7: 213716 | F7: 225462 | G7: 230982 | H7: 241030 | I7: 233048 | J7: 233018 | K7: 250000 | L7: 213716 | M7: 213716
A8: Servicio Basico Online IOMA | B8: 763760 | C8: 721443 | D8: 781327 | E8: 818781 | F8: 852102 | G8: 847647 | H8: 914890 | I8: 872560 | J8: 889037 | K8: 910000 | L8: 818781 | M8: 818781
A9: Receta Electrónica Prepagas | B9: 815603 | C9: 797198 | D9: 919640 | E9: 975702 | F9: 1037849 | G9: 1037505 | H9: 1125351 | I9: 1127209 | J9: 1157003 | K9: 1157003 | L9: 975702 | M9: 975702
A10: Receta Electrónica Apross | B10: 213655 | C10: 190000 | D10: 208408 | E10: 213654 | F10: 225525 | G10: 230993 | H10: 241068 | I10: 233115 | J10: 233023 | K10: 233023 | L10: 213654 | M10: 213654
A11: Receta Electrónica IOMA | B11: 220374 | C11: 229948 | D11: 254773 | E11: 260754 | F11: 285776 | G11: 288842 | H11: 324566 | I11: 325357 | J11: 335574 | K11: 335574 | L11: 260754 | M11: 260754
A12: Servicio Basico On Line PAMI | B12: 9286473 | C12: 8514062 | D12: 9117807 | E12: 9173479 | F12: 9361132 | G12: 9051190 | H12: 9745031 | I12: 9274503 | J12: 9473415 | K12: 9600000 | L12: 9173479 | M12: 9173479
A13: Servicio Basico On Line PAMI Imposiciones | B13: 2612360 | C13: 2472690 | D13: 2621948 | E13: 2645479 | F13: 2666197 | G13: 2487094 | H13: 2680119 | I13: 2553801 | J13: 2647447 | K13: 2647447 | L13: 2645479 | M13: 2645479
A14: se prevee un IPC de 1,5% en Julio | C14: =+C25/B25 -> 1.0239831 | D14: =+D25/C25 -> 1.0369941 | E14: =+E25/D25 -> 1.0280128 | F14: =+F25/E25 -> 1.0149833 | G14: =+G25/F25 -> 1.0159859 | H14: =+H25/G25 -> 1.0189716
A16: Variación estacional Prepagas 2025 | B16: =(+B6/#REF!) -> #REF! | C16: =(+#REF!/#REF!) -> #REF! | D16: =(+#REF!/#REF!) -> #REF! | E16: =(+#REF!/#REF!) -> #REF! | F16: =(+#REF!/#REF!) -> #REF! | G16: =(+#REF!/#REF!) -> #REF! | H16: =(+#REF!/#REF!) -> #REF! | I16: =(+#REF!/#REF!) -> #REF! | J16: =(+#REF!/#REF!) -> #REF! | ... M16: =(+#REF!/#REF!) -> #REF!
A17: Variación estacional Apross 2025 | B17: =(+B7/#REF!) -> #REF! | C17: =(+#REF!/#REF!) -> #REF! | D17: =(+#REF!/#REF!) -> #REF! | E17: =(+#REF!/#REF!) -> #REF! | F17: =(+#REF!/#REF!) -> #REF! | G17: =(+#REF!/#REF!) -> #REF! | H17: =(+#REF!/#REF!) -> #REF! | I17: =(+#REF!/#REF!) -> #REF! | J17: =(+#REF!/#REF!) -> #REF! | ... M17: =(+#REF!/#REF!) -> #REF!
A18: Variación estacional IOMA 2025 | B18: =(+B8/#REF!) -> #REF! | C18: =(+#REF!/#REF!) -> #REF! | D18: =(+#REF!/#REF!) -> #REF! | E18: =(+#REF!/#REF!) -> #REF! | F18: =(+#REF!/#REF!) -> #REF! | G18: =(+#REF!/#REF!) -> #REF! | H18: =(+#REF!/#REF!) -> #REF! | I18: =(+#REF!/#REF!) -> #REF! | J18: =(+#REF!/#REF!) -> #REF! | ... M18: =(+#REF!/#REF!) -> #REF!
A19: Variación estacional Rec Elect Prepagas 2025 | B19: =(+B9/#REF!) -> #REF! | H19: =(+#REF!/#REF!) -> #REF! | I19: =(+#REF!/#REF!) -> #REF! | J19: =(+#REF!/#REF!) -> #REF! | K19: =(+#REF!/#REF!) -> #REF! | L19: =(+#REF!/#REF!) -> #REF! | M19: =(+#REF!/#REF!) -> #REF!
A20: Variación estacional Rec Elect Apross 2025 | B20: =(+B10/#REF!) -> #REF! | H20: =(+#REF!/#REF!) -> #REF! | I20: =(+#REF!/#REF!) -> #REF! | J20: =(+#REF!/#REF!) -> #REF! | K20: =(+#REF!/#REF!) -> #REF! | L20: =(+#REF!/#REF!) -> #REF! | M20: =(+#REF!/#REF!) -> #REF!
A21: Variación estacional Rec Elect IOMA 2025 | B21: =(+B11/#REF!) -> #REF! | H21: =(+#REF!/#REF!) -> #REF! | I21: =(+#REF!/#REF!) -> #REF! | J21: =(+#REF!/#REF!) -> #REF! | K21: =(+#REF!/#REF!) -> #REF! | L21: =(+#REF!/#REF!) -> #REF! | M21: =(+#REF!/#REF!) -> #REF!
A24: REAL Precio x TRX 2025 | B24: 45658 | C24: 45689 | D24: 45747 | E24: =+D24+30 -> 45777 | F24: =+E24+30 -> 45807 | G24: =+F24+30 -> 45837 | H24: =+G24+30 -> 45867 | I24: =+H24+30 -> 45897 | J24: =+I24+30 -> 45927 | K24: =+J24+30 -> 45957 | L24: =+K24+30 -> 45987 | M24: =+L24+30 -> 46017
A25: Servicio Basico Online PREPAGAS | B25: 118 | C25: 120.83 | D25: 125.3 | E25: 128.81 | F25: 130.74 | G25: 132.83 | H25: 135.35 | I25: 137.92 | J25: 140.82 | K25: =+J25*(1+$K$34) -> 144.05886 | L25: =+K25*(1+$L$34) -> 146.94004 | M25: =+L25*(1+$M$34) -> 149.87884
A26: Servicio Basico Online APROSS | B26: 118 | C26: 120.83 | D26: 125.3 | E26: 128.81 | F26: 130.74 | G26: 132.83 | H26: 135.35 | I26: 137.92 | J26: 140.82 | K26: =+J26*(1+$K$34) -> 144.05886 | L26: =+K26*(1+$L$34) -> 146.94004 | M26: =+L26*(1+$M$34) -> 149.87884
A27: Servicio Basico Online IOMA | B27: 127.32 | C27: 130.38 | D27: 135.2 | E27: 138.99 | F27: 141.07 | G27: 143.33 | H27: 146.05 | I27: 148.82 | J27: 151.95 | K27: =+J27*(1+$K$34) -> 155.44485 | L27: =+K27*(1+$L$34) -> 158.55375 | M27: =+L27*(1+$M$34) -> 161.72482
A28: Receta Electrónica Prepagas | B28: 9.44 | C28: 9.67 | D28: 10.02 | E28: 10.3 | F28: 10.46 | G28: 10.63 | H28: 10.83 | I28: 11.03 | J28: 11.27 | K28: =+J28*(1+$K$34) -> 11.52921 | L28: =+K28*(1+$L$34) -> 11.759794 | M28: =+L28*(1+$M$34) -> 11.99499
A29: Receta Electrónica Apross | B29: 9.44 | C29: 9.67 | D29: 10.02 | E29: 10.3 | F29: 10.46 | G29: 10.63 | H29: 10.83 | I29: 11.03 | J29: 11.27 | K29: =+J29*(1+$K$34) -> 11.52921 | L29: =+K29*(1+$L$34) -> 11.759794 | M29: =+L29*(1+$M$34) -> 11.99499
A30: Receta Electrónica IOMA | B30: 10.19 | C30: 10.43 | D30: 10.82 | E30: 11.12 | F30: 11.29 | G30: 11.47 | H30: 11.68 | I30: 11.91 | J30: 12.16 | K30: =+J30*(1+$K$34) -> 12.43968 | L30: =+K30*(1+$L$34) -> 12.688474 | M30: =+L30*(1+$M$34) -> 12.942243
A31: Servicio Basico On Line PAMI | B31: 114.59 | C31: 117.34 | D31: 121.68 | E31: 125.09 | F31: 126.96 | G31: 129 | H31: 131.45 | I31: 133.94 | J31: 136.76 | K31: =+J31*(1+$K$34) -> 139.90548 | L31: =+K31*(1+$L$34) -> 142.70359 | M31: =+L31*(1+$M$34) -> 145.55766
A32: Servicio Basico On Line PAMI Imposiciones | B32: 11.84 | C32: 12.13 | D32: 12.58 | E32: 12.93 | F32: 13.13 | G32: 13.34 | H32: 13.59 | I32: 13.85 | J32: 14.14 | K32: =+J32*(1+$K$34) -> 14.46522 | L32: =+K32*(1+$L$34) -> 14.754524 | M32: =+L32*(1+$M$34) -> 15.049615
A34: IPC Indec mensual proyectado 2025 | K34: 0.023 | L34: 0.02 | M34: 0.02
A36: REAL Facturación 2025 | B36: 45658 | C36: 45689 | D36: 45747 | E36: =+D36+30 -> 45777 | F36: =+E36+30 -> 45807 | G36: =+F36+30 -> 45837 | H36: =+G36+30 -> 45867 | I36: =+H36+30 -> 45897 | J36: =+I36+30 -> 45927 | K36: =+J36+30 -> 45957 | L36: =+K36+30 -> 45987 | M36: =+L36+30 -> 46017
A37: Servicio Basico Online PREPAGAS | B37: =+B25*B6 -> 175856108 | C37: =+C25*C6 -> 1.6381116e+08 | D37: =+D25*D6 -> 1.905506e+08 | E37: =+E25*E6 -> 2.0639445e+08 | F37: =+F25*F6 -> 2.1994782e+08 | G37: =+G25*G6 -> 2.2131099e+08 | H37: =+H25*H6 -> 2.3699974e+08 | I37: =+I25*I6 -> 2.3491941e+08 | ... M37: =+M25*M6 -> 2.4015341e+08
A38: Servicio Basico Online APROSS | B38: =+B26*B7 -> 25212942 | C38: =+C26*C7 -> 22959512 | D38: =+D26*D7 -> 26111016 | E38: =+E26*E7 -> 27528758 | F38: =+F26*F7 -> 29476902 | G38: =+G26*G7 -> 30681339 | H38: =+H26*H7 -> 32623410 | I38: =+I26*I7 -> 32141980 | ... M38: =+M26*M7 -> 32031506
A39: Servicio Basico Online IOMA | B39: =+B27*B8 -> 97241923 | C39: =+C27*C8 -> 94061738 | D39: =+D27*D8 -> 1.0563541e+08 | E39: =+E27*E8 -> 1.1380237e+08 | F39: =+F27*F8 -> 1.2020603e+08 | G39: =+G27*G8 -> 1.2149324e+08 | H39: =+H27*H8 -> 1.3361968e+08 | I39: =+I27*I8 -> 1.2985438e+08 | ... M39: =+M27*M8 -> 1.3241721e+08
A40: Receta Electrónica Prepagas | B40: =+B28*B9 -> 7699292.3 | C40: =+C28*C9 -> 7708904.7 | D40: =+D28*D9 -> 9214792.8 | E40: =+E28*E9 -> 10049731 | F40: =+F28*F9 -> 10855901 | G40: =+G28*G9 -> 11028678 | H40: =+H28*H9 -> 12187551 | I40: =+I28*I9 -> 12433115 | ... M40: =+M28*M9 -> 11703536
A41: Receta Electrónica Apross | B41: =+B29*B10 -> 2016903.2 | C41: =+C29*C10 -> 1837300 | D41: =+D29*D10 -> 2088248.2 | E41: =+E29*E10 -> 2200636.2 | F41: =+F29*F10 -> 2358991.5 | G41: =+G29*G10 -> 2455455.6 | H41: =+H29*H10 -> 2610766.4 | I41: =+I29*I10 -> 2571258.4 | ... M41: =+M29*M10 -> 2562777.6
A42: Receta Electrónica IOMA | B42: =+B30*B11 -> 2245611.1 | C42: =+C30*C11 -> 2398357.6 | D42: =+D30*D11 -> 2756643.9 | E42: =+E30*E11 -> 2899584.5 | F42: =+F30*F11 -> 3226411 | G42: =+G30*G11 -> 3313017.7 | H42: =+H30*H11 -> 3790930.9 | I42: =+I30*I11 -> 3875001.9 | ... M42: =+M30*M11 -> 3374741.6
A43: Servicio Basico On Line PAMI | B43: =+B31*B12 -> 1.0641369e+09 | C43: =+C31*C12 -> 9.9904004e+08 | D43: =+D31*D12 -> 1.1094548e+09 | E43: =+E31*E12 -> 1.1475105e+09 | F43: =+F31*F12 -> 1.1884893e+09 | G43: =+G31*G12 -> 1167603510 | H43: =+H31*H12 -> 1.2809843e+09 | I43: =+I31*I12 -> 1.2422269e+09 | ... M43: =+M31*M12 -> 1.3352702e+09
A44: Servicio Basico On Line PAMI Imposiciones | B44: =+B32*B13 -> 30930342 | C44: =+C32*C13 -> 29993730 | D44: =+D32*D13 -> 32984106 | E44: =+E32*E13 -> 34206043 | F44: =+F32*F13 -> 35007167 | G44: =+G32*G13 -> 33177834 | H44: =+H32*H13 -> 36422817 | I44: =+I32*I13 -> 35370144 | ... M44: =+M32*M13 -> 39813440 | N44: =SUM(B37:M44) -> 1.9539331e+10
A47: Dias hábiles 2026
A49: BDGT TRX 2026 | B49: 46023 | C49: 46054 | D49: 46112 | E49: 46142 | F49: 46172 | G49: 46202 | H49: 46232 | I49: 46262 | J49: 46292 | K49: 46322 | L49: 46352 | M49: 46382 | N49: -> IGUAL REAL A SEPT 2025 + RFC Q4 2025
A50: Servicio Basico Online PREPAGAS | B50: =+B6 -> 1490306 | C50: =+C6 -> 1355716 | D50: =+D6 -> 1520755 | E50: =+E6 -> 1602317 | F50: =+F6 -> 1682330 | G50: =+G6 -> 1666122 | H50: =+H6 -> 1751014 | I50: =+I6 -> 1703302 | ... M50: =+M6 -> 1602317
A51: Servicio Basico Online APROSS | B51: =+B7 -> 213669 | C51: =+C7 -> 190015 | D51: =+D7 -> 208388 | E51: =+E7 -> 213716 | F51: =+F7 -> 225462 | G51: =+G7 -> 230982 | H51: =+H7 -> 241030 | I51: =+I7 -> 233048 | ... M51: =+M7 -> 213716
A52: Servicio Basico Online IOMA | B52: =+B8 -> 763760 | C52: =+C8 -> 721443 | D52: =+D8 -> 781327 | E52: =+E8 -> 818781 | F52: =+F8 -> 852102 | G52: =+G8 -> 847647 | H52: =+H8 -> 914890 | I52: =+I8 -> 872560 | ... M52: =+M8 -> 818781
A53: Receta Electrónica Prepagas | B53: =+B9 -> 815603 | C53: =+C9 -> 797198 | D53: =+D9 -> 919640 | E53: =+E9 -> 975702 | F53: =+F9 -> 1037849 | G53: =+G9 -> 1037505 | H53: =+H9 -> 1125351 | I53: =+I9 -> 1127209 | ... M53: =+M9 -> 975702
A54: Receta Electrónica Apross | B54: =+B10 -> 213655 | C54: =+C10 -> 190000 | D54: =+D10 -> 208408 | E54: =+E10 -> 213654 | F54: =+F10 -> 225525 | G54: =+G10 -> 230993 | H54: =+H10 -> 241068 | I54: =+I10 -> 233115 | ... M54: =+M10 -> 213654
A55: Receta Electrónica IOMA | B55: =+B11 -> 220374 | C55: =+C11 -> 229948 | D55: =+D11 -> 254773 | E55: =+E11 -> 260754 | F55: =+F11 -> 285776 | G55: =+G11 -> 288842 | H55: =+H11 -> 324566 | I55: =+I11 -> 325357 | ... M55: =+M11 -> 260754
A56: Servicio Basico On Line PAMI | B56: =+B12 -> 9286473 | C56: =+C12 -> 8514062 | D56: =+D12 -> 9117807 | E56: =+E12 -> 9173479 | F56: =+F12 -> 9361132 | G56: =+G12 -> 9051190 | H56: =+H12 -> 9745031 | I56: =+I12 -> 9274503 | ... M56: =+M12 -> 9173479
A57: Servicio Basico On Line PAMI Imposiciones | B57: =+B13 -> 2612360 | C57: =+C13 -> 2472690 | D57: =+D13 -> 2621948 | E57: =+E13 -> 2645479 | F57: =+F13 -> 2666197 | G57: =+G13 -> 2487094 | H57: =+H13 -> 2680119 | I57: =+I13 -> 2553801 | ... M57: =+M13 -> 2645479
A58: Presentaciones Digitales | B58: 0 | C58: =+B58 -> 0 | D58: =+C58 -> 0 | E58: =+E56*E59 -> 458673.95 | F58: =+F56*F59 -> 936113.2 | G58: =+G56*G59 -> 1357678.5 | H58: =+H56*H59 -> 1949006.2 | I58: =+I56*I59 -> 2318625.8 | J58: =+J56*J59 -> 2842024.5 | K58: =+K56*K59 -> 3360000 | L58: =+L56*L59 -> 3669391.6 | M58: =+M56*M59 -> 4128065.5 | N58: desde abril se considera un 5% acumulativo mensual sobre la cant de TRX Pami
E59: 0.05 | F59: =+E59+5% -> 0.1 | G59: =+F59+5% -> 0.15 | H59: =+G59+5% -> 0.2 | I59: =+H59+5% -> 0.25 | J59: =+I59+5% -> 0.3 | K59: =+J59+5% -> 0.35 | L59: =+K59+5% -> 0.4 | M59: =+L59+5% -> 0.45
A60: BDGT Precio x TRX 2026 | B60: =+B49 -> 46023 | C60: =+C49 -> 46054 | D60: =+D49 -> 46112 | E60: =+E49 -> 46142 | F60: =+F49 -> 46172 | G60: =+G49 -> 46202 | H60: =+H49 -> 46232 | I60: =+I49 -> 46262 | ... M60: =+M49 -> 46382
A61: Servicio Basico Online PREPAGAS | B61: =+M25*(1+$B$71) -> 154.22532 | C61: =+B61*(1+$C$71) -> 158.69786 | D61: =+C61*(1+$D$71) -> 164.09359 | E61: =+D61*(1+$E$71) -> 168.36002 | F61: =+E61*(1+$F$71) -> 171.89558 | G61: =+F61*(1+$G$71) -> 176.88055 | H61: =+G61*(1+$H$71) -> 182.01009 | I61: =+H61*(1+$I$71) -> 187.28838 | J61: =+I61*(1+$J$71) -> 192.71974 | K61: =+J61*(1+$K$71) -> 198.30862 | L61: =+K61*(1+$L$71) -> 204.05957 | M61: =+L61*(1+$M$71) -> 209.97729 | N61: =+M61/M25 -> 1.4009803
A62: Servicio Basico Online APROSS | B62: =+M26*(1+$B$71) -> 154.22532 | C62: =+B62*(1+$C$71) -> 158.69786 | D62: =+C62*(1+$D$71) -> 164.09359 | E62: =+D62*(1+$E$71) -> 168.36002 | F62: =+E62*(1+$F$71) -> 171.89558 | G62: =+F62*(1+$G$71) -> 176.88055 | H62: =+G62*(1+$H$71) -> 182.01009 | I62: =+H62*(1+$I$71) -> 187.28838 | J62: =+I62*(1+$J$71) -> 192.71974 | K62: =+J62*(1+$K$71) -> 198.30862 | L62: =+K62*(1+$L$71) -> 204.05957 | M62: =+L62*(1+$M$71) -> 209.97729 | N62: =+M62/M26 -> 1.4009803
A63: Servicio Basico Online IOMA | B63: =+M27*(1+$B$71) -> 166.41484 | C63: =+B63*(1+$C$71) -> 171.24087 | D63: =+C63*(1+$D$71) -> 177.06306 | E63: =+D63*(1+$E$71) -> 181.6667 | F63: =+E63*(1+$F$71) -> 185.4817 | G63: =+F63*(1+$G$71) -> 190.86067 | H63: =+G63*(1+$H$71) -> 196.39563 | I63: =+H63*(1+$I$71) -> 202.0911 | J63: =+I63*(1+$J$71) -> 207.95175 | K63: =+J63*(1+$K$71) -> 213.98235 | L63: =+K63*(1+$L$71) -> 220.18784 | M63: =+L63*(1+$M$71) -> 226.57328 | N63: =+M63/M27 -> 1.4009803
A64: Receta Electrónica Prepagas | B64: =+M28*(1+$B$71) -> 12.342845 | C64: =+B64*(1+$C$71) -> 12.700787 | D64: =+C64*(1+$D$71) -> 13.132614 | E64: =+D64*(1+$E$71) -> 13.474062 | F64: =+E64*(1+$F$71) -> 13.757017 | G64: =+F64*(1+$G$71) -> 14.155971 | H64: =+G64*(1+$H$71) -> 14.566494 | I64: =+H64*(1+$I$71) -> 14.988922 | J64: =+I64*(1+$J$71) -> 15.423601 | K64: =+J64*(1+$K$71) -> 15.870885 | L64: =+K64*(1+$L$71) -> 16.331141 | M64: =+L64*(1+$M$71) -> 16.804744 | N64: =+M64/M28 -> 1.4009803
A65: Receta Electrónica Apross | B65: =+M29*(1+$B$71) -> 12.342845 | C65: =+B65*(1+$C$71) -> 12.700787 | D65: =+C65*(1+$D$71) -> 13.132614 | E65: =+D65*(1+$E$71) -> 13.474062 | F65: =+E65*(1+$F$71) -> 13.757017 | G65: =+F65*(1+$G$71) -> 14.155971 | H65: =+G65*(1+$H$71) -> 14.566494 | I65: =+H65*(1+$I$71) -> 14.988922 | J65: =+I65*(1+$J$71) -> 15.423601 | K65: =+J65*(1+$K$71) -> 15.870885 | L65: =+K65*(1+$L$71) -> 16.331141 | M65: =+L65*(1+$M$71) -> 16.804744 | N65: =+M65/M29 -> 1.4009803
A66: Receta Electrónica IOMA | B66: =+M30*(1+$B$71) -> 13.317568 | C66: =+B66*(1+$C$71) -> 13.703778 | D66: =+C66*(1+$D$71) -> 14.169706 | E66: =+D66*(1+$E$71) -> 14.538118 | F66: =+E66*(1+$F$71) -> 14.843419 | G66: =+F66*(1+$G$71) -> 15.273878 | H66: =+G66*(1+$H$71) -> 15.71682 | I66: =+H66*(1+$I$71) -> 16.172608 | J66: =+I66*(1+$J$71) -> 16.641614 | K66: =+J66*(1+$K$71) -> 17.124221 | L66: =+K66*(1+$L$71) -> 17.620823 | M66: =+L66*(1+$M$71) -> 18.131827 | N66: =+M66/M30 -> 1.4009803
A67: Servicio Basico On Line PAMI | B67: =+M31*(1+$B$71) -> 149.77883 | C67: =+B67*(1+$C$71) -> 154.12242 | D67: =+C67*(1+$D$71) -> 159.36258 | E67: =+D67*(1+$E$71) -> 163.50601 | F67: =+E67*(1+$F$71) -> 166.93964 | G67: =+F67*(1+$G$71) -> 171.78088 | H67: =+G67*(1+$H$71) -> 176.76253 | I67: =+H67*(1+$I$71) -> 181.88864 | J67: =+I67*(1+$J$71) -> 187.16341 | K67: =+J67*(1+$K$71) -> 192.59115 | L67: =+K67*(1+$L$71) -> 198.1763 | M67: =+L67*(1+$M$71) -> 203.92341 | N67: =+M67/M31 -> 1.4009803
A68: Servicio Basico On Line PAMI Imposiciones | B68: =+M32*(1+$B$71) -> 15.486054 | C68: =+B68*(1+$C$71) -> 15.935149 | D68: =+C68*(1+$D$71) -> 16.476944 | E68: =+D68*(1+$E$71) -> 16.905345 | F68: =+E68*(1+$F$71) -> 17.260357 | G68: =+F68*(1+$G$71) -> 17.760908 | H68: =+G68*(1+$H$71) -> 18.275974 | I68: =+H68*(1+$I$71) -> 18.805977 | J68: =+I68*(1+$J$71) -> 19.35135 | K68: =+J68*(1+$K$71) -> 19.91254 | L68: =+K68*(1+$L$71) -> 20.490003 | M68: =+L68*(1+$M$71) -> 21.084213 | N68: =+M68/M32 -> 1.4009803
A69: Presentaciones Digitales | B69: =+B67*50% -> 74.889417 | C69: =+C67*50% -> 77.06121 | D69: =+D67*50% -> 79.681291 | E69: =+E67*50% -> 81.753005 | F69: =+F67*50% -> 83.469818 | G69: =+G67*50% -> 85.890442 | H69: =+H67*50% -> 88.381265 | I69: =+I67*50% -> 90.944322 | ... M69: =+M67*50% -> 101.9617
A71: IPC Indec mensual proyectado 2026 | B71: =+ipcene -> 0.029 | C71: =+'REAL-BDGT2026'!J196 -> 0.029 | D71: =+'REAL-BDGT2026'!K196 -> 0.034 | E71: =+'REAL-BDGT2026'!L196 -> 0.026 | F71: =+'REAL-BDGT2026'!M196 -> 0.021 | G71: =+'REAL-BDGT2026'!N196 -> 0.029 | H71: =+'REAL-BDGT2026'!O196 -> 0.029 | I71: =+'REAL-BDGT2026'!P196 -> 0.029 | J71: =+'REAL-BDGT2026'!Q196 -> 0.029 | ... M71: =+'REAL-BDGT2026'!T196 -> 0.029
B72: =1*(1+B71) -> 1.029 | C72: =+B72*(1+C71) -> 1.058841 | D72: =+C72*(1+D71) -> 1.0948416 | E72: =+D72*(1+E71) -> 1.1233075 | F72: =+E72*(1+F71) -> 1.1468969 | G72: =+F72*(1+G71) -> 1.1801569 | H72: =+G72*(1+H71) -> 1.2143815 | I72: =+H72*(1+I71) -> 1.2495986 | J72: =+I72*(1+J71) -> 1.2858369 | ... M72: =+L72*(1+M71) -> 1.4009803 | N72: =+M72-1 -> 0.40098025 | O72: inflación anual
A74: BDGT Facturación 2026 | B74: =+B60 -> 46023 | C74: =+C60 -> 46054 | D74: =+D60 -> 46112 | E74: =+E60 -> 46142 | F74: =+F60 -> 46172 | G74: =+G60 -> 46202 | H74: =+H60 -> 46232 | I74: =+I60 -> 46262 | ... M74: =+M60 -> 46382
A75: Servicio Basico Online PREPAGAS | B75: =+B50*B61 -> 2.2984293e+08 | C75: =+C50*C61 -> 2.1514923e+08 | D75: =+D50*D61 -> 2.4954614e+08 | E75: =+E50*E61 -> 2.6976612e+08 | F75: =+F50*F61 -> 2.8918509e+08 | G75: =+G50*G61 -> 2.9470458e+08 | H75: =+H50*H61 -> 3.1870221e+08 | I75: =+I50*I61 -> 3.1900867e+08 | ... M75: =+M50*M61 -> 3.3645019e+08 | N75: =SUM(B75:M75) -> 3.5306829e+09
A76: Servicio Basico Online APROSS | B76: =+B51*B62 -> 32953171 | C76: =+C51*C62 -> 30154974 | D76: =+D51*D62 -> 34195134 | E76: =+E51*E62 -> 35981230 | F76: =+F51*F62 -> 38755921 | G76: =+G51*G62 -> 40856223 | H76: =+H51*H62 -> 43869891 | I76: =+I51*I62 -> 43647182 | ... M76: =+M51*M62 -> 44875507 | N76: =SUM(B76:M76) -> 4.8338435e+08
A77: Servicio Basico Online IOMA | B77: =+B52*B63 -> 1.27101e+08 | C77: =+C52*C63 -> 1.2354053e+08 | D77: =+D52*D63 -> 1.3834415e+08 | E77: =+E52*E63 -> 1.4874524e+08 | F77: =+F52*F63 -> 1.5804933e+08 | G77: =+G52*G63 -> 1.6178248e+08 | H77: =+H52*H63 -> 1.796804e+08 | I77: =+I52*I63 -> 1.7633661e+08 | ... M77: =+M52*M63 -> 1.855139e+08 | N77: =SUM(B77:M77) -> 1.95898e+09
A78: Receta Electrónica Prepagas | B78: =+B53*B64 -> 10066861 | C78: =+C53*C64 -> 10125042 | D78: =+D53*D64 -> 12077277 | E78: =+E53*E64 -> 13146669 | F78: =+F53*F64 -> 14277707 | G78: =+G53*G64 -> 14686891 | H78: =+H53*H64 -> 16392419 | I78: =+I53*I64 -> 16895648 | ... M78: =+M53*M64 -> 16396423 | N78: =SUM(B78:M78) -> 1.7620708e+08
A79: Receta Electrónica Apross | B79: =+B54*B65 -> 2637110.5 | C79: =+C54*C65 -> 2413149.6 | D79: =+D54*D65 -> 2736941.8 | E79: =+E54*E65 -> 2878787.2 | F79: =+F54*F65 -> 3102551.3 | G79: =+G54*G65 -> 3269930.2 | H79: =+H54*H65 -> 3511515.6 | I79: =+I54*I65 -> 3494142.6 | ... M79: =+M54*M65 -> 3590400.8 | N79: =SUM(B79:M79) -> 38416078
A80: Receta Electrónica IOMA | B80: =+B55*B66 -> 2934845.8 | C80: =+C55*C66 -> 3151156.3 | D80: =+D55*D66 -> 3610058.5 | E80: =+E55*E66 -> 3790872.5 | F80: =+F55*F66 -> 4241892.9 | G80: =+G55*G66 -> 4411737.5 | H80: =+H55*H66 -> 5101145.6 | I80: =+I55*I66 -> 5261871.3 | ... M80: =+M55*M66 -> 4727946.4 | N80: =SUM(B80:M80) -> 53157163
A81: Servicio Basico On Line PAMI | B81: =+B56*B67 -> 1.3909171e+09 | C81: =+C56*C67 -> 1.3122078e+09 | D81: =+D56*D67 -> 1.4530373e+09 | E81: =+E56*E67 -> 1.4999189e+09 | F81: =+F56*F67 -> 1.562744e+09 | G81: =+G56*G67 -> 1.5548214e+09 | H81: =+H56*H67 -> 1.7225563e+09 | I81: =+I56*I67 -> 1.6869268e+09 | ... M81: =+M56*M67 -> 1.8706871e+09 | N81: =SUM(B81:M81) -> 1.9493735e+10
A82: Servicio Basico On Line PAMI Imposiciones | B82: =+B57*B68 -> 40455147 | C82: =+C57*C68 -> 39402684 | D82: =+D57*D68 -> 43201691 | E82: =+E57*E68 -> 44722735 | F82: =+F57*F68 -> 46019512 | G82: =+G57*G68 -> 44173046 | H82: =+H57*H68 -> 48981785 | I82: =+I57*I68 -> 48026723 | ... M82: =+M57*M68 -> 55777844 | N82: =SUM(B82:M82) -> 5.6891611e+08 | O82: =SUM(N75:N82) -> 2.6303478e+10 | P82: =+O82/N117-1 -> 0.34905265
A83: Presentaciones Digitales | B83: =+B58*B69 -> 0 | C83: =+C58*C69 -> 0 | D83: =+D58*D69 -> 0 | E83: =+E58*E69 -> 37497974 | F83: =+F58*F69 -> 78137198 | G83: =+G58*G69 -> 1.1661161e+08 | H83: =+H58*H69 -> 1.7225563e+08 | I83: =+I58*I69 -> 2.1086585e+08 | ... M83: =+M58*M69 -> 4.209046e+08 | N83: =SUM(B83:M83) -> 1.9893807e+09 | P83: crec s/pres digitales
A84: Total Facturación BDGT FLK 2026 | B84: =SUM(B75:B83) -> 1.8369082e+09 | C84: =SUM(C75:C83) -> 1.7361446e+09 | D84: =SUM(D75:D83) -> 1.9367487e+09 | E84: =SUM(E75:E83) -> 2.0564486e+09 | F84: =SUM(F75:F83) -> 2.1945132e+09 | G84: =SUM(G75:G83) -> 2.2353179e+09 | H84: =SUM(H75:H83) -> 2.5110513e+09 | I84: =SUM(I75:I83) -> 2.5104635e+09 | ... M84: =SUM(M75:M83) -> 2.9389239e+09 | N84: =SUM(B84:M84) -> 2.8292859e+10
A85: Gap TRX
A86: Servicio Basico Online PREPAGAS | N86: =SUM(B86:M86) -> 0
A87: Servicio Basico Online APROSS | N87: =SUM(B87:M87) -> 0
A88: Servicio Basico Online IOMA | N88: =SUM(B88:M88) -> 0
A89: Receta Electrónica Prepagas | N89: =SUM(B89:M89) -> 0
A90: Receta Electrónica Apross | N90: =SUM(B90:M90) -> 0
A91: Receta Electrónica IOMA | N91: =SUM(B91:M91) -> 0
A92: Servicio Basico On Line PAMI | N92: =SUM(B92:M92) -> 0
A93: Servicio Basico On Line PAMI Imposiciones | N93: =SUM(B93:M93) -> 0
A95: Gap Precio
A96: Servicio Basico Online PREPAGAS | N96: =SUM(B96:M96) -> 0
A97: Servicio Basico Online APROSS | N97: =SUM(B97:M97) -> 0
A98: Servicio Basico Online IOMA | N98: =SUM(B98:M98) -> 0
A99: Receta Electrónica Prepagas | N99: =SUM(B99:M99) -> 0
A100: Receta Electrónica Apross | N100: =SUM(B100:M100) -> 0
A101: Receta Electrónica IOMA | N101: =SUM(B101:M101) -> 0
A102: Servicio Basico On Line PAMI | N102: =SUM(B102:M102) -> 0
A103: Servicio Basico On Line PAMI Imposiciones | N103: =SUM(B103:M103) -> 0
A105: Gap Facturación
A106: Servicio Basico Online PREPAGAS | N106: =SUM(B106:M106) -> 0
A107: Servicio Basico Online APROSS | N107: =SUM(B107:M107) -> 0
A108: Servicio Basico Online IOMA | N108: =SUM(B108:M108) -> 0
A109: Receta Electrónica Prepagas | N109: =SUM(B109:M109) -> 0
A110: Receta Electrónica Apross | N110: =SUM(B110:M110) -> 0
A111: Receta Electrónica IOMA | N111: =SUM(B111:M111) -> 0
A112: Servicio Basico On Line PAMI | N112: =SUM(B112:M112) -> 0
A113: Servicio Basico On Line PAMI Imposiciones | N113: =SUM(B113:M113) -> 0
B114: =SUM(B106:B113) -> 0 | C114: =SUM(C106:C113) -> 0 | D114: =SUM(D106:D113) -> 0 | E114: =SUM(E106:E113) -> 0 | F114: =SUM(F106:F113) -> 0 | G114: =SUM(G106:G113) -> 0 | H114: =SUM(H106:H113) -> 0 | I114: =SUM(I106:I113) -> 0 | ... M114: =SUM(M106:M113) -> 0
...

Sheet Astra
A2: Facturación Astra - Programa Elegir Salud | B2: Septiembre 2025 (*) Real | F2: Octubre 2025 RFC | I2: Noviembre 2025 RFC | L2: Diciembre 2025 RFC | O2: Enero 2026 RFC | R2: Febrero 2026 RFC | U2: Marzo 2026 RFC | X2: Abril 2026 RFC | AA2: Mayo 2026 RFC | AD2: Junio 2026 RFC | AG2: Julio 2026 RFC | AJ2: Agosto 2026 RFC | AM2: Septiembre 2026 RFC | AP2: Octubre 2026 RFC | AS2: Noviembre 2026 RFC | AV2: Diciembre 2026 RFC
B3: Cantidad | C3: Precio Unit. Ago-25 | D3: Precio Unit. Sept-25 | E3: Total a Facturar | F3: Cantidad | G3: Precio Unitario | H3: Total | I3: Cantidad | J3: Precio Unitario | K3: Total | L3: Cantidad | M3: Precio Unitario | N3: Total | O3: Cantidad | P3: Precio Unitario | Q3: Total | R3: Cantidad | S3: Precio Unitario | T3: Total | U3: Cantidad | V3: Precio Unitario | W3: Total | X3: Cantidad | Y3: Precio Unitario | Z3: Total | AA3: Cantidad | AB3: Precio Unitario | AC3: Total | AD3: Cantidad | AE3: Precio Unitario | AF3: Total | AG3: Cantidad | AH3: Precio Unitario | AI3: Total | AJ3: Cantidad | AK3: Precio Unitario | AL3: Total | AM3: Cantidad | AN3: Precio Unitario | AO3: Total | AP3: Cantidad | AQ3: Precio Unitario | AR3: Total | AS3: Cantidad | AT3: Precio Unitario | AU3: Total | AV3: Cantidad | AW3: Precio Unitario | AX3: Total
A4: Operación | B4: 1 | C4: 7134253.4 | D4: =C4*$D$15 -> 7248401.4 | E4: =B4*D4 -> 7248401.4 | F4: =+B4 -> 1 | G4: =+D4*$G$15 -> 7407866.3 | H4: =+G4*F4 -> 7407866.3 | I4: =+F4 -> 1 | J4: =+G4*$J$15 -> 7578247.2 | K4: =+J4*I4 -> 7578247.2 | L4: =+I4 -> 1 | M4: =+J4*$M$15 -> 7729812.1 | N4: =+M4*L4 -> 7729812.1 | O4: =+L4 -> 1 | P4: =+M4*$P$15 -> 7884408.4 | Q4: =+P4*O4 -> 7884408.4 | R4: =+O4 -> 1 | S4: =+P4*$S$15 -> 8113056.2 | T4: =+S4*R4 -> 8113056.2 | U4: =+R4 -> 1 | V4: =+S4*V15 -> 8348334.8 | W4: =+V4*U4 -> 8348334.8 | X4: =+U4 -> 1 | Y4: =+V4*Y15 -> 8632178.2 | Z4: =+Y4*X4 -> 8632178.2 | AA4: =+X4 -> 1 | AB4: =+Y4*AB15 -> 8856614.9 | AC4: =+AB4*AA4 -> 8856614.9 | AD4: =+AA4 -> 1 | AE4: =+AB4*AE15 -> 9042603.8 | AF4: =+AE4*AD4 -> 9042603.8 | AG4: =+AD4 -> 1 | AH4: =+AE4*AH15 -> 9304839.3 | AI4: =+AH4*AG4 -> 9304839.3 | AJ4: =+AG4 -> 1 | AK4: =+AH4*AK15 -> 9574679.6 | AL4: =+AK4*AJ4 -> 9574679.6 | AM4: =+AJ4 -> 1 | AN4: =+AK4*AN15 -> 9852345.3 | AO4: =+AN4*AM4 -> 9852345.3 | AP4: =+AM4 -> 1 | AQ4: =+AN4*AQ15 -> 10138063 | AR4: =+AQ4*AP4 -> 10138063 | AS4: =+AP4 -> 1 | AT4: =+AQ4*AT15 -> 10432067 | AU4: =+AT4*AS4 -> 10432067 | AV4: =+AS4 -> 1 | AW4: =+AT4*AW15 -> 10734597 | AX4: =+AW4*AV4 -> 10734597
A5: Cápitas Activas Adicionales a 12,000 | B5: 4299 | C5: 563.05874 | D5: =C5*$D$15 -> 572.06768 | E5: =B5*D5 -> 2459319 | F5: =+B5 -> 4299 | G5: =+D5*$G$15 -> 584.65317 | H5: =+G5*F5 -> 2513424 | I5: =+F5 -> 4299 | J5: =+G5*$J$15 -> 598.1002 | K5: =+J5*I5 -> 2571232.7 | L5: =+I5 -> 4299 | M5: =+J5*$M$15 -> 610.0622 | N5: =+M5*L5 -> 2622657.4 | O5: =+L5 -> 4299 | P5: =+M5*$P$15 -> 622.26344 | Q5: =+P5*O5 -> 2675110.5 | R5: =+O5 -> 4299 | S5: =+P5*$S$15 -> 640.30908 | T5: =+S5*R5 -> 2752688.8 | U5: =+R5 -> 4299 | V5: =+S5*V15 -> 658.87805 | W5: =+V5*U5 -> 2832516.7 | X5: =+U5 -> 4299 | Y5: =+V5*Y15 -> 681.2799 | Z5: =+Y5*X5 -> 2928822.3 | AA5: =+X5 -> 4299 | AB5: =+Y5*AB15 -> 698.99318 | AC5: =+AB5*AA5 -> 3004971.7 | AD5: =+AA5 -> 4299 | AE5: =+AB5*AE15 -> 713.67204 | AF5: =+AE5*AD5 -> 3068076.1 | AG5: =+AD5 -> 4299 | AH5: =+AE5*AH15 -> 734.36852 | AI5: =+AH5*AG5 -> 3157050.3 | AJ5: =+AG5 -> 4299 | AK5: =+AH5*AK15 -> 755.66521 | AL5: =+AK5*AJ5 -> 3248604.7 | AM5: =+AJ5 -> 4299 | AN5: =+AK5*AN15 -> 777.5795 | AO5: =+AN5*AM5 -> 3342814.3 | AP5: =+AM5 -> 4299 | AQ5: =+AN5*AQ15 -> 800.12931 | AR5: =+AQ5*AP5 -> 3439755.9 | AS5: =+AP5 -> 4299 | AT5: =+AQ5*AT15 -> 823.33306 | AU5: =+AT5*AS5 -> 3539508.8 | AV5: =+AS5 -> 4299 | AW5: =+AT5*AW15 -> 847.20972 | AX5: =+AW5*AV5 -> 3642154.6
A6: Auditoría basada en Alertas Tempranas | B6: 1 | C6: 632964.57 | D6: =C6*$D$15 -> 643092 | E6: =B6*D6 -> 643092 | F6: =+B6 -> 1 | G6: =+D6*$G$15 -> 657240.02 | H6: =+G6*F6 -> 657240.02 | I6: =+F6 -> 1 | J6: =+G6*$J$15 -> 672356.54 | K6: =+J6*I6 -> 672356.54 | L6: =+I6 -> 1 | M6: =+J6*$M$15 -> 685803.68 | N6: =+M6*L6 -> 685803.68 | O6: =+L6 -> 1 | P6: =+M6*$P$15 -> 699519.75 | Q6: =+P6*O6 -> 699519.75 | R6: =+O6 -> 1 | S6: =+P6*$S$15 -> 719805.82 | T6: =+S6*R6 -> 719805.82 | U6: =+R6 -> 1 | V6: =+S6*V15 -> 740680.19 | W6: =+V6*U6 -> 740680.19 | X6: =+U6 -> 1 | Y6: =+V6*Y15 -> 765863.32 | Z6: =+Y6*X6 -> 765863.32 | AA6: =+X6 -> 1 | AB6: =+Y6*AB15 -> 785775.76 | AC6: =+AB6*AA6 -> 785775.76 | AD6: =+AA6 -> 1 | AE6: =+AB6*AE15 -> 802277.05 | AF6: =+AE6*AD6 -> 802277.05 | AG6: =+AD6 -> 1 | AH6: =+AE6*AH15 -> 825543.09 | AI6: =+AH6*AG6 -> 825543.09 | AJ6: =+AG6 -> 1 | AK6: =+AH6*AK15 -> 849483.84 | AL6: =+AK6*AJ6 -> 849483.84 | AM6: =+AJ6 -> 1 | AN6: =+AK6*AN15 -> 874118.87 | AO6: =+AN6*AM6 -> 874118.87 | AP6: =+AM6 -> 1 | AQ6: =+AN6*AQ15 -> 899468.32 | AR6: =+AQ6*AP6 -> 899468.32 | AS6: =+AP6 -> 1 | AT6: =+AQ6*AT15 -> 925552.9 | AU6: =+AT6*AS6 -> 925552.9 | AV6: =+AS6 -> 1 | AW6: =+AT6*AW15 -> 952393.93 | AX6: =+AW6*AV6 -> 952393.93
A7: Supervisor de Cutomer Service – Valor Horario por Recurso | B7: 34 | C7: 31106.733 | D7: =C7*$D$15 -> 31604.44 | E7: =B7*D7 -> 1074551 | F7: =+B7 -> 34 | G7: =+D7*$G$15 -> 32299.738 | H7: =+G7*F7 -> 1098191.1 | I7: =+F7 -> 34 | J7: =+G7*$J$15 -> 33042.632 | K7: =+J7*I7 -> 1123449.5 | L7: =+I7 -> 34 | M7: =+J7*$M$15 -> 33703.485 | N7: =+M7*L7 -> 1145918.5 | O7: =+L7 -> 34 | P7: =+M7*$P$15 -> 34377.554 | Q7: =+P7*O7 -> 1168836.8 | R7: =+O7 -> 34 | S7: =+P7*$S$15 -> 35374.503 | T7: =+S7*R7 -> 1202733.1 | U7: =+R7 -> 34 | V7: =+S7*V15 -> 36400.364 | W7: =+V7*U7 -> 1237612.4 | X7: =+U7 -> 34 | Y7: =+V7*Y15 -> 37637.976 | Z7: =+Y7*X7 -> 1279691.2 | AA7: =+X7 -> 34 | AB7: =+Y7*AB15 -> 38616.564 | AC7: =+AB7*AA7 -> 1312963.2 | AD7: =+AA7 -> 34 | AE7: =+AB7*AE15 -> 39427.512 | AF7: =+AE7*AD7 -> 1340535.4 | AG7: =+AD7 -> 34 | AH7: =+AE7*AH15 -> 40570.909 | AI7: =+AH7*AG7 -> 1379410.9 | AJ7: =+AG7 -> 34 | AK7: =+AH7*AK15 -> 41747.466 | AL7: =+AK7*AJ7 -> 1419413.8 | AM7: =+AJ7 -> 34 | AN7: =+AK7*AN15 -> 42958.142 | AO7: =+AN7*AM7 -> 1460576.8 | AP7: =+AM7 -> 34 | AQ7: =+AN7*AQ15 -> 44203.928 | AR7: =+AQ7*AP7 -> 1502933.6 | AS7: =+AP7 -> 34 | AT7: =+AQ7*AT15 -> 45485.842 | AU7: =+AT7*AS7 -> 1546518.6 | AV7: =+AS7 -> 34 | AW7: =+AT7*AW15 -> 46804.932 | AX7: =+AW7*AV7 -> 1591367.7
A8: Auditoría Digital - Servicio Base (Bonificado 50%) | B8: 1 | C8: 1164072.9 | D8: =C8*$D$15 -> 1182698 | E8: =(B8*D8)/2 -> 591349.01 | F8: =+B8 -> 1 | G8: =+D8*$G$15 -> 1208717.4 | H8: =+G8*F8*0.5 -> 604358.69 | I8: =+F8 -> 1 | J8: =+G8*$J$15 -> 1236517.9 | K8: =+J8*I8*0.5 -> 618258.94 | L8: =+I8 -> 1 | M8: =+J8*$M$15 -> 1261248.2 | N8: =+M8*L8*0.5 -> 630624.12 | O8: =+L8 -> 1 | P8: =+M8*$P$15 -> 1286473.2 | Q8: =+P8*O8*0.5 -> 643236.6 | R8: =+O8 -> 1 | S8: =+P8*$S$15 -> 1323780.9 | T8: =+S8*R8*0.5 -> 661890.47 | U8: =+R8 -> 1 | V8: =+S8*V15 -> 1362170.6 | W8: =+V8*U8*0.5 -> 681085.29 | X8: =+U8 -> 1 | Y8: =+V8*Y15 -> 1408484.4 | Z8: =+Y8*X8*0.5 -> 704242.19 | AA8: =+X8 -> 1 | AB8: =+Y8*AB15 -> 1445105 | AC8: =+AB8*AA8*0.5 -> 722552.49 | AD8: =+AA8 -> 1 | AE8: =+AB8*AE15 -> 1475452.2 | AF8: =+AE8*AD8*0.5 -> 737726.09 | AG8: =+AD8 -> 1 | AH8: =+AE8*AH15 -> 1518240.3 | AI8: =+AH8*AG8*0.5 -> 759120.14 | AJ8: =+AG8 -> 1 | AK8: =+AH8*AK15 -> 1562269.3 | AL8: =+AK8*AJ8*0.5 -> 781134.63 | AM8: =+AJ8 -> 1 | AN8: =+AK8*AN15 -> 1607575.1 | AO8: =+AN8*AM8*0.5 -> 803787.53 | AP8: =+AM8 -> 1 | AQ8: =+AN8*AQ15 -> 1654194.7 | AR8: =+AQ8*AP8*0.5 -> 827097.37 | AS8: =+AP8 -> 1 | AT8: =+AQ8*AT15 -> 1702166.4 | AU8: =+AT8*AS8*0.5 -> 851083.2 | AV8: =+AS8 -> 1 | AW8: =+AT8*AW15 -> 1751529.2 | AX8: =+AW8*AV8*0.5 -> 875764.61
A9: Auditoría Digital - Cápitas Adicionales (Bonificado 50%) | B9: 4299 | C9: 97.084123 | D9: =C9*D15 -> 98.637469 | E9: =(B9*D9)/2 -> 212021.24 | F9: =+B9 -> 4299 | G9: =+D9*$G$15 -> 100.80749 | H9: =+G9*F9*0.5 -> 216685.71 | I9: =+F9 -> 4299 | J9: =+G9*$J$15 -> 103.12607 | K9: =+J9*I9*0.5 -> 221669.48 | L9: =+I9 -> 4299 | M9: =+J9*$M$15 -> 105.18859 | N9: =+M9*L9*0.5 -> 226102.87 | O9: =+L9 -> 4299 | P9: =+M9*$P$15 -> 107.29236 | Q9: =+P9*O9*0.5 -> 230624.92 | R9: =+O9 -> 4299 | S9: =+P9*$S$15 -> 110.40384 | T9: =+S9*R9*0.5 -> 237313.05 | U9: =+R9 -> 4299 | V9: =+S9*V15 -> 113.60555 | W9: =+V9*U9*0.5 -> 244195.13 | X9: =+U9 -> 4299 | Y9: =+V9*Y15 -> 117.46814 | Z9: =+Y9*X9*0.5 -> 252497.76 | AA9: =+X9 -> 4299 | AB9: =+Y9*AB15 -> 120.52231 | AC9: =+AB9*AA9*0.5 -> 259062.7 | AD9: =+AA9 -> 4299 | AE9: =+AB9*AE15 -> 123.05328 | AF9: =+AE9*AD9*0.5 -> 264503.02 | AG9: =+AD9 -> 4299 | AH9: =+AE9*AH15 -> 126.62182 | AI9: =+AH9*AG9*0.5 -> 272173.61 | AJ9: =+AG9 -> 4299 | AK9: =+AH9*AK15 -> 130.29385 | AL9: =+AK9*AJ9*0.5 -> 280066.64 | AM9: =+AJ9 -> 4299 | AN9: =+AK9*AN15 -> 134.07238 | AO9: =+AN9*AM9*0.5 -> 288188.57 | AP9: =+AM9 -> 4299 | AQ9: =+AN9*AQ15 -> 137.96048 | AR9: =+AQ9*AP9*0.5 -> 296546.04 | AS9: =+AP9 -> 4299 | AT9: =+AQ9*AT15 -> 141.96133 | AU9: =+AT9*AS9*0.5 -> 305145.88 | AV9: =+AS9 -> 4299 | AW9: =+AT9*AW15 -> 146.07821 | AX9: =+AW9*AV9*0.5 -> 313995.11
A10: Operadores Call Center Beneficiarios Suma Fija Agosto (**) | B10: 3 | D10: 40000 | E10: =(B10*D10) -> 120000 | F10: =+B10 -> 3 | G10: 46000 | H10: =+G10*F10 -> 138000 | I10: =+F10 -> 3 | J10: =+G10 -> 46000 | K10: =+J10*I10 -> 138000 | L10: =+I10 -> 3 | M10: =+J10 -> 46000 | N10: =+M10*L10 -> 138000 | Q10: =+P10*O10 -> 0 | R10: =+O10 -> 0 | S10: =+P10*$S$15 -> 0 | T10: =+S10*R10 -> 0 | U10: =+R10 -> 0 | X10: =+U10 -> 0 | AA10: =+X10 -> 0 | AD10: =+AA10 -> 0 | AG10: =+AD10 -> 0 | AJ10: =+AG10 -> 0 | AM10: =+AJ10 -> 0 | AP10: =+AM10 -> 0 | AS10: =+AP10 -> 0 | AV10: =+AS10 -> 0
A11: Operadores Call Center Beneficiarios (**) | B11: 3 | D11: 2553412.7 | E11: =(B11*D11) -> 7660238.1 | F11: =+B11 -> 3 | G11: =+D11+24790.41 -> 2578203.1 | H11: =+G11*F11 -> 7734609.3 | I11: =+F11 -> 3 | J11: =+G11+24790.41 -> 2602993.5 | K11: =+J11*I11 -> 7808980.6 | L11: =+I11 -> 3 | M11: =+J11+24790.41 -> 2627783.9 | N11: =+M11*L11 -> 7883351.8 | O11: =+L11 -> 3 | P11: =+M11*$P$16 -> 2654061.8 | Q11: =+P11*O11 -> 7962185.3 | R11: =+O11 -> 3 | S11: =+P11*$S$16 -> 2680602.4 | T11: =+S11*R11 -> 8041807.2 | U11: =+R11 -> 3 | V11: =+S11*V16 -> 2707408.4 | W11: =+V11*U11 -> 8122225.2 | X11: =+U11 -> 3 | Y11: =+V11*Y16 -> 2734482.5 | Z11: =+Y11*X11 -> 8203447.5 | AA11: =+X11 -> 3 | AB11: =+Y11*AB16 -> 2761827.3 | AC11: =+AB11*AA11 -> 8285482 | AD11: =+AA11 -> 3 | AE11: =+AB11*AE16 -> 2789445.6 | AF11: =+AE11*AD11 -> 8368336.8 | AG11: =+AD11 -> 3 | AH11: =+AE11*AH16 -> 2817340 | AI11: =+AH11*AG11 -> 8452020.1 | AJ11: =+AG11 -> 3 | AK11: =+AH11*AK16 -> 2845513.4 | AL11: =+AK11*AJ11 -> 8536540.3 | AM11: =+AJ11 -> 3 | AN11: =+AK11*AN16 -> 2873968.6 | AO11: =+AN11*AM11 -> 8621905.8 | AP11: =+AM11 -> 3 | AQ11: =+AN11*AQ16 -> 2902708.3 | AR11: =+AQ11*AP11 -> 8708124.8 | AS11: =+AP11 -> 3 | AT11: =+AQ11*AT16 -> 2931735.4 | AU11: =+AT11*AS11 -> 8795206.1 | AV11: =+AS11 -> 3 | AW11: =+AT11*AW16 -> 2961052.7 | AX11: =+AW11*AV11 -> 8883158.1
A12: Total | E12: =SUM(E4:E11) -> 20008972 | H12: =SUM(H4:H11) -> 20370375 | K12: =SUM(K4:K11) -> 20732195 | N12: =SUM(N4:N11) -> 21062270 | Q12: =SUM(Q4:Q11) -> 21263922 | T12: =SUM(T4:T11) -> 21729295 | W12: =SUM(W4:W11) -> 22206650 | Z12: =SUM(Z4:Z11) -> 22766742 | AC12: =SUM(AC4:AC11) -> 23227423 | AF12: =SUM(AF4:AF11) -> 23624058 | AI12: =SUM(AI4:AI11) -> 24150157 | AL12: =SUM(AL4:AL11) -> 24689924 | AO12: =SUM(AO4:AO11) -> 25243737 | AR12: =SUM(AR4:AR11) -> 25811989 | AU12: =SUM(AU4:AU11) -> 26395083 | AX12: =SUM(AX4:AX11) -> 26993431 | AY12: =SUM(O12:AX12) -> 2.8810241e+08
A13: (*) Todos los items se actualizan por IPC Caba del mes anterior al de la prestación del servicio. En el caso de Operadores Call Center, se aplica lo homologado por Convenio de Comercio.
A14: Mes | D14: 45894 | G14: 45925 | J14: 45955 | M14: 45986 | P14: 46016 | S14: 46048 | V14: 46079 | Y14: 46107 | AB14: 46138 | AE14: 46168 | AH14: 46199 | AK14: 46229 | AN14: 46260 | AQ14: 46291 | AT14: 46321 | AW14: 46352
A15: IPC Caba mensual proyectado | D15: 1.016 | G15: 1.022 | J15: =1+Flk!K34 -> 1.023 | M15: =1+Flk!L34 -> 1.02 | P15: =1+Flk!M34 -> 1.02 | S15: =1+ipcene -> 1.029 | V15: =1+'REAL-BDGT2026'!J196 -> 1.029 | Y15: =1+'REAL-BDGT2026'!K196 -> 1.034 | AB15: =1+'REAL-BDGT2026'!L196 -> 1.026 | AE15: =1+'REAL-BDGT2026'!M196 -> 1.021 | AH15: =1+'REAL-BDGT2026'!N196 -> 1.029 | AK15: =1+'REAL-BDGT2026'!O196 -> 1.029 | AN15: =1+'REAL-BDGT2026'!P196 -> 1.029 | AQ15: =1+'REAL-BDGT2026'!Q196 -> 1.029 | AT15: =1+'REAL-BDGT2026'!R196 -> 1.029 | AW15: =1+'REAL-BDGT2026'!S196 -> 1.029
A16: (**) Convenio de Comercio mensual proyectado | G16: 1.01 | J16: =+G16 -> 1.01 | M16: =+J16 -> 1.01 | P16: =+M16 -> 1.01 | S16: =+P16 -> 1.01 | V16: =+S16 -> 1.01 | Y16: =+V16 -> 1.01 | AB16: =+Y16 -> 1.01 | AE16: =+AB16 -> 1.01 | AH16: =+AE16 -> 1.01 | AK16: =+AH16 -> 1.01 | AN16: =+AK16 -> 1.01 | AQ16: =+AN16 -> 1.01 | AT16: =+AQ16 -> 1.01 | AW16: =+AT16 -> 1.01
G17: VALIDADO CON LUIS CONVENIO DE COMERCIO
A19: Costo Astra | B19: Septiembre 2025 | F19: =+F2 -> Octubre 2025 RFC | I19: =+I2 -> Noviembre 2025 RFC | L19: =+L2 -> Diciembre 2025 RFC | O19: =+O2 -> Enero 2026 RFC | R19: =+R2 -> Febrero 2026 RFC | U19: =+U2 -> Marzo 2026 RFC | X19: =+X2 -> Abril 2026 RFC | AA19: =+AA2 -> Mayo 2026 RFC | AD19: =+AD2 -> Junio 2026 RFC | AG19: =+AG2 -> Julio 2026 RFC | AJ19: =+AJ2 -> Agosto 2026 RFC | AM19: =+AM2 -> Septiembre 2026 RFC | AP19: =+AP2 -> Octubre 2026 RFC | AS19: =+AS2 -> Noviembre 2026 RFC | AV19: =+AV2 -> Diciembre 2026 RFC
A20: Avanter | B20: Cantidad | D20: Precio Unit. Sept-25 | E20: Total a Facturar | F20: Cantidad | G20: Precio Unitario | H20: Total | I20: Cantidad | J20: Precio Unitario | K20: Total | L20: Cantidad | M20: Precio Unitario | N20: Total | O20: Cantidad | P20: Precio Unitario | Q20: Total | R20: Cantidad | S20: Precio Unitario | T20: Total | U20: Cantidad | V20: Precio Unitario | W20: Total | X20: Cantidad | Y20: Precio Unitario | Z20: Total | AA20: Cantidad | AB20: Precio Unitario | AC20: Total | AD20: Cantidad | AE20: Precio Unitario | AF20: Total | AG20: Cantidad | AH20: Precio Unitario | AI20: Total | AJ20: Cantidad | AK20: Precio Unitario | AL20: Total | AM20: Cantidad | AN20: Precio Unitario | AO20: Total | AP20: Cantidad | AQ20: Precio Unitario | AR20: Total | AS20: Cantidad | AT20: Precio Unitario | AU20: Total | AV20: Cantidad | AW20: Precio Unitario | AX20: Total
A21: Operación | B21: 1 | D21: 1620021.7 | E21: =+D21*B21 -> 1620021.7 | F21: 1 | G21: =+D21*G15 -> 1655662.2 | H21: =+G21*F21 -> 1655662.2 | I21: 1 | J21: =+G21*J15 -> 1693742.4 | K21: =+J21*I21 -> 1693742.4 | L21: 1 | M21: =+J21*M15 -> 1727617.2 | N21: =+M21*L21 -> 1727617.2 | O21: 1 | P21: =+M21*P15 -> 1762169.6 | Q21: =+P21*O21 -> 1762169.6 | R21: 1 | S21: =+P21*S15 -> 1813272.5 | T21: =+S21*R21 -> 1813272.5 | U21: 1 | V21: =+S21*V15 -> 1865857.4 | W21: =+V21*U21 -> 1865857.4 | X21: 1 | Y21: =+V21*Y15 -> 1929296.6 | Z21: =+Y21*X21 -> 1929296.6 | AA21: 1 | AB21: =+Y21*AB15 -> 1979458.3 | AC21: =+AB21*AA21 -> 1979458.3 | AD21: 1 | AE21: =+AB21*AE15 -> 2021026.9 | AF21: =+AE21*AD21 -> 2021026.9 | AG21: 1 | AH21: =+AE21*AH15 -> 2079636.7 | AI21: =+AH21*AG21 -> 2079636.7 | AJ21: 1 | AK21: =+AH21*AK15 -> 2139946.1 | AL21: =+AK21*AJ21 -> 2139946.1 | AM21: 1 | AN21: =+AK21*AN15 -> 2202004.6 | AO21: =+AN21*AM21 -> 2202004.6 | AP21: 1 | AQ21: =+AN21*AQ15 -> 2265862.7 | AR21: =+AQ21*AP21 -> 2265862.7 | AS21: 1 | AT21: =+AQ21*AT15 -> 2331572.7 | AU21: =+AT21*AS21 -> 2331572.7 | AV21: 1 | AW21: =+AT21*AW15 -> 2399188.3 | AX21: =+AW21*AV21 -> 2399188.3
A22: Cápitas Activas Adicionales a 10.000 | B22: 6299 | D22: 151.63 | E22: =+D22*B22 -> 955117.37 | F22: 6299 | G22: =+D22*G15 -> 154.96586 | H22: =+G22*F22 -> 976129.95 | I22: 6299 | J22: =+G22*J15 -> 158.53007 | K22: =+J22*I22 -> 998580.94 | L22: 6299 | M22: =+J22*M15 -> 161.70068 | N22: =+M22*L22 -> 1018552.6 | O22: 6299 | P22: =+M22*P15 -> 164.93469 | Q22: =+P22*O22 -> 1038923.6 | R22: 6299 | S22: =+P22*S15 -> 169.7178 | T22: =+S22*R22 -> 1069052.4 | U22: 6299 | V22: =+S22*V15 -> 174.63961 | W22: =+V22*U22 -> 1100054.9 | X22: 6299 | Y22: =+V22*Y15 -> 180.57736 | Z22: =+Y22*X22 -> 1137456.8 | AA22: 6299 | AB22: =+Y22*AB15 -> 185.27237 | AC22: =+AB22*AA22 -> 1167030.7 | AD22: 6299 | AE22: =+AB22*AE15 -> 189.16309 | AF22: =+AE22*AD22 -> 1191538.3 | AG22: 6299 | AH22: =+AE22*AH15 -> 194.64882 | AI22: =+AH22*AG22 -> 1226092.9 | AJ22: 6299 | AK22: =+AH22*AK15 -> 200.29364 | AL22: =+AK22*AJ22 -> 1261649.6 | AM22: 6299 | AN22: =+AK22*AN15 -> 206.10215 | AO22: =+AN22*AM22 -> 1298237.4 | AP22: 6299 | AQ22: =+AN22*AQ15 -> 212.07911 | AR22: =+AQ22*AP22 -> 1335886.3 | AS22: 6299 | AT22: =+AQ22*AT15 -> 218.22941 | AU22: =+AT22*AS22 -> 1374627 | AV22: 6299 | AW22: =+AT22*AW15 -> 224.55806 | AX22: =+AW22*AV22 -> 1414491.2
A23: Total Avanter | E23: =SUM(E21:E22) -> 2575139.1 | H23: =SUM(H21:H22) -> 2631792.1 | K23: =SUM(K21:K22) -> 2692323.3 | N23: =SUM(N21:N22) -> 2746169.8 | Q23: =SUM(Q21:Q22) -> 2801093.2 | T23: =SUM(T21:T22) -> 2882324.9 | W23: =SUM(W21:W22) -> 2965912.3 | Z23: =SUM(Z21:Z22) -> 3066753.3 | AC23: =SUM(AC21:AC22) -> 3146488.9 | AF23: =SUM(AF21:AF22) -> 3212565.2 | AI23: =SUM(AI21:AI22) -> 3305729.6 | AL23: =SUM(AL21:AL22) -> 3401595.7 | AO23: =SUM(AO21:AO22) -> 3500242 | AR23: =SUM(AR21:AR22) -> 3601749 | AU23: =SUM(AU21:AU22) -> 3706199.8 | AX23: =SUM(AX21:AX22) -> 3813679.6 | AY23: =SUM(O23:AX23) -> 39404334
A25: Indicom | B25: Cantidad | D25: Precio Unit. Sept-25 | E25: Total a Facturar | F25: =+F20 -> Cantidad | G25: =+G20 -> Precio Unitario | H25: =+H20 -> Total | I25: =+I20 -> Cantidad | J25: =+J20 -> Precio Unitario | K25: =+K20 -> Total | L25: =+L20 -> Cantidad | M25: =+M20 -> Precio Unitario | ... AX25: =+AX20 -> Total
A26: Operador CALL CENTER | B26: 3 | D26: 1937633.4 | E26: =+D26*B26 -> 5812900.3 | F26: =+B26 -> 3 | G26: =+D26+18811.97 -> 1956445.4 | H26: =+G26*F26 -> 5869336.2 | I26: =+F26 -> 3 | J26: =+G26+18811.97 -> 1975257.4 | K26: =+J26*I26 -> 5925772.1 | L26: =+I26 -> 3 | M26: =+J26+18811.97 -> 1994069.3 | N26: =+M26*L26 -> 5982208 | O26: =+L26 -> 3 | P26: =+M26*P16 -> 2014010 | Q26: =+P26*O26 -> 6042030.1 | R26: =+O26 -> 3 | S26: =+P26*S16 -> 2034150.1 | T26: =+S26*R26 -> 6102450.4 | U26: =+R26 -> 3 | V26: =+S26*V16 -> 2054491.6 | W26: =+V26*U26 -> 6163474.9 | X26: =+U26 -> 3 | Y26: =+V26*Y16 -> 2075036.5 | Z26: =+Y26*X26 -> 6225109.6 | AA26: =+X26 -> 3 | AB26: =+Y26*AB16 -> 2095786.9 | AC26: =+AB26*AA26 -> 6287360.7 | AD26: =+AA26 -> 3 | AE26: =+AB26*AE16 -> 2116744.8 | AF26: =+AE26*AD26 -> 6350234.3 | AG26: =+AD26 -> 3 | AH26: =+AE26*AH16 -> 2137912.2 | AI26: =+AH26*AG26 -> 6413736.7 | AJ26: =+AG26 -> 3 | AK26: =+AH26*AK16 -> 2159291.3 | AL26: =+AK26*AJ26 -> 6477874 | AM26: =+AJ26 -> 3 | AN26: =+AK26*AN16 -> 2180884.3 | AO26: =+AN26*AM26 -> 6542652.8 | AP26: =+AM26 -> 3 | AQ26: =+AN26*AQ16 -> 2202693.1 | AR26: =+AQ26*AP26 -> 6608079.3 | AS26: =+AP26 -> 3 | AT26: =+AQ26*AT16 -> 2224720 | AU26: =+AT26*AS26 -> 6674160.1 | AV26: =+AS26 -> 3 | AW26: =+AT26*AW16 -> 2246967.2 | AX26: =+AW26*AV26 -> 6740901.7
A27: Monto Fijo | B27: 3 | D27: 40000 | E27: =+D27*B27 -> 120000 | F27: =+B27 -> 3 | G27: =+D27 -> 40000 | H27: =+G27*F27 -> 120000 | I27: =+F27 -> 3 | J27: =+G27 -> 40000 | K27: =+J27*I27 -> 120000 | L27: =+I27 -> 3 | M27: =+J27 -> 40000 | N27: =+M27*L27 -> 120000 | Q27: =+P27*O27 -> 0 | T27: =+S27*R27 -> 0 | W27: =+V27*U27 -> 0 | Z27: =+Y27*X27 -> 0 | AC27: =+AB27*AA27 -> 0 | AF27: =+AE27*AD27 -> 0 | AI27: =+AH27*AG27 -> 0 | AL27: =+AK27*AJ27 -> 0 | AO27: =+AN27*AM27 -> 0 | AR27: =+AQ27*AP27 -> 0 | AU27: =+AT27*AS27 -> 0 | AX27: =+AW27*AV27 -> 0
A28: Total Indicom | E28: =SUM(E26:E27) -> 5932900.3 | H28: =SUM(H26:H27) -> 5989336.2 | K28: =SUM(K26:K27) -> 6045772.1 | N28: =SUM(N26:N27) -> 6102208 | Q28: =SUM(Q26:Q27) -> 6042030.1 | T28: =SUM(T26:T27) -> 6102450.4 | W28: =SUM(W26:W27) -> 6163474.9 | Z28: =SUM(Z26:Z27) -> 6225109.6 | AC28: =SUM(AC26:AC27) -> 6287360.7 | AF28: =SUM(AF26:AF27) -> 6350234.3 | AI28: =SUM(AI26:AI27) -> 6413736.7 | AL28: =SUM(AL26:AL27) -> 6477874 | AO28: =SUM(AO26:AO27) -> 6542652.8 | AR28: =SUM(AR26:AR27) -> 6608079.3 | AU28: =SUM(AU26:AU27) -> 6674160.1 | AX28: =SUM(AX26:AX27) -> 6740901.7 | AY28: =SUM(O28:AX28) -> 76628064
B30: Variación según IPC (mes de facturación)
B31: Facturación Abril 2022 | C31: Facturación Mayo 2022 | D31: Facturación Junio 2022 | E31: Facturación Julio 2022 | F31: Facturación Agosto 2022 | G31: Facturación Septiembre 2022 | H31: Facturación Octubre 2022 | I31: Facturación Noviembre 2022 | J31: Facturación Diciembre 2022 | K31: Facturación Enero 2023 | L31: Facturación Febrero 2023 | M31: Facturación Marzo 2023
C32: IPC Abril 2022 | D32: IPC Mayo 2022 | E32: IPC Junio 2022 | F32: IPC Julio 2022 | G32: IPC Agosto 2022 | H32: IPC Septiembre 2022 | I32: IPC Octubre 2022 | J32: IPC Noviembre 2022 | K32: IPC Diciembre 2022 | L32: IPC Enero 2023 | M32: IPC Febrero 2023
A33: Concepto | C33: 1.053 | D33: 1.055 | E33: 1.051 | F33: 1.077 | G33: 1.062 | H33: 1.056 | I33: 1.07 | J33: 1.058 | K33: 1.058 | L33: 1.073 | M33: 1.06
A34: Operación | B34: 506187.72 | C34: =B34*C33 -> 533015.67 | D34: =C34*$D$33 -> 562331.53 | E34: =D34*$E$33 -> 591010.44 | F34: =E34*$F$33 -> 636518.24 | G34: =F34*$G$33 -> 675982.37 | H34: =G34*$H$33 -> 713837.39 | I34: =H34*$I$33 -> 763806 | J34: =I34*$J$33 -> 808106.75 | K34: =J34*$J$33 -> 854976.94 | L34: =K34*$L$33 -> 917390.26 | M34: =L34*M$33 -> 972433.68
A35: Cápitas Activas Adicionales a 12,000 | B35: 39.95 | C35: =B35*$C$33 -> 42.06735 | D35: =C35*$D$33 -> 44.381054 | E35: =D35*$E$33 -> 46.644488 | F35: =E35*$F$33 -> 50.236114 | G35: =F35*$G$33 -> 53.350753 | H35: =G35*$H$33 -> 56.338395 | I35: =H35*$I$33 -> 60.282082 | J35: =I35*$J$33 -> 63.778443 | K35: =J35*$J$33 -> 67.477593 | L35: =K35*$L$33 -> 72.403457 | M35: =L35*M$33 -> 76.747665
A36: Auditoría basada en Alertas Tempranas | B36: 44909.94 | C36: =B36*$C$33 -> 47290.167 | D36: =C36*$D$33 -> 49891.126 | E36: =D36*$E$33 -> 52435.573 | F36: =E36*$F$33 -> 56473.113 | G36: =F36*$G$33 -> 59974.446 | H36: =G36*$H$33 -> 63333.015 | I36: =H36*$I$33 -> 67766.326 | J36: =I36*$J$33 -> 71696.772 | K36: =J36*$J$33 -> 75855.185 | L36: =K36*$L$33 -> 81392.614 | M36: =L36*M$33 -> 86276.171
A37: Supervisor de Cutomer Service – Valor Horario por Recurso | B37: 5210 | C37: =B37*$C$33 -> 5486.13 | D37: =C37*$D$33 -> 5787.8672 | E37: =D37*$E$33 -> 6083.0484 | F37: =E37*$F$33 -> 6551.4431 | G37: =F37*$G$33 -> 6957.6326 | H37: =G37*$H$33 -> 7347.26 | I37: =H37*$I$33 -> 7861.5682 | J37: =I37*$J$33 -> 8317.5392 | K37: =J37*$J$33 -> 8799.9564 | L37: =K37*$L$33 -> 9442.3532 | M37: 4240
A38: Auditoría Digital - Servicio Base | B38: 82593 | C38: =B38*$C$33 -> 86970.429 | D38: =C38*$D$33 -> 91753.803 | E38: =D38*$E$33 -> 96433.247 | F38: =E38*$F$33 -> 103858.61 | G38: =F38*$G$33 -> 110297.84 | H38: =G38*$H$33 -> 116474.52 | I38: =H38*$I$33 -> 124627.74 | J38: =I38*$J$33 -> 131856.14 | K38: =J38*$J$33 -> 139503.8 | L38: =K38*$L$33 -> 149687.58 | M38: =L38*M$33 -> 158668.83
A39: Auditoría Digital - Cápitas Adicionales | B39: 6.89 | C39: =B39*$C$33 -> 7.25517 | D39: =C39*$D$33 -> 7.6542043 | E39: =D39*$E$33 -> 8.0445688 | F39: =E39*$F$33 -> 8.6640006 | G39: =F39*$G$33 -> 9.2011686 | H39: 9.71 | I39: =H39*$I$33 -> 10.3897 | J39: =I39*$J$33 -> 10.992303 | K39: =J39*$J$33 -> 11.629856 | L39: =K39*$L$33 -> 12.478836 | M39: =L39*M$33 -> 13.227566
B40: Variación según IPC (mes de facturación)
B41: Facturación Abril 2023 | C41: Facturación Mayo 2023 | D41: Facturación Junio 2023 | E41: Facturación Julio 2023 | F41: Facturación Agosto 2023 | G41: Facturación Septiembre 2023 | H41: Facturación Octubre 2023 | I41: Facturación Noviembre 2023 | J41: Facturación Diciembre 2023 | K41: Facturación Enero 2024 | L41: Facturación Febrero 2024 | M41: Facturación Marzo 2024
B42: IPC Marzo 2023 | C42: IPC Abril 2023 | D42: IPC Mayo 2023 | E42: IPC Junio 2023 | F42: IPC Julio 2023 | G42: IPC Agosto 2023 | H42: IPC Septiembre 2023 | I42: IPC Octubre 2023 | J42: IPC Noviembre 2023 | K42: IPC Diciembre 2023 | L42: IPC Enero 2024 | M42: IPC Febrero 2024
A43: Concepto | B43: 1.071 | C43: 1.078 | D43: 1.075 | E43: 1.071 | F43: 1.073 | G43: 1.108 | H43: 1.12 | I43: 1.094 | J43: 1.119 | K43: 1.211 | L43: 1.217 | M43: 1.141
A44: Operación | B44: =M34*$B$43 -> 1041476.5 | C44: =B44*$C$43 -> 1122711.6 | D44: =C44*$D$43 -> 1206915 | E44: =D44*$E$43 -> 1292606 | F44: =E44*$F$43 -> 1386966.2 | G44: =F44*$G$43 -> 1536758.6 | H44: =G44*H$43 -> 1721169.6 | I44: =H44*I$43 -> 1882959.5 | J44: =I44*J$43 -> 2107031.7 | K44: =J44*K$43 -> 2551615.4 | L44: =K44*L$43 -> 3105315.9 | M44: =L44*M$43 -> 3543165.5
A45: Cápitas Activas Adicionales a 12,000 | B45: =M35*$B$43 -> 82.196749 | C45: =B45*$C$43 -> 88.608095 | D45: =C45*$D$43 -> 95.253702 | E45: =D45*$E$43 -> 102.01672 | F45: =E45*$F$43 -> 109.46394 | G45: =F45*$G$43 -> 121.28604 | H45: =G45*H$43 -> 135.84037 | I45: =H45*I$43 -> 148.60936 | J45: =I45*J$43 -> 166.29387 | K45: =J45*K$43 -> 201.38188 | L45: =K45*L$43 -> 245.08175 | M45: =L45*M$43 -> 279.63828
A46: Auditoría basada en Alertas Tempranas | B46: =M36*$B$43 -> 92401.779 | C46: =B46*$C$43 -> 99609.117 | D46: =C46*$D$43 -> 107079.8 | E46: =D46*$E$43 -> 114682.47 | F46: =E46*$F$43 -> 123054.29 | G46: =F46*$G$43 -> 136344.15 | H46: =G46*H$43 -> 152705.45 | I46: =H46*I$43 -> 167059.76 | J46: =I46*J$43 -> 186939.87 | K46: =J46*K$43 -> 226384.18 | L46: =K46*L$43 -> 275509.55 | M46: =L46*M$43 -> 314356.4
A47: Supervisor de Cutomer Service – Valor Horario por Recurso | B47: =M37*$B$43 -> 4541.04 | C47: =B47*$C$43 -> 4895.2411 | D47: =C47*$D$43 -> 5262.3842 | E47: =D47*$E$43 -> 5636.0135 | F47: =E47*$F$43 -> 6047.4425 | G47: =F47*$G$43 -> 6700.5663 | H47: =G47*H$43 -> 7504.6342 | I47: =H47*I$43 -> 8210.0698 | J47: =I47*J$43 -> 9187.0681 | K47: =J47*K$43 -> 11125.54 | L47: =K47*L$43 -> 13539.782 | M47: =L47*M$43 -> 15448.891
A48: Auditoría Digital - Servicio Base | B48: =M38*$B$43 -> 169934.32 | C48: =B48*$C$43 -> 183189.2 | D48: =C48*$D$43 -> 196928.39 | E48: =D48*$E$43 -> 210910.3 | F48: =E48*$F$43 -> 226306.75 | G48: =F48*$G$43 -> 250747.88 | H48: =G48*H$43 -> 280837.63 | I48: =H48*I$43 -> 307236.37 | J48: =I48*J$43 -> 343797.49 | K48: =J48*K$43 -> 416338.77 | L48: =K48*L$43 -> 506684.28 | M48: =L48*M$43 -> 578126.76
A49: Auditoría Digital - Cápitas Adicionales | B49: =M39*$B$43 -> 14.166723 | C49: =B49*$C$43 -> 15.271727 | D49: 16.42 | E49: =D49*$E$43 -> 17.58582 | F49: =E49*$F$43 -> 18.869585 | G49: =F49*$G$43 -> 20.9075 | H49: =G49*H$43 -> 23.4164 | I49: =H49*I$43 -> 25.617542 | J49: =I49*J$43 -> 28.666029 | K49: 34.72 | L49: 42.257 | M49: =L49*M$43 -> 48.215237
B50: Variación según IPC (mes de facturación)
B51: Facturación Abril 2024 | C51: Facturación Mayo 2024 | D51: Facturación Junio 2024 | E51: Facturación Julio 2024 | F51: Facturación Agosto 2024 | G51: Facturación Septiembre 2024 | H51: Facturación Octubre 2024 | I51: Facturación Noviembre 2024 | J51: Facturación Diciembre 2024 | K51: Facturación Enero 2025 | L51: Facturación Febrero 2025 | M51: Facturación Marzo 2025
B52: IPC Marzo 2024 | C52: IPC Abril 2024 | D52: IPC Mayo 2024 | E52: IPC Junio 2024 | F52: IPC Julio 2024 | G52: IPC Agosto 2024 | H52: IPC Septiembre 2024 | I52: IPC Octubre 2024 | J52: IPC Noviembre 2024 | K52: IPC Diciembre 2024 | L52: IPC Enero 2025 | M52: IPC Febrero 2025
A53: Concepto | B53: 1.132 | C53: 1.098 | D53: 1.044 | E53: 1.048 | F53: 1.051 | G53: 1.042 | H53: 1.04 | I53: 1.032 | J53: 1.032 | K53: 1.033 | L53: 1.031 | M53: 1.021
A54: Operación | B54: =M44*$B$53 -> 4010863.3 | C54: =B54*$C$53 -> 4403927.9 | D54: =C54*$D$53 -> 4597700.8 | E54: =D54*$E$53 -> 4818390.4 | F54: =E54*$F$53 -> 5064128.3 | G54: =F54*$G$53 -> 5276821.7 | H54: =G54*$H$53 -> 5487894.6 | I54: =H54*$I$53 -> 5663507.2 | J54: =I54*$I$53 -> 5844739.4 | K54: =J54*$K$53 -> 6037615.8 | L54: =K54*$L$53 -> 6224781.9 | M54: =L54*$M$53 -> 6355502.3
A55: Cápitas Activas Adicionales a 12,000 | B55: =M45*B53 -> 316.55053 | C55: =B55*$C$53 -> 347.57248 | D55: =C55*$D$53 -> 362.86567 | E55: =D55*$E$53 -> 380.28322 | F55: =E55*$F$53 -> 399.67767 | G55: =F55*$G$53 -> 416.46413 | H55: =G55*$H$53 -> 433.12269 | I55: =H55*$I$53 -> 446.98262 | J55: =I55*$I$53 -> 461.28606 | K55: =J55*$K$53 -> 476.5085 | L55: =K55*$L$53 -> 491.28027 | M55: =L55*$M$53 -> 501.59715
A56: Auditoría basada en Alertas Tempranas | B56: =M46*$B$53 -> 355851.44 | C56: =B56*$C$53 -> 390724.89 | D56: =C56*$D$53 -> 407916.78 | E56: =D56*$E$53 -> 427496.79 | F56: =E56*$F$53 -> 449299.12 | G56: =F56*$G$53 -> 468169.69 | H56: =G56*$H$53 -> 486896.47 | I56: =H56*$I$53 -> 502477.16 | J56: =I56*$I$53 -> 518556.43 | K56: =J56*$K$53 -> 535668.79 | L56: =K56*$L$53 -> 552274.52 | M56: =L56*$M$53 -> 563872.29
A57: Supervisor de Cutomer Service – Valor Horario por Recurso | B57: =M47*$B$53 -> 17488.144 | C57: =B57*$C$53 -> 19201.983 | D57: =C57*$D$53 -> 20046.87 | E57: =D57*$E$53 -> 21009.119 | F57: =E57*$F$53 -> 22080.585 | G57: =F57*$G$53 -> 23007.969 | H57: =G57*$H$53 -> 23928.288 | I57: =H57*$I$53 -> 24693.993 | J57: =I57*$I$53 -> 25484.201 | K57: =J57*$K$53 -> 26325.18 | L57: =K57*$L$53 -> 27141.26 | M57: =L57*$M$53 -> 27711.227
A58: Auditoría Digital - Servicio Base | B58: =M48*$B$53 -> 654439.49 | C58: =B58*$C$53 -> 718574.56 | D58: =C58*$D$53 -> 750191.84 | E58: =D58*$E$53 -> 786201.05 | F58: =E58*$F$53 -> 826297.31 | G58: =F58*$G$53 -> 861001.79 | H58: =G58*$H$53 -> 895441.86 | I58: =H58*$I$53 -> 924096 | J58: =I58*$I$53 -> 953667.08 | K58: =J58*$K$53 -> 985138.09 | L58: =K58*$L$53 -> 1015677.4 | M58: =L58*$M$53 -> 1037006.6
A59: Auditoría Digital - Cápitas Adicionales | B59: =M49*$B$53 -> 54.579648 | C59: =B59*$C$53 -> 59.928454 | D59: =C59*$D$53 -> 62.565306 | E59: =D59*$E$53 -> 65.56844 | F59: =E59*$F$53 -> 68.912431 | G59: =F59*$G$53 -> 71.806753 | H59: =G59*$H$53 -> 74.679023 | I59: =H59*$I$53 -> 77.068752 | J59: 79.54 | K59: =J59*$K$53 -> 82.16482 | L59: =K59*$L$53 -> 84.711929 | M59: =L59*$M$53 -> 86.49088
B61: Facturación Abril 2025 | C61: Facturación Mayo 2025 | D61: Facturación Junio 2025 | E61: Facturación Julio 2025 | F61: Facturación Agosto 2025 | G61: Facturación Septiembre 2025 | H61: RFC Octubre | I61: RFC Noviembre | J61: RFC Diciembre
B62: IPC Marzo 2025 | C62: IPC Abril 2025 | D62: IPC Mayo 2025 | E62: IPC Junio 2025 | F62: IPC Julio 2025 | G62: IPC Agosto 2025
A63: Concepto | B63: 1.032 | C63: 1.023 | D63: 1.016 | E63: 1.021 | F63: 1.025 | G63: 1.016
A64: Operación | B64: =M54*B63 -> 6558878.4 | C64: =B64*C63 -> 6709732.6 | D64: =C64*$D$63 -> 6817088.3 | E64: =D64*E$63 -> 6960247.2 | F64: =E64*$F$63 -> 7134253.4 | G64: =F64*$G$63 -> 7248401.4
A65: Cápitas Activas Adicionales a 12,000 | B65: =M55*B63 -> 517.64826 | C65: =B65*C63 -> 529.55417 | D65: =C65*$D$63 -> 538.02704 | E65: =D65*E$63 -> 549.3256 | F65: =E65*$F$63 -> 563.05874 | G65: =F65*$G$63 -> 572.06768
A66: Auditoría basada en Alertas Tempranas | B66: =M56*B63 -> 581916.2 | C66: =B66*C63 -> 595300.28 | D66: =C66*$D$63 -> 604825.08 | E66: =D66*E$63 -> 617526.41 | F66: =E66*$F$63 -> 632964.57 | G66: =F66*$G$63 -> 643092
A67: Supervisor de Cutomer Service – Valor Horario por Recurso | B67: =M57*B63 -> 28597.986 | C67: =B67*C63 -> 29255.739 | D67: =C67*$D$63 -> 29723.831 | E67: =D67*E$63 -> 30348.032 | F67: =E67*$F$63 -> 31106.733 | G67: =F67*$G$63 -> 31604.44
A68: Auditoría Digital - Servicio Base | B68: =M58*B63 -> 1070190.8 | C68: =B68*C63 -> 1094805.2 | D68: =C68*$D$63 -> 1112322.1 | E68: =D68*E$63 -> 1135680.8 | F68: =E68*$F$63 -> 1164072.9 | G68: =F68*$G$63 -> 1182698
A69: Auditoría Digital - Cápitas Adicionales | B69: 89.25 | C69: 91.31 | D69: =C69*$D$63 -> 92.77096 | E69: =D69*E$63 -> 94.71915 | F69: 97.09 | G69: =F69*$G$63 -> 98.64344

Sheet Bayer
A2: Facturación Más Simple Bayer- Septiembre 2025 | F2: 45957 | G2: =+F2+30 -> 45987 | H2: =+G2+30 -> 46017 | I2: 46023 | J2: 46054 | K2: 46112 | L2: 46142 | M2: 46172 | N2: 46202 | O2: 46232 | P2: 46262 | Q2: 46292 | R2: 46322 | S2: 46352 | T2: 46382
A3: Concepto | B3: Abono Mínimo (*) | C3: Total Vendido | D3: % PVP | E3: Total a Facturar
A4: Operación Servicio | B4: 748624.35 | C4: 1.6547251e+08 | D4: 0.5 | E4: =C4*D4% -> 827362.54 | F4: =+E4*(1+F6) -> 846391.88 | G4: =+F4*(1+G6) -> 863319.72 | H4: =+G4*(1+H6) -> 880586.11 | I4: =+H4*(1+I6) -> 906123.11 | J4: =+I4*(1+J6) -> 932400.68 | K4: =+J4*(1+K6) -> 964102.3 | L4: =+K4*(1+L6) -> 989168.96 | M4: =+L4*(1+M6) -> 1009941.5 | ... T4: =+S4*(1+T6) -> 1233683.8 | U4: =SUM(I4:T4) -> 12740729
E6: IPC Indec mensual proyectado | F6: =+Flk!K34 -> 0.023 | G6: =+Flk!L34 -> 0.02 | H6: =+Flk!M34 -> 0.02 | I6: =+Flk!B71 -> 0.029 | J6: =+Flk!C71 -> 0.029 | K6: =+Flk!D71 -> 0.034 | L6: =+Flk!E71 -> 0.026 | M6: =+Flk!F71 -> 0.021 | N6: =+Flk!G71 -> 0.029 | O6: =+Flk!H71 -> 0.029 | P6: =+Flk!I71 -> 0.029 | ... T6: =+Flk!M71 -> 0.029
A9: (*)
A10: En Septiembre 2025 el valor del abono mínimo se incrementó con el mismo porcentaje de aumento que tuvieron los productos incluidos en el programa durante el último trimestre.

Sheet Colgate
B2: COLGATE PALMOLIVE | F2: 45957 | G2: =+F2+30 -> 45987 | H2: =+G2+30 -> 46017 | I2: 46023 | J2: 46054 | K2: 46112 | L2: 46142 | M2: 46172 | N2: 46202 | O2: 46232 | P2: 46262 | Q2: 46292 | R2: 46322 | S2: 46352 | T2: 46382
C4: Estimación Facturación Licha Dic 25 | F4: =+E4*(1+F6) -> 0 | G4: =+F4*(1+G6) -> 0 | H4: 1300000 | I4: =+H4*(1+I6) -> 1337700 | J4: =+I4*(1+J6) -> 1376493.3 | K4: =+J4*(1+K6) -> 1423294.1 | L4: =+K4*(1+L6) -> 1460299.7 | M4: =+L4*(1+M6) -> 1490966 | N4: =+M4*(1+N6) -> 1534204 | O4: =+N4*(1+O6) -> 1578695.9 | P4: =+O4*(1+P6) -> 1624478.1 | ... T4: =+S4*(1+T6) -> 1821274.3 | U4: =SUM(I4:T4) -> 18809003
C5: luego actualiza por IPC Mensual
E6: IPC Indec mensual proyectado | F6: =+Flk!K34 -> 0.023 | G6: =+Flk!L34 -> 0.02 | H6: =+Flk!M34 -> 0.02 | I6: =+Flk!B71 -> 0.029 | J6: =+Flk!C71 -> 0.029 | K6: =+Flk!D71 -> 0.034 | L6: =+Flk!E71 -> 0.026 | M6: =+Flk!F71 -> 0.021 | N6: =+Flk!G71 -> 0.029 | O6: =+Flk!H71 -> 0.029 | P6: =+Flk!I71 -> 0.029 | ... T6: =+Flk!M71 -> 0.029

Sheet HealthC
B2: HEALTHCARE | F2: 45957 | G2: =+F2+30 -> 45987 | H2: =+G2+30 -> 46017 | I2: 46023 | J2: 46054 | K2: 46112 | L2: 46142 | M2: 46172 | N2: 46202 | O2: 46232 | P2: 46262 | Q2: 46292 | R2: 46322 | S2: 46352 | T2: 46382
C4: Estimación Facturación Licha Dic 25 | F4: =+E4*(1+F7) -> 0 | G4: =+F4*(1+G7) -> 0 | H4: 345000 | I4: =+H4*(I6) -> 367193.57 | J4: =+I4 -> 367193.57 | K4: =+J4 -> 367193.57 | L4: =+K4*(L6) -> 402018.8 | M4: =+L4 -> 402018.8 | N4: =+M4 -> 402018.8 | O4: =+N4*(O6) -> 433346.05 | P4: =+O4 -> 433346.05 | Q4: =+P4 -> 433346.05 | R4: =+Q4*(R6) -> 472151.05 | S4: =+R4 -> 472151.05 | T4: =+S4 -> 472151.05 | U4: =SUM(I4:T4) -> 5024128.4
C5: luego actualiza por IPC Trimestral
I6: =1*(1+F7)*(1+G7)*(1+H7) -> 1.0643292 | L6: =1*(1+I7)*(1+J7)*(1+K7) -> 1.0948416 | O6: =1*(1+L7)*(1+M7)*(1+N7) -> 1.0779248 | R6: =1*(1+O7)*(1+P7)*(1+Q7) -> 1.0895474
E7: IPC Indec mensual proyectado | F7: =+Flk!K34 -> 0.023 | G7: =+Flk!L34 -> 0.02 | H7: =+Flk!M34 -> 0.02 | I7: =+Flk!B71 -> 0.029 | J7: =+Flk!C71 -> 0.029 | K7: =+Flk!D71 -> 0.034 | L7: =+Flk!E71 -> 0.026 | M7: =+Flk!F71 -> 0.021 | N7: =+Flk!G71 -> 0.029 | O7: =+Flk!H71 -> 0.029 | P7: =+Flk!I71 -> 0.029 | ... T7: =+Flk!M71 -> 0.029

Sheet SidusFarma
A2: Cli_id | B2: Conceptos | C2: FACTURACIÓN SIDUS FARMA | H2: Precio cerrado en propuesta vigente | M2: finaliza propuesta
C3: 45901 | H3: Mes 8 | I3: mes 9 | J3: mes 10 | K3: mes 11 | L3: mes 12
C4: Envases Aprobados | D4: Monto Total | E4: PVP Promedio | F4: % PVP | G4: $ Total Facturación | H4: 45957 | I4: =+H4+30 -> 45987 | J4: =+I4+30 -> 46017 | K4: 46023 | L4: 46054 | M4: 46112 | N4: 46142 | O4: 46172 | P4: 46202 | Q4: 46232 | R4: 46262 | S4: 46292 | T4: 46322 | U4: 46352 | V4: 46382
A5: 5041 | B5: Sidus Farma BONOS Dispensas | C5: =SUM('[1]Soporte Transaccional'!K2:K4197) -> 0 | D5: =SUM('[1]Soporte Transaccional'!N2:N2189) -> 0 | E5: =D5/C5 -> #DIV/0! | F5: 0.01 | G5: =D5*F5 -> 0
A6: 5041 | B6: Mínimo Facturable x Propuesta Mes 7 | G6: 766721.67 | H6: =+G6 -> 766721.67 | I6: 958402.08 | J6: 1150082.5 | K6: 1341762.9 | L6: 1533443.3 | M6: =+L6 -> 1533443.3 | N6: =+M6 -> 1533443.3 | O6: =+N6*O9 -> 1673982.9 | P6: =+O6 -> 1673982.9 | Q6: =+P6 -> 1673982.9 | R6: =+Q6*R9 -> 1809703.8 | S6: =+R6 -> 1809703.8 | T6: =+S6 -> 1809703.8 | U6: =+T6*U9 -> 1971758 | V6: =+U6 -> 1971758 | W6: =SUM(K6:V6) -> 20336669
A7: TOTAL A FACTURAR | G7: =G6 -> 766721.67 | M7: = minimo feb | N7: = minimo feb | O7: en mayo se actualiza por ipc indec trimestral | R7: actualiza por ipc indec trimestral | U7: actualiza por ipc indec trimestral
O9: =1*(1+L10)*(1+M10)*(1+N10) -> 1.0916496 | R9: =1*(1+O10)*(1+P10)*(1+Q10) -> 1.0810767 | U9: =1*(1+R10)*(1+S10)*(1+T10) -> 1.0895474
G10: IPC Indec mensual proyectado | H10: =+Flk!K34 -> 0.023 | I10: =+Flk!L34 -> 0.02 | J10: =+Flk!M34 -> 0.02 | K10: =+Flk!B71 -> 0.029 | L10: =+Flk!C71 -> 0.029 | M10: =+Flk!D71 -> 0.034 | N10: =+Flk!E71 -> 0.026 | O10: =+Flk!F71 -> 0.021 | P10: =+Flk!G71 -> 0.029 | Q10: =+Flk!H71 -> 0.029 | R10: =+Flk!I71 -> 0.029 | ... V10: =+Flk!M71 -> 0.029
A13: LICHA: Se reduciría el programa (LICHA AVISA NOVEDADES)

Sheet SidusDermo
B2: FACTURACIÓN TRANSACCIONAL SIDUS DERMO | G2: Actualización Mensual por IPC Indec
B3: Cli_id | C3: Conceptos | D3: 45901 | W3: PRECIOS UNITARIOS
D4: Valor x TRX Septiembre 25 con IPC | E4: Total TRX Septiembre 2025 | F4: Facturac Sept25 | G4: 45957 | H4: =+G4+30 -> 45987 | I4: =+H4+30 -> 46017 | J4: 46023 | K4: 46054 | L4: 46112 | M4: 46142 | N4: 46172 | O4: 46202 | P4: 46232 | Q4: 46262 | R4: 46292 | S4: 46322 | T4: 46352 | U4: 46382 | W4: 45925 | X4: 45957 | Y4: 45987 | Z4: 46017 | AA4: 46023 | AB4: 46054 | AC4: 46112 | AD4: 46142 | AE4: 46172 | AF4: 46202 | AG4: 46232 | AH4: 46262 | AI4: 46292 | AJ4: 46322 | AK4: 46352 | AL4: 46382
B5: 5040 | C5: SIDUS BONOS | D5: 250.47311 | E5: 4386 | F5: =D5*E5 -> 1098575.1 | G5: =+X5*$E$5 -> 1123842.3 | H5: =+Y5*$E$5 -> 1146319.1 | I5: =+Z5*$E$5 -> 1169245.5 | J5: =+AA5*$E$5 -> 1203153.6 | K5: =+AB5*$E$5 -> 1238045.1 | L5: =+AC5*$E$5 -> 1280138.6 | M5: =+AD5*$E$5 -> 1313422.2 | N5: =+AE5*$E$5 -> 1341004.1 | ... U5: =+AL5*$E$5 -> 1638089.9 | V5: =+U5/J5 -> 1.3614968 | W5: 250.47311 | X5: =(W5*(1+G19)) -> 256.23399 | Y5: =(X5*(1+H19)) -> 261.35867 | Z5: =(Y5*(1+I19)) -> 266.58585 | AA5: =(Z5*(1+J19)) -> 274.31684 | AB5: =(AA5*(1+K19)) -> 282.27202 | AC5: =(AB5*(1+L19)) -> 291.86927 | AD5: =(AC5*(1+M19)) -> 299.45787 | AE5: =(AD5*(1+N19)) -> 305.74649 | ... AL5: =(AK5*(1+U19)) -> 373.48151 | AM5: =+AL5/W5 -> 1.4911042
B6: 5040 | C6: SIDUS DINAMICAS | D6: 167.8288 | E6: 3895 | F6: =D6*E6 -> 653693.19 | G6: =+X6*$E$6 -> 668728.14 | H6: =+Y6*$E$6 -> 682102.7 | I6: =+Z6*$E$6 -> 695744.75 | J6: =+AA6*$E$6 -> 715921.35 | K6: =+AB6*$E$6 -> 736683.07 | L6: =+AC6*$E$6 -> 761730.3 | M6: =+AD6*$E$6 -> 781535.28 | N6: =+AE6*$E$6 -> 797947.52 | ... U6: =+AL6*$E$6 -> 974724.66 | V6: =+U6/J6 -> 1.3614968 | W6: 167.8288 | X6: =(W6*(1+G19)) -> 171.68887 | Y6: =(X6*(1+H19)) -> 175.12264 | Z6: =(Y6*(1+I19)) -> 178.6251 | AA6: =(Z6*(1+J19)) -> 183.80523 | AB6: =(AA6*(1+K19)) -> 189.13558 | AC6: =(AB6*(1+L19)) -> 195.56619 | AD6: =(AC6*(1+M19)) -> 200.65091 | AE6: =(AD6*(1+N19)) -> 204.86458 | ... AL6: =(AK6*(1+U19)) -> 250.25023 | AM6: =+AL6/W6 -> 1.4911042
B7: 5040 | C7: SIDUS CÓDIGOS DINAMICAS | D7: 1569.8403 | E7: 394 | F7: =D7*E7 -> 618517.07 | G7: =+X7*$E$7 -> 632742.96 | H7: =+Y7*$E$7 -> 645397.82 | I7: =+Z7*$E$7 -> 658305.77 | J7: =+AA7*$E$7 -> 677396.64 | K7: =+AB7*$E$7 -> 697041.14 | L7: =+AC7*$E$7 -> 720740.54 | M7: =+AD7*$E$7 -> 739479.8 | N7: =+AE7*$E$7 -> 755008.87 | ... U7: =+AL7*$E$7 -> 922273.39 | V7: =+U7/J7 -> 1.3614968 | W7: 1569.8403 | X7: =(W7*(1+G19)) -> 1605.9466 | Y7: =(X7*(1+H19)) -> 1638.0655 | Z7: =(Y7*(1+I19)) -> 1670.8268 | AA7: =(Z7*(1+J19)) -> 1719.2808 | AB7: =(AA7*(1+K19)) -> 1769.14 | AC7: =(AB7*(1+L19)) -> 1829.2907 | AD7: =(AC7*(1+M19)) -> 1876.8523 | AE7: =(AD7*(1+N19)) -> 1916.2662 | ... AL7: =(AK7*(1+U19)) -> 2340.7954 | AM7: =+AL7/W7 -> 1.4911042
B8: TOTAL | F8: =F6+F7+F5 -> 2370785.3 | G8: =SUM(G5:G7) -> 2425313.4 | H8: =SUM(H5:H7) -> 2473819.7 | I8: =SUM(I5:I7) -> 2523296.1 | J8: =SUM(J5:J7) -> 2596471.6 | K8: =SUM(K5:K7) -> 2671769.3 | L8: =SUM(L5:L7) -> 2762609.5 | M8: =SUM(M5:M7) -> 2834437.3 | N8: =SUM(N5:N7) -> 2893960.5 | ... U8: =SUM(U5:U7) -> 3535087.9
B10: FACTURACIÓN PLATAFORMA EMISIÓN BONOS DIGITALES (BONOS DERMO) | G10: Actualización Trimestral por IPC Indec
B11: Cli_id | C11: Conceptos | D11: 45901
D12: Precio Unitario | E12: Cantidad | F12: Facturac Sept25 | G12: =+G4 -> 45957 | H12: =+H4 -> 45987 | I12: =+I4 -> 46017 | J12: =+J4 -> 46023 | K12: =+K4 -> 46054 | L12: =+L4 -> 46112 | M12: =+M4 -> 46142 | N12: =+N4 -> 46172 | ... U12: =+U4 -> 46382
B13: 5040 | C13: USO DE LA PLATAFORMA | D13: =C45 -> 1123863.2 | E13: 1 | F13: =D13*E13 -> 1123863.2 | G13: =+C48 -> 1194990 | H13: =+G13 -> 1194990 | I13: =+H13 -> 1194990 | J13: =+I13*J18 -> 1271862.7 | K13: =+J13 -> 1271862.7 | L13: =+K13 -> 1271862.7 | M13: =+L13*M18 -> 1392488.2 | N13: =+M13 -> 1392488.2 | O13: =+N13 -> 1392488.2 | P13: =+O13*P18 -> 1500997.6 | Q13: =+P13 -> 1500997.6 | R13: =+Q13 -> 1500997.6 | S13: =+R13*S18 -> 1635408 | T13: =+S13 -> 1635408 | U13: =+T13 -> 1635408 | V13: =+U13/J13 -> 1.2858369
B14: 5040 | C14: MENSAJES WHATSAPP | D14: 0.13 | E14: 2254 | F14: =(D14*E14)*$C$17 -> 414623.3 | G14: =+$D$14*$E$14*G17 -> 439530 | H14: =+$D$14*$E$14*H17 -> 447441.54 | I14: =+$D$14*$E$14*I17 -> 455495.49 | J14: =+$D$14*$E$14*J17 -> 414623.3 | K14: =+$D$14*$E$14*K17 -> 416088.4 | L14: =+$D$14*$E$14*L17 -> 411693.1 | M14: =+$D$14*$E$14*M17 -> 414623.3 | N14: =+$D$14*$E$14*N17 -> 404367.6 | ... U14: =+$D$14*$E$14*U17 -> 448785.32 | V14: =+U14/J14 -> 1.0823929
B15: TOTAL | F15: =F13+F14 -> 1538486.5 | G15: =G13+G14 -> 1634520 | H15: =H13+H14 -> 1642431.5 | I15: =I13+I14 -> 1650485.4 | J15: =J13+J14 -> 1686486 | K15: =K13+K14 -> 1687951.1 | L15: =L13+L14 -> 1683555.8 | M15: =M13+M14 -> 1807111.5 | ... U15: =U13+U14 -> 2084193.3
B17: Valor dólar | C17: 1415 | F17: Proyección Dolar BNA | G17: 1500 | H17: =+G17*1.018 -> 1527 | I17: =+H17*1.018 -> 1554.486 | J17: =+'REAL-BDGT2026'!I203 -> 1415 | K17: =+'REAL-BDGT2026'!J203 -> 1420 | L17: =+'REAL-BDGT2026'!K203 -> 1405 | M17: =+'REAL-BDGT2026'!L203 -> 1415 | N17: =+'REAL-BDGT2026'!M203 -> 1380 | O17: =+'REAL-BDGT2026'!N203 -> 1400.7 | P17: =+'REAL-BDGT2026'!O203 -> 1421.7105 | Q17: =+'REAL-BDGT2026'!P203 -> 1443.0362 | ... U17: =+'REAL-BDGT2026'!T203 -> 1531.586
J18: =1*(1+G19)*(1+H19)*(1+I19) -> 1.0643292 | M18: =1*(1+J19)*(1+K19)*(1+L19) -> 1.0948416 | P18: =1*(1+M19)*(1+N19)*(1+O19) -> 1.0779248 | S18: =1*(1+P19)*(1+Q19)*(1+R19) -> 1.0895474
F19: IPC Indec mensual proyectado | G19: =+Flk!K34 -> 0.023 | H19: =+Flk!L34 -> 0.02 | I19: =+Flk!M34 -> 0.02 | J19: =+Flk!B71 -> 0.029 | K19: =+Flk!C71 -> 0.029 | L19: =+Flk!D71 -> 0.034 | M19: =+Flk!E71 -> 0.026 | N19: =+Flk!F71 -> 0.021 | O19: =+Flk!G71 -> 0.029 | P19: =+Flk!H71 -> 0.029 | Q19: =+Flk!I71 -> 0.029 | ... U19: =+Flk!M71 -> 0.029
B21: Meses | F21: 45925 | G21: =+G12 -> 45957 | H21: =+H12 -> 45987 | I21: =+I12 -> 46017 | J21: =+J12 -> 46023 | K21: =+K12 -> 46054 | L21: =+L12 -> 46112 | M21: =+M12 -> 46142 | N21: =+N12 -> 46172 | ... U21: =+U12 -> 46382
B22: FACTURACIÓN TOTAL SIDUS DERMO | F22: =+F15+F8 -> 3909271.8 | G22: =+G15+G8 -> 4059833.3 | H22: =+H15+H8 -> 4116251.2 | I22: =+I15+I8 -> 4173781.5 | J22: =+J15+J8 -> 4282957.6 | K22: =+K15+K8 -> 4359720.4 | L22: =+L15+L8 -> 4446165.3 | M22: =+M15+M8 -> 4641548.8 | ... U22: =+U15+U8 -> 5619281.3 | V22: =SUM(J22:U22) -> 58977483
B23: Evolución IPC CABA | C23: Facturado
A24: Base Octubre 2023 | B24: 298674.25 | C24: 298674.25
A25: 0.119 | B25: =B24*A25+B24 -> 334216.49 | C25: 298674.25
A26: 0.211 | B26: =B25*A26+B25 -> 404736.16 | C26: 298674.25
A27: 0.217 | B27: =B26*A27+B26 -> 492563.91 | C27: 492563.92
A28: 0.141 | B28: =B27*A28+B27 -> 562015.42 | C28: 492563.92
A29: 0.132 | B29: =B28*A29+B28 -> 636201.46 | C29: 492563.92
A30: 0.098 | B30: =B29*A30+B29 -> 698549.2 | C30: 698549.2
A31: 0.044 | B31: =B30*A31+B30 -> 729285.37 | C31: 698549.2
A32: 0.048 | B32: =B31*A32+B31 -> 764291.06 | C32: 698549.2
A33: 0.051 | B33: =B32*A33+B32 -> 803269.91 | C33: =B33 -> 803269.91
A34: 0.042 | B34: =B33*A34+B33 -> 837007.25 | C34: 803269.91
A35: 0.04 | B35: =B34*A35+B34 -> 870487.54 | C35: 803269.91
A36: 0.032 | B36: =B35*A36+B35 -> 898343.14 | C36: =B36 -> 898343.14
A37: 0.032 | B37: 927090.13 | C37: 898343.14
A38: 0.033 | B38: =B37*A38+B37 -> 957684.1 | C38: 898343.14
A39: 0.031 | B39: =B38*A39+B38 -> 987372.31 | C39: 987372.3
A40: 0.021 | B40: =B39*A40+B39 -> 1008107.1 | C40: 987372.3
A41: 0.032 | B41: =B40*A41+B40 -> 1040366.6 | C41: 987372.3
A42: 0.028 | B42: =B41*A42+B41 -> 1069496.8 | C42: =B42 -> 1069496.8
A43: 0.015 | B43: =B42*A43+B42 -> 1085539.3 | C43: 1069496.8
A44: 0.016 | B44: =B43*A44+B43 -> 1102907.9 | C44: 1069496.8
A45: 0.019 | B45: =B44*A45+B44 -> 1123863.2 | C45: =B45 -> 1123863.2
A46: 0.019 | B46: =B45*A46+B45 -> 1145216.6 | C46: 1123863.2
A47: 0.021 | B47: =B46*A47+B46 -> 1169266.1 | C47: 1123863.2
A48: 0.022 | B48: =B47*A48+B47 -> 1194990 | C48: =+B48 -> 1194990 | D48: SR estimó
A51: Conceptos | B51: MES
B52: 45901
B53: Precio Unitario
A54: FACTURACIÓN TRANSACCIONAL | B54: =H8 -> 2473819.7
A55: FACTURACIÓN PLATAFORMA EMISIÓN BONOS DIGITALES | B55: =F15 -> 1538486.5
B56: =B54+B55 -> 4012306.1
B59: COSTO AVANTER (SIDUS DERMO) | D59: Septiembre 2025 | G59: =+G21 -> 45957 | H59: =+H21 -> 45987 | I59: =+I21 -> 46017 | J59: =+J21 -> 46023 | K59: =+K21 -> 46054 | L59: =+L21 -> 46112 | M59: =+M21 -> 46142 | N59: =+N21 -> 46172 | ... U59: =+U21 -> 46382
D60: Cantidad | E60: Precio Unit. Sept-25 | F60: Total a Facturar
B61: USO DE LA PLATAFORMA | D61: 1 | E61: 732919.71 | F61: =+E61*D61 -> 732919.71 | G61: 777016.98 | H61: =+G61 -> 777016.98 | I61: =+H61 -> 777016.98 | J61: =+I61*J18 -> 827001.86 | K61: =+J61 -> 827001.86 | L61: =+K61 -> 827001.86 | M61: =+L61*M18 -> 905436.04 | N61: =+M61 -> 905436.04 | O61: =+N61 -> 905436.04 | P61: =+O61*P18 -> 975991.99 | Q61: =+P61 -> 975991.99 | R61: =+Q61 -> 975991.99 | S61: =+R61*S18 -> 1063389.5 | T61: =+S61 -> 1063389.5 | U61: =+T61 -> 1063389.5 | V61: =+U61/J61 -> 1.2858369 | W61: COSTOS UNITARIOS
B62: MENSAJES WHATSAPP | D62: 2255 | E62: 0.1 | F62: =(D62*E62)*$C$17 -> 319082.5 | G62: =+$E$62*$D$62*G17 -> 338250 | H62: =+$E$62*$D$62*H17 -> 344338.5 | I62: =+$E$62*$D$62*I17 -> 350536.59 | J62: =+$E$62*$D$62*J17 -> 319082.5 | K62: =+$E$62*$D$62*K17 -> 320210 | L62: =+$E$62*$D$62*L17 -> 316827.5 | M62: =+$E$62*$D$62*M17 -> 319082.5 | N62: =+$E$62*$D$62*N17 -> 311190 | ... U62: =+$E$62*$D$62*U17 -> 345372.64 | V62: =+U62/J62 -> 1.0823929 | W62: 45925 | X62: 45957 | Y62: 45987 | Z62: 46017 | AA62: 46023 | AB62: 46054 | AC62: 46112 | AD62: 46142 | AE62: 46172 | AF62: 46202 | AG62: 46232 | AH62: 46262 | AI62: 46292 | AJ62: 46322 | AK62: 46352 | AL62: 46382
B63: TRX Bonos | D63: 4386 | E63: 74.81 | F63: =+E63*D63 -> 328116.66 | G63: =+$D$63*X63 -> 335663.34 | H63: =+$D$63*Y63 -> 342376.61 | I63: =+$D$63*Z63 -> 349224.14 | J63: =+$D$63*AA63 -> 359351.64 | K63: =+$D$63*AB63 -> 369772.84 | L63: =+$D$63*AC63 -> 382345.12 | M63: =+$D$63*AD63 -> 392286.09 | N63: =+$D$63*AE63 -> 400524.1 | ... U63: =+$D$63*AL63 -> 489256.13 | V63: =+U63/J63 -> 1.3614968 | W63: =+E63 -> 74.81 | X63: =+W63*(1+$G$19) -> 76.53063 | Y63: =+X63*(1+H19) -> 78.061243 | Z63: =+Y63*(1+I19) -> 79.622467 | AA63: =+Z63*(1+J19) -> 81.931519 | AB63: =+AA63*(1+K19) -> 84.307533 | AC63: =+AB63*(1+L19) -> 87.173989 | AD63: =+AC63*(1+M19) -> 89.440513 | AE63: =+AD63*(1+N19) -> 91.318764 | AF63: =+AE63*(1+O19) -> 93.967008 | ... AL63: =+AK63*(1+U19) -> 111.5495
B64: TRX Bonos Dinamicas (hasta 25.000) | D64: 3895 | E64: 47.09 | F64: =+E64*D64 -> 183415.55 | G64: =+$D$64*X64 -> 187634.11 | H64: =+$D$64*Y64 -> 191386.79 | I64: =+$D$64*Z64 -> 195214.53 | J64: =+$D$64*AA64 -> 200875.75 | K64: =+$D$64*AB64 -> 206701.14 | L64: =+$D$64*AC64 -> 213728.98 | M64: =+$D$64*AD64 -> 219285.94 | N64: =+$D$64*AE64 -> 223890.94 | ... U64: =+$D$64*AL64 -> 273491.7 | V64: =+U64/J64 -> 1.3614968 | W64: =+E64 -> 47.09 | X64: =+W64*(1+G19) -> 48.17307 | Y64: =+X64*(1+H19) -> 49.136531 | Z64: =+Y64*(1+I19) -> 50.119262 | AA64: =+Z64*(1+J19) -> 51.572721 | AB64: =+AA64*(1+K19) -> 53.06833 | AC64: =+AB64*(1+L19) -> 54.872653 | AD64: =+AC64*(1+M19) -> 56.299342 | AE64: =+AD64*(1+N19) -> 57.481628 | ... AL64: =+AK64*(1+U19) -> 70.216096
B65: Armado Dinamicas | D65: 394 | E65: 994.37 | F65: =+E65*D65 -> 391781.78 | G65: =+$D$65*X65 -> 400792.76 | H65: =+$D$65*Y65 -> 408808.62 | I65: =+$D$65*Z65 -> 416984.79 | J65: =+$D$65*AA65 -> 429077.35 | K65: =+$D$65*AB65 -> 441520.59 | L65: =+$D$65*AC65 -> 456532.29 | M65: =+$D$65*AD65 -> 468402.13 | N65: =+$D$65*AE65 -> 478238.57 | ... U65: =+$D$65*AL65 -> 584187.46 | V65: =+U65/J65 -> 1.3614968 | W65: =+E65 -> 994.37 | X65: =+W65*(1+G19) -> 1017.2405 | Y65: =+X65*(1+H19) -> 1037.5853 | Z65: =+Y65*(1+I19) -> 1058.337 | AA65: =+Z65*(1+J19) -> 1089.0288 | AB65: =+AA65*(1+K19) -> 1120.6106 | AC65: =+AB65*(1+L19) -> 1158.7114 | AD65: =+AC65*(1+M19) -> 1188.8379 | AE65: =+AD65*(1+N19) -> 1213.8035 | ... AL65: =+AK65*(1+U19) -> 1482.7093
B66: Total Costo Avanter por Sidus Dermo | F66: =SUM(F61:F65) -> 1955316.2 | G66: =SUM(G61:G65) -> 2039357.2 | H66: =SUM(H61:H65) -> 2063927.5 | I66: =SUM(I61:I65) -> 2088977 | J66: =SUM(J61:J65) -> 2135389.1 | K66: =SUM(K61:K65) -> 2165206.4 | L66: =SUM(L61:L65) -> 2196435.8 | M66: =SUM(M61:M65) -> 2304492.7 | ... U66: =SUM(U61:U65) -> 2755697.4 | V66: =SUM(J66:U66) -> 29125197

Sheet IQVIA
A1: FACTURACION año 2025 | C1: IQVIA | D1: WORLD SALUD | G1: Proyección año 2026
C2: 0.39 | D2: 0.61
A3: Registros comprados por IQVIA | B3: 28000000 | C3: =B3*C2 -> 10920000 | D3: =B3*D2 -> 17080000
A5: Farmacias IQVIA | B5: 4.081 | C5: =C3*0.7*B5 -> 31195164 | E5: precio unitario registros válidos farmacias Iqvia
B6: 5.703 | C6: =C3*0.3*B6 -> 18683028 | E6: precio unitario registros con prescripción Iqvia (otras dispensas)
A8: Farmacias Wsalud | B8: 5.101 | D8: =D3*0.7*B8 -> 60987556 | E8: precio unitario registro válido farmacias WS
B9: 7.185 | D9: =D3*0.3*B9 -> 36815940 | E9: precio unitario registros con prescripción WS (otras dispensas)
A13: PROYECCIÓN | E13: AÑO 2025 | G13: AÑO 2026 | I13: Hipótesis
A15: Registros Farmacias | C15: =SUM(C5:C9) -> 49878192 | D15: =SUM(D5:D9) -> 97803496 | E15: =SUM(C15:D15) -> 147681688 | G15: =+E15*1.3 -> 1.9198619e+08 | H15: =+A15 -> Registros Farmacias
A17: Precio fijo Operación | B17: 12 | C17: 4044535.8 | E17: =C17*B17 -> 48534429 | G17: =+E17*1.3 -> 63094758 | H17: =+A17 -> Precio fijo Operación
A19: Precio farmacia nueva | B19: Cuantas??? | C19: 23835.29
A21: FACTURACIÓN (Registros + Operación) | E21: =SUM(E15:E19) -> 196216117 | G21: =SUM(G15:G17) -> 2.5508095e+08 | I21: (Incremento 1,30)
E23: =+E21*5%*-1 -> -9810805.8 | G23: =+G21*5%*-1 -> -12754048 | H23: IIBB 5%
A25: Ventas netas de IIBB | E25: =+E21+E23 -> 1.8640531e+08 | G25: =+G21+G23 -> 2.423269e+08 | H25: =+A25 -> Ventas netas de IIBB
A27: COSTOS año 2025 | C27: Real ene-sep2025 | D27: Estimado oct-dic
A29: SWH | C29: =SUM(Reporte_Registros_IQVIA_Serie_T!C26:K26) -> 19242638 | D29: =SUM(Reporte_Registros_IQVIA_Serie_T!L26:N26) -> 6987954 | E29: =SUM(C29:D29) -> 26230592 | I29: Hipótesis
A30: Farmacias | C30: =SUM(Reporte_Registros_IQVIA_Serie_T!C27:K27) -> 6560334 | D30: =SUM(Reporte_Registros_IQVIA_Serie_T!L27:N27) -> 2119440 | E30: =SUM(C30:D30) -> 8679774
A32: Costos | E32: =SUM(E29:E30) -> 34910366 | G32: =E32*1.3 -> 45383476 | I32: (Incremento 1,30)
A34: Resultado bruto | E34: =E25-E32 -> 1.5149495e+08 | G34: =G25-G32 -> 1.9694343e+08
E35: =E34/E25 -> 0.81271797 | G35: =G34/G25 -> 0.81271797
A37: El costo 2025 a las farmacias y a las SWHouse es de
A38: 1 | B38: por registro | G38: considerar IPC

Sheet Panalab Man
A1: Panalab Manual | B1: Septiembre 2025 | D1: 45957 | F1: =+D1+30 -> 45987 | H1: =+F1+30 -> 46017 | J1: =+H1+30 -> 46047 | L1: =+J1+30 -> 46077 | N1: =+L1+30 -> 46107 | P1: 46142 | R1: 46172 | T1: 46202 | V1: 46232 | X1: 46262 | Z1: 46292 | AB1: 46322 | AD1: 46352 | AF1: 46382
B2: Facturación Proceso Manual Panalab
A3: Cantidad Registros Procesados sin Acondicionamiento | B3: 143483.22 | C3: =B3*B4 -> 11180213 | D3: 160000 | E3: =D3*D4 -> 12753946 | F3: 135000 | G3: =F3*F4 -> 10976364 | H3: =+F3*0.9 -> 121500 | I3: =H3*H4 -> 10076303 | J3: =+H3*0.9 -> 109350 | K3: =J3*J4 -> 9331663.8 | L3: =+J3*0.9 -> 98415 | M3: =L3*L4 -> 8642053.8 | N3: =+L3*0.9 -> 88573.5 | O3: =N3*N4 -> 8042295.3 | P3: =+N3*0.9 -> 79716.15 | Q3: =P3*P4 -> 7426255.5 | R3: =+P3*0.9 -> 71744.535 | S3: =R3*R4 -> 6823986.2 | T3: =+R3*0.9 -> 64570.082 | U3: =T3*T4 -> 6319693.6 | V3: =+T3*0.9 -> 58113.073 | W3: =V3*V4 -> 5852668.2 | X3: =+V3*0.9 -> 52301.766 | Y3: =X3*X4 -> 5420156 | Z3: =+X3*0.9 -> 47071.589 | AA3: =Z3*Z4 -> 5019606.5 | AB3: =+Z3*0.9 -> 42364.43 | AC3: =AB3*AB4 -> 4648657.6 | AD3: =+AB3*0.9 -> 38127.987 | AE3: =AD3*AD4 -> 4305121.8 | AF3: =+AD3*0.9 -> 34315.189 | AG3: =AF3*AF4 -> 3986973.3
A4: Valor unitario sin acondicionamiento Registro Septiembre 2025 | B4: 77.92 | D4: =+B4*(1+D13) -> 79.71216 | F4: =+D4*(1+F13) -> 81.306403 | H4: =+F4*(1+H13) -> 82.932531 | J4: =+H4*(1+J13) -> 85.337575 | L4: =+J4*(1+L13) -> 87.812364 | N4: =+L4*(1+N13) -> 90.797985 | P4: =+N4*(1+P13) -> 93.158732 | R4: =+P4*(1+R13) -> 95.115066 | T4: =+R4*(1+T13) -> 97.873403 | V4: =+T4*(1+V13) -> 100.71173 | X4: =+V4*(1+X13) -> 103.63237 | Z4: =+X4*(1+Z13) -> 106.63771 | AB4: =+Z4*(1+AB13) -> 109.7302 | AD4: =+AB4*(1+AD13) -> 112.91238 | AF4: =+AD4*(1+AF13) -> 116.18684
A5: Cantidad Registros Procesados con Acondicionamiento | B5: 16475.777 | C5: =B5*B6 -> 2136578.8 | D5: =+D3*0.1 -> 16000 | E5: =D5*D6 -> 2122602.2 | F5: =+F3*0.1 -> 13500 | G5: =F5*F6 -> 1826764.6 | H5: =+H3*0.1 -> 12150 | I5: =H5*H6 -> 1676969.9 | J5: =+J3*0.1 -> 10935 | K5: =J5*J6 -> 1553041.8 | L5: =+L3*0.1 -> 9841.5 | M5: =L5*L6 -> 1438272 | N5: =+N3*0.1 -> 8857.35 | O5: =N5*N6 -> 1338455.9 | P5: =+P3*0.1 -> 7971.615 | Q5: =P5*P6 -> 1235930.2 | R5: =+R3*0.1 -> 7174.4535 | S5: =R5*R6 -> 1135696.3 | T5: =+T3*0.1 -> 6457.0082 | U5: =T5*T6 -> 1051768.3 | V5: =+V3*0.1 -> 5811.3073 | W5: =V5*V6 -> 974042.63 | X5: =+X3*0.1 -> 5230.1766 | Y5: =X5*X6 -> 902060.88 | Z5: =+Z3*0.1 -> 4707.1589 | AA5: =Z5*Z6 -> 835398.58 | AB5: =+AB3*0.1 -> 4236.443 | AC5: =AB5*AB6 -> 773662.62 | AD5: =+AD3*0.1 -> 3812.7987 | AE5: =AD5*AD6 -> 716488.96 | AF5: =+AF3*0.1 -> 3431.5189 | AG5: =AF5*AF6 -> 663540.42
A6: Valor unitario con acondicionamiento Registro Septiembre 2025 | B6: 129.68 | D6: =+B6*(1+D13) -> 132.66264 | F6: =+D6*(1+F13) -> 135.31589 | H6: =+F6*(1+H13) -> 138.02221 | J6: =+H6*(1+J13) -> 142.02485 | L6: =+J6*(1+L13) -> 146.14358 | N6: =+L6*(1+N13) -> 151.11246 | P6: =+N6*(1+P13) -> 155.04138 | R6: =+P6*(1+R13) -> 158.29725 | T6: =+R6*(1+T13) -> 162.88787 | V6: =+T6*(1+V13) -> 167.61162 | X6: =+V6*(1+X13) -> 172.47236 | Z6: =+X6*(1+Z13) -> 177.47405 | AB6: =+Z6*(1+AB13) -> 182.6208 | AD6: =+AB6*(1+AD13) -> 187.9168 | AF6: =+AD6*(1+AF13) -> 193.36639
A7: Cantidad Total Registros Procesados | B7: 159959 | C7: =C3+C5 -> 13316791 | D7: =+D5+D3 -> 176000 | E7: =E3+E5 -> 14876548 | F7: =+F5+F3 -> 148500 | G7: =G3+G5 -> 12803129 | H7: =+H5+H3 -> 133650 | I7: =I3+I5 -> 11753272 | J7: =+J5+J3 -> 120285 | K7: =K3+K5 -> 10884706 | L7: =+L5+L3 -> 108256.5 | M7: =M3+M5 -> 10080326 | N7: =+N5+N3 -> 97430.85 | O7: =O3+O5 -> 9380751.2 | P7: =+P5+P3 -> 87687.765 | Q7: =Q3+Q5 -> 8662185.7 | R7: =+R5+R3 -> 78918.989 | S7: =S3+S5 -> 7959682.4 | T7: =+T5+T3 -> 71027.09 | U7: =U3+U5 -> 7371461.9 | V7: =+V5+V3 -> 63924.381 | W7: =W3+W5 -> 6826710.9 | X7: =+X5+X3 -> 57531.943 | Y7: =Y3+Y5 -> 6322216.9 | Z7: =+Z5+Z3 -> 51778.748 | AA7: =AA3+AA5 -> 5855005.1 | AB7: =+AB5+AB3 -> 46600.874 | AC7: =AC3+AC5 -> 5422320.2 | AD7: =+AD5+AD3 -> 41940.786 | AE7: =AE3+AE5 -> 5021610.8 | AF7: =+AF5+AF3 -> 37746.708 | AG7: =AG3+AG5 -> 4650513.7
A8: Total a facturar por proceso de Registros
A9: Cajas Utilizadas | B9: 72 | C9: =B9*B10 -> 264008.16 | D9: =+B9 -> 72 | E9: =D9*D10 -> 270080.35 | F9: =+D9*0.9 -> 64.8 | G9: =F9*F10 -> 247933.76 | H9: =+F9*0.9 -> 58.32 | I9: =H9*H10 -> 227603.19 | J9: =+H9*0.9 -> 52.488 | K9: =J9*J10 -> 210783.32 | L9: =+J9*0.9 -> 47.2392 | M9: =L9*L10 -> 195206.43 | N9: =+L9*0.9 -> 42.51528 | O9: =N9*N10 -> 181659.1 | P9: =+N9*0.9 -> 38.263752 | Q9: =P9*P10 -> 167744.01 | R9: =+P9*0.9 -> 34.437377 | S9: =R9*R10 -> 154139.98 | T9: =+R9*0.9 -> 30.993639 | U9: =T9*T10 -> 142749.03 | V9: =+T9*0.9 -> 27.894275 | W9: =V9*V10 -> 132199.88 | X9: =+V9*0.9 -> 25.104848 | Y9: =X9*X10 -> 122430.31 | Z9: =+X9*0.9 -> 22.594363 | AA9: =Z9*Z10 -> 113382.71 | AB9: =+Z9*0.9 -> 20.334927 | AC9: =AB9*AB10 -> 105003.72 | AD9: =+AB9*0.9 -> 18.301434 | AE9: =AD9*AD10 -> 97243.95 | AF9: =+AD9*0.9 -> 16.471291 | AG9: =AF9*AF10 -> 90057.622
A10: Valor unitario Caja Septiembre 2025 | B10: 3666.78 | D10: =+B10*(1+D13) -> 3751.1159 | F10: =+D10*(1+F13) -> 3826.1383 | H10: =+F10*(1+H13) -> 3902.661 | J10: =+H10*(1+J13) -> 4015.8382 | L10: =+J10*(1+L13) -> 4132.2975 | N10: =+L10*(1+N13) -> 4272.7956 | P10: =+N10*(1+P13) -> 4383.8883 | R10: =+P10*(1+R13) -> 4475.95 | T10: =+R10*(1+T13) -> 4605.7525 | V10: =+T10*(1+V13) -> 4739.3193 | X10: =+V10*(1+X13) -> 4876.7596 | Z10: =+X10*(1+Z13) -> 5018.1856 | AB10: =+Z10*(1+AB13) -> 5163.713 | AD10: =+AB10*(1+AD13) -> 5313.4607 | AF10: =+AD10*(1+AF13) -> 5467.551
A11: Total Facturación | C11: =C7+C9 -> 13580800 | E11: =E7+E9 -> 15146628 | G11: =G7+G9 -> 13051063 | I11: =I7+I9 -> 11980876 | K11: =K7+K9 -> 11095489 | M11: =M7+M9 -> 10275532 | O11: =O7+O9 -> 9562410.3 | Q11: =Q7+Q9 -> 8829929.7 | S11: =S7+S9 -> 8113822.4 | U11: =U7+U9 -> 7514210.9 | W11: =W7+W9 -> 6958910.7 | Y11: =Y7+Y9 -> 6444647.2 | AA11: =AA7+AA9 -> 5968387.8 | AC11: =AC7+AC9 -> 5527323.9 | AE11: =AE7+AE9 -> 5118854.7 | AG11: =AG7+AG9 -> 4740571.3 | AH11: =SUM(J11:AG11) -> 90150090
E12: 15200000
C13: IPC CABA mensual proyectado | D13: =+Flk!K34 -> 0.023 | F13: =+Flk!L34 -> 0.02 | H13: =+Flk!M34 -> 0.02 | J13: =+Flk!B71 -> 0.029 | L13: =+Flk!C71 -> 0.029 | N13: =+Flk!D71 -> 0.034 | P13: =+Flk!E71 -> 0.026 | R13: =+Flk!F71 -> 0.021 | T13: =+Flk!G71 -> 0.029 | V13: =+Flk!H71 -> 0.029 | X13: =+Flk!I71 -> 0.029 | Z13: =+Flk!J71 -> 0.029 | AB13: =+Flk!K71 -> 0.029 | AD13: =+Flk!L71 -> 0.029 | AF13: =+Flk!M71 -> 0.029
D15: 165000 | E15: aprox
A16: Se toma como base la cantidad de registros procesados estimada por Licha en 135.000 a Nov-25 y sobre esa base se aplica una disminución de un 10% mensual acumulativa
A17: llegando a Dic-26 con un aprox de 35.000 registros procesados
A21: COSTOS SERDATA | B21: Septiembre 2025 | D21: 45957 | F21: =+D21+30 -> 45987 | H21: =+F21+30 -> 46017 | J21: =+H21+30 -> 46047 | L21: =+J21+30 -> 46077 | N21: =+L21+30 -> 46107 | P21: 46142 | R21: 46172 | T21: 46202 | V21: 46232 | X21: 46262 | Z21: 46292 | AB21: 46322 | AD21: 46352 | AF21: 46382
B22: Proceso Manual Panalab
A23: Cantidad de Registros Procesados | B23: 148666 | C23: =B23*B24 -> 7950657.7 | D23: =+D3 -> 160000 | E23: =D23*D24 -> 8753606.4 | F23: =+F3 -> 135000 | G23: =F23*F24 -> 7533572.5 | H23: =+H3 -> 121500 | I23: =H23*H24 -> 6915819.6 | J23: =+J3 -> 109350 | K23: =J23*J24 -> 6404740.5 | L23: =+L3 -> 98415 | M23: =L23*L24 -> 5931430.2 | N23: =+N3 -> 88573.5 | O23: =N23*N24 -> 5519788.9 | P23: =+P3 -> 79716.15 | Q23: =P23*P24 -> 5096973.1 | R23: =+R3 -> 71744.535 | S23: =R23*R24 -> 4683608.6 | T23: =+T3 -> 64570.082 | U23: =T23*T24 -> 4337489.9 | V23: =+V3 -> 58113.073 | W23: =V23*V24 -> 4016949.4 | X23: =+X3 -> 52301.766 | Y23: =X23*X24 -> 3720096.8 | Z23: =+Z3 -> 47071.589 | AA23: =Z23*Z24 -> 3445181.7 | AB23: =+AB3 -> 42364.43 | AC23: =AB23*AB24 -> 3190582.8 | AD23: =+AD3 -> 38127.987 | AE23: =AD23*AD24 -> 2954798.7 | AF23: =+AF3 -> 34315.189 | AG23: =AF23*AF24 -> 2736439.1
A24: Valor Unitario | B24: 53.48 | D24: =+B24*(1+D13) -> 54.71004 | F24: =+D24*(1+F13) -> 55.804241 | H24: =+F24*(1+H13) -> 56.920326 | J24: =+H24*(1+J13) -> 58.571015 | L24: =+J24*(1+L13) -> 60.269574 | N24: =+L24*(1+N13) -> 62.31874 | P24: =+N24*(1+P13) -> 63.939027 | R24: =+P24*(1+R13) -> 65.281747 | T24: =+R24*(1+T13) -> 67.174918 | V24: =+T24*(1+V13) -> 69.12299 | X24: =+V24*(1+X13) -> 71.127557 | Z24: =+X24*(1+Z13) -> 73.190256 | AB24: =+Z24*(1+AB13) -> 75.312773 | AD24: =+AB24*(1+AD13) -> 77.496844 | AF24: =+AD24*(1+AF13) -> 79.744252
A25: Costo Total | C25: =C21+C23 -> 7950657.7 | E25: =E21+E23 -> 8753606.4 | G25: =G21+G23 -> 7533572.5 | I25: =I21+I23 -> 6915819.6 | K25: =K21+K23 -> 6404740.5 | M25: =M21+M23 -> 5931430.2 | O25: =O21+O23 -> 5519788.9 | Q25: =Q21+Q23 -> 5096973.1 | S25: =S21+S23 -> 4683608.6 | U25: =U21+U23 -> 4337489.9 | W25: =W21+W23 -> 4016949.4 | Y25: =Y21+Y23 -> 3720096.8 | AA25: =AA21+AA23 -> 3445181.7 | AC25: =AC21+AC23 -> 3190582.8 | AE25: =AE21+AE23 -> 2954798.7 | AG25: =AG21+AG23 -> 2736439.1
A28: * datos históricos
A29: Bonos Procesados Agosto | B29: 113911 | C29: =B29*B30 -> 5960962.6 | D29: IPC CABA
A30: Valor unitario Registro Agosto 2025 | B30: 52.33 | D30: Mes | E30: Incremento
A31: Bonos Procesados | B31: 186841 | C31: 9624179.9
A32: Valor unitario Registro Julio 2025 | B32: 51.51 | F32: Servicios IMED
A33: Bonos Procesados | B33: 164661 | C33: 8104614.4 | F33: Factor 1 | G33: Factor 2 | H33: Factor 3
A34: Valor unitario Registro Mayo 2025 | B34: 49.22 | F34: Valor registro procesado | G34: Valor caja | H34: Valor guarda caja
D35: 44866 | E35: base | F35: 8.5 | G35: 400 | H35: 40
B36: =+B24/B30-1 -> 0.021975922 | D36: 44896 | E36: 0.058 | F36: =+F35*(1+E36) -> 8.993 | G36: =+G35*(1+E36) -> 423.2 | H36: =+H35*(1+E36) -> 42.32
B37: =+B30/B32-1 -> 0.015919239 | D37: 44927 | E37: 0.073 | F37: =+F36*(1+E37) -> 9.649489 | G37: =+G36*(1+E37) -> 454.0936 | H37: =+H36*(1+E37) -> 45.40936
D38: 44958 | E38: 0.06 | F38: =+F37*(1+E38) -> 10.228458 | G38: =+G37*(1+E38) -> 481.33922 | H38: =+H37*(1+E38) -> 48.133922
D39: 44986 | E39: 0.071 | F39: =+F38*(1+E39) -> 10.954679 | G39: =+G38*(1+E39) -> 515.5143 | H39: =+H38*(1+E39) -> 51.55143
D40: 45017 | E40: 0.078 | F40: =+F39*(1+E40) -> 11.809144 | G40: =+G39*(1+E40) -> 555.72442 | H40: =+H39*(1+E40) -> 55.572442
D41: 45047 | E41: 0.075 | F41: =+F40*(1+E41) -> 12.69483 | G41: =+G40*(1+E41) -> 597.40375 | H41: =+H40*(1+E41) -> 59.740375
D42: 45078 | E42: 0.071 | F42: =+F41*(1+E42) -> 13.596163 | G42: =+G41*(1+E42) -> 639.81941 | H42: =+H41*(1+E42) -> 63.981941
D43: 45108 | E43: 0.073 | F43: =+F42*(1+E43) -> 14.588682 | G43: =+G42*(1+E43) -> 686.52623 | H43: =+H42*(1+E43) -> 68.652623
D44: 45139 | E44: 0.108 | F44: =+F43*(1+E44) -> 16.16426 | G44: =+G43*(1+E44) -> 760.67106 | H44: =+H43*(1+E44) -> 76.067106
D45: 45170 | E45: 0.12 | F45: =+F44*(1+E45) -> 18.103971 | G45: =+G44*(1+E45) -> 851.95159 | H45: =+H44*(1+E45) -> 85.195159
D46: 45200 | E46: 0.094 | F46: =+F45*(1+E46) -> 19.805745 | G46: =+G45*(1+E46) -> 932.03504 | H46: =+H45*(1+E46) -> 93.203504
D47: 45231 | E47: 0.119 | F47: =+F46*(1+E47) -> 22.162628 | G47: =+G46*(1+E47) -> 1042.9472 | H47: =+H46*(1+E47) -> 104.29472
D48: 45261 | E48: 0.211 | F48: =+F47*(1+E48) -> 26.838943 | G48: =+G47*(1+E48) -> 1263.0091 | H48: =+H47*(1+E48) -> 126.30091
D49: 45292 | E49: 0.217 | F49: =+F48*(1+E49) -> 32.662993 | G49: =+G48*(1+E49) -> 1537.082 | H49: =+H48*(1+E49) -> 153.7082
... D69: 45901 | E69: 0.022 | F69: =+F68*(1+E69) -> 77.918992 | G69: =+G68*(1+E69) -> 3666.7761 | H69: =+H68*(1+E69) -> 366.67761

Sheet Panalab Dig
A1: FACTURACIÓN PANALAB BONOS DIGITALES (*)
A2: Cli_id | B2: Conceptos | C2: MES
C3: 45901
C4: Envases Aprobados | D4: Monto Total | E4: PVP Promedio | F4: % PVP | G4: $ Total Facturación sin Mínimo
A5: 5080 | B5: Panalab BONOS Digitales Emisiones | C5: 5306 | D5: 2.2382739e+08 | E5: =D5/C5 -> 42183.828 | F5: 0.002 | G5: =D5*F5 -> 447654.78
A6: 5080 | B6: Panalab BONOS Digitales Dispensas | C6: =C5 -> 5306 | D6: 2.2382739e+08 | E6: =D6/C6 -> 42183.828 | F6: 0.004 | G6: =D6*F6 -> 895309.57
A7: TOTAL | G7: =G5+G6 -> 1342964.4
A9: Cli_id | B9: Conceptos | C9: 45901 | H9: 45957 | J9: =+H9+30 -> 45987 | L9: =+J9+30 -> 46017 | N9: =+L9+30 -> 46047 | P9: =+N9+30 -> 46077 | R9: =+P9+30 -> 46107 | T9: 46142 | V9: 46172 | X9: 46202 | Z9: 46232 | AB9: 46262 | AD9: 46292 | AF9: 46322 | AH9: 46352 | AJ9: 46382
C10: Envases | D10: PVP Promedio | E10: Monto Total | F10: 0,6 % Monto | G10: $ Total Facturación
A11: 5080 | B11: Facturación Transaccional Bonos Digitales | C11: =C6 -> 5306 | D11: =E6 -> 42183.828 | E11: =C11*D11 -> 2.2382739e+08 | F11: =D11*0.6% -> 253.10297 | G11: =C11*F11 -> 1342964.4 | I11: =+G11*(1+H35) -> 1373852.5 | K11: =+I11*(1+J35) -> 1401329.6 | M11: =+K11*(1+L35) -> 1429356.2 | O11: =+M11*(1+N35) -> 1470807.5 | Q11: =+O11*(1+P35) -> 1513460.9 | S11: =+Q11*(1+R35) -> 1564918.6 | U11: =+S11*(1+T35) -> 1605606.5 | W11: =+U11*(1+V35) -> 1639324.2 | Y11: =+W11*(1+X35) -> 1686864.6 | AA11: =+Y11*(1+Z35) -> 1735783.7 | AC11: =+AA11*(1+AB35) -> 1786121.4 | AE11: =+AC11*(1+AD35) -> 1837918.9 | AG11: =+AE11*(1+AF35) -> 1891218.6 | AI11: =+AG11*(1+AH35) -> 1946063.9 | AK11: =+AI11*(1+AJ35) -> 2002499.8 | AL11: =+AK11/O11 -> 1.3614968
A12: (*) | B12: Actualiza Mensual por IPC CABA
A13: (**) | B13: Actualiza Trimestral por IPC CABA --->>> | C13: FACTURACIÓN PLATAFORMA EMISIÓN BONOS DIGITALES (BONOS DERMO) PANALAB (**)
C14: Cli_id | D14: Conceptos | E14: 45901
E15: Precio Unitario | F15: Cantidad | G15: Precio Total | I15: validar con licha
C16: 5080 | D16: USO DE LA PLATAFORMA | E16: =D69 -> 1041934.1 | F16: 1 | G16: =E16*F16 -> 1041934.1 | I16: =+C71 -> 1081894.3 | K16: =+I16 -> 1081894.3 | M16: =+K16 -> 1081894.3 | O16: =+M16*N36 -> 1151491.7 | Q16: =+O16 -> 1151491.7 | S16: =+Q16 -> 1151491.7 | U16: =+S16*T36 -> 1260701 | W16: =+U16 -> 1260701 | Y16: =+W16 -> 1260701 | AA16: =+Y16*Z36 -> 1358940.9 | AC16: =+AA16 -> 1358940.9 | AE16: =+AC16 -> 1358940.9 | AG16: =+AE16*AF36 -> 1480630.6 | AI16: =+AG16 -> 1480630.6 | AK16: =+AI16 -> 1480630.6 | AL16: =+AK16/O16 -> 1.2858369
C17: 5080 | D17: MENSAJES WHATSAPP | E17: 0.13 | F17: 42322 | G17: =(E17*F17)*D20 -> 7785131.9 | H17: =+E17 -> 0.13 | I17: =+H17*$F$17*H20 -> 8252790 | J17: =+H17 -> 0.13 | K17: =+J17*$F$17*J20 -> 8401340.2 | L17: =+J17 -> 0.13 | M17: =+L17*$F$17*L20 -> 8552564.3 | N17: =+L17 -> 0.13 | O17: =+N17*$F$17*N20 -> 7785131.9 | P17: =+N17 -> 0.13 | Q17: =+P17*$F$17*P20 -> 7925264.3 | R17: =+P17 -> 0.13 | S17: =+R17*$F$17*R20 -> 8067919 | T17: =+R17 -> 0.13 | U17: =+T17*$F$17*T20 -> 8213141.6 | V17: =+T17 -> 0.13 | W17: =+V17*$F$17*V20 -> 8360978.1 | X17: =+V17 -> 0.13 | Y17: =+X17*$F$17*X20 -> 8511475.7 | Z17: =+X17 -> 0.13 | AA17: =+Z17*$F$17*Z20 -> 8664682.3 | AB17: =+Z17 -> 0.13 | AC17: =+AB17*$F$17*AB20 -> 8820646.6 | AD17: =+AB17 -> 0.13 | AE17: =+AD17*$F$17*AD20 -> 8979418.2 | AF17: =+AD17 -> 0.13 | AG17: =+AF17*$F$17*AF20 -> 9141047.7 | AH17: =+AF17 -> 0.13 | AI17: =+AH17*$F$17*AH20 -> 9305586.6 | AJ17: =+AH17 -> 0.13 | AK17: =+AJ17*$F$17*AJ20 -> 9473087.2 | AL17: =+AK17/O17 -> 1.2168178
C18: TOTAL | G18: =G16+G17 -> 8827066 | I18: =SUM(I16:I17) -> 9334684.3 | K18: =SUM(K16:K17) -> 9483234.5 | M18: =SUM(M16:M17) -> 9634458.7 | O18: =SUM(O16:O17) -> 8936623.6 | Q18: =SUM(Q16:Q17) -> 9076756 | S18: =SUM(S16:S17) -> 9219410.8 | U18: =SUM(U16:U17) -> 9473842.6 | W18: =SUM(W16:W17) -> 9621679.2 | Y18: =SUM(Y16:Y17) -> 9772176.8 | AA18: =SUM(AA16:AA17) -> 10023623 | AC18: =SUM(AC16:AC17) -> 10179588 | AE18: =SUM(AE16:AE17) -> 10338359 | AG18: =SUM(AG16:AG17) -> 10621678 | AI18: =SUM(AI16:AI17) -> 10786217 | AK18: =SUM(AK16:AK17) -> 10953718 | AL18: =+AK18/O18 -> 1.225711
C20: Valor dólar BNA | D20: 1415 | H20: 1500 | J20: =+H20*1.018 -> 1527 | L20: =+J20*1.018 -> 1554.486 | N20: =+SidusDermo!J17 -> 1415 | P20: =+N20*1.018 -> 1440.47 | R20: =+P20*1.018 -> 1466.3985 | T20: =+R20*1.018 -> 1492.7936 | V20: =+T20*1.018 -> 1519.6639 | X20: =+V20*1.018 -> 1547.0179 | Z20: =+X20*1.018 -> 1574.8642 | AB20: =+Z20*1.018 -> 1603.2117 | AD20: =+AB20*1.018 -> 1632.0696 | AF20: =+AD20*1.018 -> 1661.4468 | AH20: =+AF20*1.018 -> 1691.3529 | AJ20: =+AH20*1.018 -> 1721.7972
A22: FACTURACIÓN PANALAB BONOS PAPEL ON LINE (*)
A23: Cli_id | B23: Conceptos | C23: 45901
C24: Envases Aprobados | D24: Monto Total | E24: PVP Promedio | F24: % PVP | G24: $ Total Facturación sin Mínimo | O24: (1)
A25: 5081 | B25: Panalab BONOS Papel On Line Dispensas | C25: 76780 | D25: 3.1017947e+09 | E25: =D25/C25 -> 40398.472 | F25: 0.004 | G25: =D25*F25 -> 12407179 | I25: =+G25*(1+H35) -> 12692544 | K25: =+I25*(1+J35) -> 12946395 | M25: =+K25*(1+L35) -> 13205323 | O25: =+M25*(1+N35)*1.05 -> 14267691 | Q25: =+O25*(1+P35)*1.05 -> 15415526 | S25: =+Q25*(1+R35)*1.05 -> 16736637 | U25: =+S25*(1+T35)*1.05 -> 18030379 | W25: =+U25*(1+V35)*1.05 -> 19329468 | Y25: =+W25*(1+X35)*1.05 -> 20884524 | AA25: =+Y25*(1+Z35)*1.05 -> 22564684 | AC25: =+AA25*(1+AB35)*1.05 -> 24380012 | AE25: =+AC25*(1+AD35)*1.05 -> 26341384 | AG25: =+AE25*(1+AF35)*1.05 -> 28460549 | AI25: =+AG25*(1+AH35)*1.05 -> 30750200 | AK25: =+AI25*(1+AJ35)*1.05 -> 33224053 | AL25: =+AK25/O25 -> 2.3286216
E27: RESUMEN TOTAL FACTURACIÓN PANALAB BONOS DIGITALES Y ON LINE
A28: (1) | E28: Cli_id | F28: Conceptos | G28: 45901 | H28: =+H9 -> 45957 | J28: =+J9 -> 45987 | L28: =+L9 -> 46017 | N28: =+N9 -> 46047 | P28: =+P9 -> 46077 | R28: =+R9 -> 46107 | T28: =+T9 -> 46142 | V28: =+V9 -> 46172 | X28: =+X9 -> 46202 | Z28: =+Z9 -> 46232 | AB28: =+AB9 -> 46262 | AD28: =+AD9 -> 46292 | AF28: =+AF9 -> 46322 | AH28: =+AH9 -> 46352 | AJ28: =+AJ9 -> 46382
A29: a partir del mes de enero 2026 se estima que crecerá un 10% en forma mensual | G29: Precio Unitario
A30: por la caida del procesamiento manual | E30: 5080 | F30: BONOS DIGITALES | G30: =+G11 -> 1342964.4 | I30: =+I11 -> 1373852.5 | K30: =+K11 -> 1401329.6 | M30: =+M11 -> 1429356.2 | O30: =+O11 -> 1470807.5 | Q30: =+Q11 -> 1513460.9 | S30: =+S11 -> 1564918.6 | U30: =+U11 -> 1605606.5 | W30: =+W11 -> 1639324.2 | Y30: =+Y11 -> 1686864.6 | AA30: =+AA11 -> 1735783.7 | AC30: =+AC11 -> 1786121.4 | AE30: =+AE11 -> 1837918.9 | AG30: =+AG11 -> 1891218.6 | AI30: =+AI11 -> 1946063.9 | AK30: =+AK11 -> 2002499.8 | AL30: =+AK30/O30 -> 1.3614968
E31: 5080 | F31: PLATAFORMA EMISIÓN BONOS DIGITALES | G31: =G18 -> 8827066 | I31: =+I18 -> 9334684.3 | K31: =+K18 -> 9483234.5 | M31: =+M18 -> 9634458.7 | O31: =+O18 -> 8936623.6 | Q31: =+Q18 -> 9076756 | S31: =+S18 -> 9219410.8 | U31: =+U18 -> 9473842.6 | W31: =+W18 -> 9621679.2 | Y31: =+Y18 -> 9772176.8 | AA31: =+AA18 -> 10023623 | AC31: =+AC18 -> 10179588 | AE31: =+AE18 -> 10338359 | AG31: =+AG18 -> 10621678 | AI31: =+AI18 -> 10786217 | AK31: =+AK18 -> 10953718 | AL31: =+AK31/O31 -> 1.225711
E32: 5081 | F32: BONOS PAPEL ON LINE | G32: =G25 -> 12407179 | I32: =+I25 -> 12692544 | K32: =+K25 -> 12946395 | M32: =+M25 -> 13205323 | O32: =+O25 -> 14267691 | Q32: =+Q25 -> 15415526 | S32: =+S25 -> 16736637 | U32: =+U25 -> 18030379 | W32: =+W25 -> 19329468 | Y32: =+Y25 -> 20884524 | AA32: =+AA25 -> 22564684 | AC32: =+AC25 -> 24380012 | AE32: =+AE25 -> 26341384 | AG32: =+AG25 -> 28460549 | AI32: =+AI25 -> 30750200 | AK32: =+AK25 -> 33224053 | AL32: =+AK32/O32 -> 2.3286216
E33: TOTAL | G33: =G30+G31+G32 -> 22577209 | I33: =SUM(I30:I32) -> 23401081 | K33: =SUM(K30:K32) -> 23830959 | M33: =SUM(M30:M32) -> 24269137 | O33: =SUM(O30:O32) -> 24675122 | Q33: =SUM(Q30:Q32) -> 26005743 | S33: =SUM(S30:S32) -> 27520966 | U33: =SUM(U30:U32) -> 29109828 | W33: =SUM(W30:W32) -> 30590471 | Y33: =SUM(Y30:Y32) -> 32343565 | AA33: =SUM(AA30:AA32) -> 34324091 | AC33: =SUM(AC30:AC32) -> 36345721 | AE33: =SUM(AE30:AE32) -> 38517662 | AG33: =SUM(AG30:AG32) -> 40973446 | AI33: =SUM(AI30:AI32) -> 43482481 | AK33: =SUM(AK30:AK32) -> 46180271 | AL33: =SUM(N33:AK33) -> 4.1006937e+08
G35: IPC CABA mensual proyectado | H35: {=+'Panalab Man'!D13:E13} -> 0.023 | I35: 0 | J35: {=+'Panalab Man'!F13:G13} -> 0.02 | K35: 0 | L35: {=+'Panalab Man'!H13:I13} -> 0.02 | M35: 0 | N35: {=+'Panalab Man'!J13:K13} -> 0.029 | O35: 0 | P35: {=+'Panalab Man'!L13:M13} -> 0.029 | Q35: 0 | R35: {=+'Panalab Man'!N13:O13} -> 0.034 | S35: 0 | T35: {=+'Panalab Man'!P13:Q13} -> 0.026 | U35: 0 | V35: {=+'Panalab Man'!R13:S13} -> 0.021 | W35: 0 | X35: {=+'Panalab Man'!T13:U13} -> 0.029 | Y35: 0 | Z35: {=+'Panalab Man'!V13:W13} -> 0.029 | AA35: 0 | AB35: {=+'Panalab Man'!X13:Y13} -> 0.029 | AC35: 0 | AD35: {=+'Panalab Man'!Z13:AA13} -> 0.029 | AE35: 0 | AF35: {=+'Panalab Man'!AB13:AC13} -> 0.029 | AG35: 0 | AH35: {=+'Panalab Man'!AD13:AE13} -> 0.029 | AI35: 0 | AJ35: {=+'Panalab Man'!AF13:AG13} -> 0.029 | AK35: 0
E36: 0.025 | F36: 0.016 | G36: 0.022 | H36: =1*(1+E36)*(1+F36)*(1+G36) -> 1.0643108 | N36: =1*(1+H35)*(1+J35)*(1+L35) -> 1.0643292 | T36: =1*(1+N35)*(1+P35)*(1+R35) -> 1.0948416 | Z36: =1*(1+T35)*(1+V35)*(1+X35) -> 1.0779248 | AF36: =1*(1+Z35)*(1+AB35)*(1+AD35) -> 1.0895474
B38: COSTO AVANTER (PANALAB) | C38: Conceptos | E38: 45901 | H38: =+H28 -> 45957 | J38: =+J28 -> 45987 | L38: =+L28 -> 46017 | N38: =+N28 -> 46047 | P38: =+P28 -> 46077 | R38: =+R28 -> 46107 | T38: =+T28 -> 46142 | V38: =+V28 -> 46172 | X38: =+X28 -> 46202 | Z38: =+Z28 -> 46232 | AB38: =+AB28 -> 46262 | AD38: =+AD28 -> 46292 | AF38: =+AF28 -> 46322 | AH38: =+AH28 -> 46352 | AJ38: =+AJ28 -> 46382
E39: Precio Unitario | F39: Cantidad | G39: Precio Total
C40: USO DE LA PLATAFORMA | E40: 732919.71 | F40: 1 | G40: =E40*F40 -> 732919.71 | I40: =+G40*H36 -> 780054.36 | K40: =+I40 -> 780054.36 | M40: =+K40 -> 780054.36 | O40: =+M40*N36 -> 830234.64 | Q40: =+O40 -> 830234.64 | S40: =+Q40 -> 830234.64 | U40: =+S40*T36 -> 908975.41 | W40: =+U40 -> 908975.41 | Y40: =+W40 -> 908975.41 | AA40: =+Y40*Z36 -> 979807.17 | AC40: =+AA40 -> 979807.17 | AE40: =+AC40 -> 979807.17 | AG40: =+AE40*AF36 -> 1067546.3 | AI40: =+AG40 -> 1067546.3 | AK40: =+AI40 -> 1067546.3 | AL40: =+AK40/O40 -> 1.2858369
C41: MENSAJES WHATSAPP | E41: 0.1 | F41: 42322 | G41: =(E41*F41)*D20 -> 5988563 | H41: =+E41 -> 0.1 | I41: =+H41*$F$41*H20 -> 6348300 | J41: =+H41 -> 0.1 | K41: =+J41*$F$41*J20 -> 6462569.4 | L41: =+J41 -> 0.1 | M41: =+L41*$F$41*L20 -> 6578895.6 | N41: =+L41 -> 0.1 | O41: =+N41*$F$41*N20 -> 5988563 | P41: =+N41 -> 0.1 | Q41: =+P41*$F$41*P20 -> 6096357.1 | R41: =+P41 -> 0.1 | S41: =+R41*$F$41*R20 -> 6206091.6 | T41: =+R41 -> 0.1 | U41: =+T41*$F$41*T20 -> 6317801.2 | V41: =+T41 -> 0.1 | W41: =+V41*$F$41*V20 -> 6431521.6 | X41: =+V41 -> 0.1 | Y41: =+X41*$F$41*X20 -> 6547289 | Z41: =+X41 -> 0.1 | AA41: =+Z41*$F$41*Z20 -> 6665140.2 | AB41: =+Z41 -> 0.1 | AC41: =+AB41*$F$41*AB20 -> 6785112.7 | AD41: =+AB41 -> 0.1 | AE41: =+AD41*$F$41*AD20 -> 6907244.8 | AF41: =+AD41 -> 0.1 | AG41: =+AF41*$F$41*AF20 -> 7031575.2 | AH41: =+AF41 -> 0.1 | AI41: =+AH41*$F$41*AH20 -> 7158143.5 | AJ41: =+AH41 -> 0.1 | AK41: =+AJ41*$F$41*AJ20 -> 7286990.1 | AL41: =+AK41/O41 -> 1.2168178
C42: TRX Bonos | E42: 74.81 | F42: 4674 | G42: =(E42*F42) -> 349661.94 | H42: =+E42*H36 -> 79.621091 | I42: =+H42*$F$42 -> 372148.98 | J42: =+H42 -> 79.621091 | K42: =+J42*$F$42 -> 372148.98 | L42: =+J42 -> 79.621091 | M42: =+L42*$F$42 -> 372148.98 | N42: =+L42*N36 -> 84.743052 | O42: =+N42*$F$42 -> 396089.03 | P42: =+N42 -> 84.743052 | Q42: =+P42*$F$42 -> 396089.03 | R42: =+P42 -> 84.743052 | S42: =+R42*$F$42 -> 396089.03 | T42: =+R42*T36 -> 92.780218 | U42: =+T42*F42 -> 433654.74 | V42: =+T42 -> 92.780218 | W42: =+V42*$F$42 -> 433654.74 | X42: =+V42 -> 92.780218 | Y42: =+X42*$F$42 -> 433654.74 | Z42: =+X42*Z36 -> 100.0101 | AA42: =+Z42*$F$42 -> 467447.21 | AB42: =+Z42 -> 100.0101 | AC42: =+AB42*$F$42 -> 467447.21 | AD42: =+AB42 -> 100.0101 | AE42: =+AD42*$F$42 -> 467447.21 | AF42: =+AD42*AF36 -> 108.96574 | AG42: =+AF42*$F$42 -> 509305.89 | AH42: =+AF42 -> 108.96574 | AI42: =+AH42*$F$42 -> 509305.89 | AJ42: =+AH42 -> 108.96574 | AK42: =+AJ42*$F$42 -> 509305.89 | AL42: =+AK42/O42 -> 1.2858369
C43: TOTAL COSTO AVANTER | G43: =G40+G41 -> 6721482.7 | I43: =SUM(I40:I42) -> 7500503.3 | K43: =SUM(K40:K42) -> 7614772.7 | M43: =SUM(M40:M42) -> 7731099 | O43: =SUM(O40:O42) -> 7214886.7 | Q43: =SUM(Q40:Q42) -> 7322680.8 | S43: =SUM(S40:S42) -> 7432415.2 | U43: =SUM(U40:U42) -> 7660431.4 | W43: =SUM(W40:W42) -> 7774151.8 | Y43: =SUM(Y40:Y42) -> 7889919.2 | AA43: =SUM(AA40:AA42) -> 8112394.6 | AC43: =SUM(AC40:AC42) -> 8232367.1 | AE43: =SUM(AE40:AE42) -> 8354499.2 | AG43: =SUM(AG40:AG42) -> 8608427.4 | AI43: =SUM(AI40:AI42) -> 8734995.8 | AK43: =SUM(AK40:AK42) -> 8863842.4 | AL43: =SUM(N43:AK43) -> 96201011
A45: Cálculo Incremento del servicio de Bonos Dermo
C47: Evol IPC CABA | D47: Facturado
B48: Base Octubre 2023 | C48: 275000 | D48: 275000
A49: IPC Noviembre 2023 | B49: 0.119 | C49: =(D48*B49)+D48 -> 307725 | D49: 275000
A50: IPC Diciembre 2023 | B50: 0.211 | C50: =(C49*B50)+C49 -> 372654.97 | D50: 275000
A51: IPC Enero 2024 | B51: 0.217 | C51: =(C50*B51)+C50 -> 453521.1 | D51: 453521.1
A52: IPC Febrero 2024 | B52: 0.141 | C52: =(C51*B52)+C51 -> 517467.58 | D52: 453521.1
A53: IPC Marzo 2024 | B53: 0.132 | C53: =(C52*B53)+C52 -> 585773.3 | D53: 453521.1
A54: IPC Abril 2024 | B54: 0.098 | C54: 642156.36 | D54: 642156.36
A55: IPC Mayo 2024 | B55: 0.044 | C55: =(C54*B55)+C54 -> 670411.24 | D55: 642156.36
A56: IPC Junio 2024 | B56: 0.048 | C56: =(C55*B56)+C55 -> 702590.98 | D56: 642156.36
A57: IPC JuLio 2024 | B57: 0.051 | C57: 739599.16 | D57: =C57 -> 739599.16
A58: IPC Agosto 2024 | B58: 0.042 | C58: =(C57*B58)+C57 -> 770662.33 | D58: 739599.16
A59: IPC Septiembre 2024 | B59: 0.04 | C59: =(C58*B59)+C58 -> 801488.82 | D59: 739599.16
A60: IPC Octubre 2024 | B60: 0.032 | C60: =(C59*B60)+C59 -> 827136.46 | D60: =C60 -> 827136.46
A61: IPC Noviembre 2024 | B61: 0.032 | C61: =(C60*B61)+C60 -> 853604.83 | D61: 827136.46
A62: IPC Diciembre 2024 | B62: 0.033 | C62: =(C61*B62)+C61 -> 881773.79 | D62: 827136.46
A63: IPC CABA Enero 2025 | B63: 0.031 | C63: =(C62*B63)+C62 -> 909108.78 | D63: =C63 -> 909108.78
A64: IPC CABA Febrero 2025 | B64: 0.021 | C64: =(C63*B64)+C63 -> 928200.06 | D64: 909108.78
A65: IPC CABA Marzo 2025 | B65: 0.032 | C65: =(C64*B65)+C64 -> 957902.46 | D65: 909108.78
A66: IPC CABA Abril 2025 | B66: 0.023 | C66: =(C65*B66)+C65 -> 979934.22 | D66: 979934.22
A67: IPC CABA Mayo 2025 | B67: 0.016 | C67: =(C66*B67)+C66 -> 995613.17 | D67: 979934.22
A68: IPC CABA Junio 2025 | B68: 0.021 | C68: =(C67*B68)+C67 -> 1016521 | D68: 979934.22
A69: IPC CABA Julio 2025 | B69: 0.025 | C69: =(C68*B69)+C68 -> 1041934.1 | D69: =C69 -> 1041934.1
A70: IPC CABA Agosto 2025 | B70: 0.016 | C70: =(C69*B70)+C69 -> 1058605 | D70: 1041934.1
A71: IPC CABA Septiembre 2025 | B71: 0.022 | C71: =(C70*B71)+C70 -> 1081894.3 | D71: 1041934.1
A74: Se toma como base la cantidad de emisión y dispensa de bonos y los msjes de whatsapp reales del mes de Septiembre25
A75: manteniendo el mismo volumen estable a diciembre 2026

Sheet Osseg
A2: % increm. abono | C2: =+C5/B5-1 -> 0.87971934 | F2: =+F5/E5-1 -> 0.51536315 | I2: 0.201 | L2: =(+K14-1)*0 -> 0 | O2: =(+N14-1)*0 -> 0 | R2: =+R5/Q5 -> 1.1529 | U2: =+U5/T5 -> 1 | X2: 1.1430045 | AA2: =+AA5/Z5 -> 1.0643292 | AD2: =+AD5/AC5 -> 1.0456784 | AG2: =+AG5/AF5 -> 1.0456784 | AJ2: =+AJ5/AI5 -> 1.0456784
A3: 70000 | W3: =+W5/A3 -> 139.53866 | X3: =+X5/$A$3 -> 159.49331 | AA3: =+AA5/$A$3 -> 169.75339 | AD3: =+AD5/$A$3 -> 177.50744 | AG3: =+AG5/$A$3 -> 185.6157 | AJ3: =+AJ5/$A$3 -> 194.09432
B4: 45170 | C4: 45292 | D4: 45323 | E4: 45352 | F4: 45383 | G4: 45413 | H4: 45444 | I4: 45474 | J4: 45505 | K4: 45536 | L4: 45566 | M4: 45597 | N4: 45627 | O4: =+N4+31 -> 45658 | P4: =+O4+31 -> 45689 | Q4: =+P4+31 -> 45720 | R4: =+Q4+31 -> 45751 | S4: =+R4+31 -> 45782 | T4: =+S4+31 -> 45813 | U4: =+T4+31 -> 45844 | V4: =+U4+31 -> 45875 | ... X4: =+W4+31 -> 45937 | Y4: =+X4+30 -> 45967 | Z4: =+Y4+30 -> 45997 | AA4: =+Z4+30 -> 46027 | AB4: =+AA4+28 -> 46055 | AC4: =+AB4+30 -> 46085 | AD4: =+AC4+30 -> 46115 | AE4: =+AD4+30 -> 46145 | AF4: =+AE4+30 -> 46175 | AG4: =+AF4+30 -> 46205 | AH4: =+AG4+30 -> 46235 | AI4: =+AH4+31 -> 46266 | AJ4: =+AI4+30 -> 46296 | AK4: =+AJ4+31 -> 46327 | AL4: =+AK4+30 -> 46357
A5: precio hasta 70.000 | B5: 2476556.2 | C5: =4655230.67 -> 4655230.7 | D5: =4655230.67 -> 4655230.7 | E5: =4655230.67 -> 4655230.7 | F5: 7054365 | G5: 7054365 | H5: 7054365 | I5: =+H5*(1+I2) -> 8472292.4 | J5: =+I5 -> 8472292.4 | K5: =+J5 -> 8472292.4 | L5: =+I5*(1+L2) -> 8472292.4 | M5: =+L5 -> 8472292.4 | N5: =+M5 -> 8472292.4 | O5: =+L5*(1+O2) -> 8472292.4 | P5: =+O5 -> 8472292.4 | Q5: =+P5 -> 8472292.4 | R5: 9767706 | S5: =+R5 -> 9767706 | T5: =+S5 -> 9767706 | U5: 9767706 | V5: =+U5 -> 9767706 | W5: =+V5 -> 9767706 | X5: =+X13 -> 11164532 | Y5: =+X5 -> 11164532 | Z5: =+Y5 -> 11164532 | AA5: =+Z5*AA19 -> 11882737 | AB5: =+AA5 -> 11882737 | AC5: =+AB5 -> 11882737 | AD5: =+AC5*AD19 -> 12425521 | AE5: =+AD5 -> 12425521 | AF5: =+AE5 -> 12425521 | AG5: =+AF5*AG19 -> 12993099 | AH5: =+AG5 -> 12993099 | AI5: =+AH5 -> 12993099 | AJ5: =+AI5*AJ19 -> 13586602 | AK5: =+AJ5 -> 13586602 | AL5: =+AK5 -> 13586602
A6: Trx Mes | C6: 61433 | D6: 60301 | E6: 66283 | F6: 71760 | G6: 76379 | H6: 61932 | I6: =70000+I7 -> 71195 | J6: =70000+J7 -> 71883 | K6: 67978 | L6: 71178 | M6: 65631 | N6: 62378 | O6: 62369 | P6: 60426 | Q6: 65677 | R6: 70989 | S6: 69445 | T6: 67278 | U6: 73360 | V6: 69061 | W6: 69485 | X6: 69457
A7: Cant Trx Adic | C7: 0 | D7: 0 | E7: 0 | F7: =+F6-$A$3 -> 1760 | G7: =+G6-$A$3 -> 6379 | H7: 0 | I7: 1195 | J7: 1883 | K7: 0 | L7: =+L6-70000 -> 1178 | M7: 0 | N7: 0 | O7: 0 | P7: 0 | Q7: 0 | R7: =+R6-70000 -> 989 | S7: 0 | T7: 0 | U7: =+U6-70000 -> 3360 | V7: 0 | W7: 0 | X7: 0
A8: precio trx adic. | C8: 44.43 | D8: 44.43 | E8: 44.43 | F8: 67.33 | G8: 67.33 | H8: 67.33 | I8: 80.86 | J8: =+I8 -> 80.86 | K8: =+J8 -> 80.86 | L8: =+K8 -> 80.86 | M8: =+L8 -> 80.86 | N8: =+M8 -> 80.86 | O8: =+N8 -> 80.86 | P8: =+O8 -> 80.86 | Q8: =+P8 -> 80.86 | R8: 93.22 | S8: =+R8 -> 93.22 | T8: =+S8 -> 93.22 | U8: 93.22 | V8: =+U8 -> 93.22 | W8: =+V8 -> 93.22 | X8: =+W8*X2 -> 106.55088 | Y8: =+X8 -> 106.55088 | Z8: =+Y8 -> 106.55088 | AA8: =+Z8*AA19 -> 113.40521 | AB8: =+AA8 -> 113.40521 | AC8: =+AB8 -> 113.40521 | AD8: =+AC8*AD19 -> 118.58537 | AE8: =+AD8 -> 118.58537 | AF8: =+AE8 -> 118.58537 | AG8: =+AF8*AG19 -> 124.00216 | AH8: =+AG8 -> 124.00216 | AI8: =+AH8 -> 124.00216 | AJ8: =+AI8*AJ19 -> 129.66638 | AK8: =+AJ8 -> 129.66638 | AL8: =+AK8 -> 129.66638
A9: Total Trx Adic a facturar | F9: =+F8*F7 -> 118500.8 | G9: =+G8*G7 -> 429498.07 | H9: =+H8*H7 -> 0 | I9: =+I8*I7 -> 96627.7 | J9: =+J8*J7 -> 152259.38 | K9: =+K8*K7 -> 0 | L9: =+L8*L7 -> 95253.08 | M9: =+M8*M7 -> 0 | ... AL9: =+AL8*AL7 -> 0
A10: Precio Total | C10: =+C5 -> 4655230.7 | D10: =+D5 -> 4655230.7 | E10: =+E5 -> 4655230.7 | F10: =+F5+F9 -> 7172865.8 | G10: =+G5+G9 -> 7483863.1 | H10: =+H5+H9 -> 7054365 | I10: =+I5+I9 -> 8568920.1 | J10: =+J5+J9 -> 8624551.7 | K10: =+K5+K9 -> 8472292.4 | L10: =+L5+L9 -> 8567545.4 | M10: =+M5+M9 -> 8472292.4 | ... AL10: =+AL5+AL9 -> 13586602 | AM10: =SUM(AA10:AL10) -> 1.5266388e+08
T12: =+T5/70000 -> 139.53866 | X12: =+X13/A3 -> 159.49331
A13: IPC CABA | F13: 0.098 | G13: 0.044 | H13: 0.048 | I13: 0.051 | J13: 0.042 | K13: 0.04 | L13: 0.032 | M13: 0.032 | O13: 0.032 | P13: 0.032 | U13: =+T5*U19 -> 10530922 | X13: =+U13*X19 -> 11164532
H14: =(1+F13)*(1+G13)*(1+H13) -> 1.201335 | K14: =(1+I13)*(1+J13)*(1+K13) -> 1.1389477 | X14: =+X13/T5 -> 1.1430045
O16: 0.022 | P16: 0.024 | Q16: 0.037 | R16: 0.028 | S16: 0.015 | T16: 0.016 | U16: 0.019 | V16: 0.019 | W16: 0.021 | X16: 0.023 | Y16: 0.02 | Z16: =+Y16 -> 0.02 | AA16: 0.015 | AB16: =+AA16 -> 0.015 | AC16: =+AB16 -> 0.015 | AD16: =+AC16 -> 0.015 | AE16: =+AD16 -> 0.015 | AF16: =+AE16 -> 0.015 | AG16: =+AF16 -> 0.015 | AH16: =+AG16 -> 0.015 | AI16: =+AH16 -> 0.015 | ... AL16: =+AK16 -> 0.015
Q18: 0.02
Q19: =+Q16-Q18 -> 0.017 | U19: =1*(1+Q19)*(1+R16)*(1+S16)*(1+T16) -> 1.0781367 | X19: =1*(1+U16)*(1+V16)*(1+W16) -> 1.0601666 | AA19: =1*(1+X16)*(1+Y16)*(1+Z16) -> 1.0643292 | AD19: =1*(1+AA16)*(1+AB16)*(1+AC16) -> 1.0456784 | AG19: =1*(1+AD16)*(1+AE16)*(1+AF16) -> 1.0456784 | AJ19: =1*(1+AG16)*(1+AH16)*(1+AI16) -> 1.0456784

Sheet PciaART
A1: Facturación Provincia ART- SEPTIEMBRE 2025
A2: Concepto | B2: Cantidad | C2: Monto Vendido | D2: % | E2: Monto a Facturar | F2: 45957 | G2: 45987 | H2: 46017 | I2: 46023 | J2: 46054 | K2: 46112 | L2: 46142 | M2: 46172 | N2: 46202 | O2: 46232 | P2: 46262 | Q2: 46292 | R2: 46322 | S2: 46352 | T2: 46382
A3: Operación Servicio | B3: 1 | C3: 3.3394173e+08 | D3: 0.35 | E3: =C3*D3% -> 1168796 | F3: =+E3 -> 1168796 | G3: =+F3 -> 1168796 | H3: =+G3 -> 1168796 | I3: =+H3*(I4) -> 1243983.8 | J3: =+I3 -> 1243983.8 | K3: =+J3 -> 1243983.8 | L3: =+K3*(L4) -> 1300806.9 | M3: =+L3 -> 1300806.9 | N3: =+M3 -> 1300806.9 | O3: =+N3*(O4) -> 1360225.7 | P3: =+O3 -> 1360225.7 | Q3: =+P3 -> 1360225.7 | R3: =+Q3*(R4) -> 1422358.6 | S3: =+R3 -> 1422358.6 | T3: =+S3 -> 1422358.6 | U3: =SUM(I3:T3) -> 15982125
I4: =1*(1+F5)*(1+G5)*(1+H5) -> 1.0643292 | L4: =1*(1+I5)*(1+J5)*(1+K5) -> 1.0456784 | O4: =1*(1+L5)*(1+M5)*(1+N5) -> 1.0456784 | R4: =1*(1+O5)*(1+P5)*(1+Q5) -> 1.0456784
E5: Indice incremento de precios medicamentos (*) | F5: 0.023 | G5: 0.02 | H5: 0.02 | I5: 0.015 | J5: =+I5 -> 0.015 | K5: =+J5 -> 0.015 | L5: =+K5 -> 0.015 | M5: =+L5 -> 0.015 | N5: =+M5 -> 0.015 | O5: =+N5 -> 0.015 | P5: =+O5 -> 0.015 | Q5: =+P5 -> 0.015 | ... T5: =+S5 -> 0.015
B6: (*) se considera ipc trimestral acumulado
C8: se aplica IPC trimestral acumulado
B10: COMPARATIVO | E10: precio con actualización mensual por ipc | F10: 1194509.6 | G10: 1218399.8 | H10: 1242767.7 | I10: 1261409.3 | J10: 1280330.4 | K10: 1299535.4 | L10: 1319028.4 | M10: 1338813.8 | N10: 1358896 | O10: 1379279.5 | P10: 1399968.7 | Q10: 1420968.2 | R10: 1442282.7 | S10: 1463916.9 | T10: 1485875.7 | U10: =SUM(I10:T10) -> 16450305

Sheet Ceoderma
A1: FACTURACIÓN CEODERMA
A2: Cli_id | B2: Conceptos | C2: MES
C3: 45901
C4: Envases Aprobados | D4: Monto Total | E4: PVP Promedio | F4: % PVP | G4: $ Total Facturación | H4: 45957 | I4: 45987 | J4: 46017 | K4: 46023 | L4: 46054 | M4: 46112 | N4: 46142 | O4: 46172 | P4: 46202 | Q4: 46232 | R4: 46262 | S4: 46292 | T4: 46322 | U4: 46352 | V4: 46382
A5: 5120 | B5: Transacciones CEODERMA | C5: 3003 | D5: 88416400 | E5: =D5/C5 -> 29442.691 | F5: 0.006 | G5: =D5*F5 -> 530498.4 | H5: =+G5 -> 530498.4 | I5: =+H5 -> 530498.4 | J5: =+I5 -> 530498.4 | K5: =+J5*K7 -> 564624.94 | L5: =+K5 -> 564624.94 | M5: =+L5 -> 564624.94 | N5: =+M5*N7 -> 590416.09 | O5: =+N5 -> 590416.09 | P5: =+O5 -> 590416.09 | Q5: =+P5*Q7 -> 617385.33 | R5: =+Q5 -> 617385.33 | S5: =+R5 -> 617385.33 | T5: =+S5*T7 -> 645586.49 | U5: =+T5 -> 645586.49 | V5: =+U5 -> 645586.49 | W5: =SUM(K5:V5) -> 7254038.6
A6: TOTAL | G6: =G5 -> 530498.4
K7: =1*(1+H8)*(1+I8)*(1+J8) -> 1.0643292 | N7: =1*(1+K8)*(1+L8)*(1+M8) -> 1.0456784 | Q7: =1*(1+N8)*(1+O8)*(1+P8) -> 1.0456784 | T7: =1*(1+Q8)*(1+R8)*(1+S8) -> 1.0456784
G8: Indice incremento de precios medicamentos (*) | H8: 0.023 | I8: 0.02 | J8: 0.02 | K8: 0.015 | L8: =+K8 -> 0.015 | M8: =+L8 -> 0.015 | N8: =+M8 -> 0.015 | O8: =+N8 -> 0.015 | P8: =+O8 -> 0.015 | Q8: =+P8 -> 0.015 | R8: =+Q8 -> 0.015 | S8: =+R8 -> 0.015 | ... V8: =+U8 -> 0.015
D9: (*) se considera ipc trimestral acumulado

Sheet MaxVis
A1: FACTURACIÓN MAX VISION
A2: Cli_id | B2: Conceptos | C2: MES
C3: 45901
C4: Envases Aprobados | D4: Monto Total | E4: PVP Promedio | F4: % PVP | G4: $ Total Factur sin Mínimo | H4: 45957 | I4: 45987 | J4: 46017 | K4: 46023 | L4: 46054 | M4: 46112 | N4: 46142 | O4: 46172 | P4: 46202 | Q4: 46232 | R4: 46262 | S4: 46292 | T4: 46322 | U4: 46352 | V4: 46382
A5: 5025 | B5: Max Vision Bonos Transaccionados | C5: 6016 | D5: 1.1399257e+08 | E5: =D5/C5 -> 18948.233 | F5: 0.01 | G5: =D5*F5 -> 1139925.7 | H5: =+G5 -> 1139925.7 | I5: =+H5 -> 1139925.7 | J5: =+I5 -> 1139925.7 | K5: =+J5*K7 -> 1213256.2 | L5: =+K5 -> 1213256.2 | M5: =+L5 -> 1213256.2 | N5: =+M5*N7 -> 1268675.8 | O5: =+N5 -> 1268675.8 | P5: =+O5 -> 1268675.8 | Q5: =+P5*Q7 -> 1326626.8 | R5: =+Q5 -> 1326626.8 | S5: =+R5 -> 1326626.8 | T5: =+S5*T7 -> 1387225 | U5: =+T5 -> 1387225 | V5: =+U5 -> 1387225 | W5: =SUM(K5:V5) -> 15587351
A6: TOTAL | G6: =G5 -> 1139925.7
K7: =1*(1+H8)*(1+I8)*(1+J8) -> 1.0643292 | N7: =1*(1+K8)*(1+L8)*(1+M8) -> 1.0456784 | Q7: =1*(1+N8)*(1+O8)*(1+P8) -> 1.0456784 | T7: =1*(1+Q8)*(1+R8)*(1+S8) -> 1.0456784
G8: Indice incremento de precios medicamentos (*) | H8: 0.023 | I8: 0.02 | J8: 0.02 | K8: 0.015 | L8: =+K8 -> 0.015 | M8: =+L8 -> 0.015 | N8: =+M8 -> 0.015 | O8: =+N8 -> 0.015 | P8: =+O8 -> 0.015 | Q8: =+P8 -> 0.015 | R8: =+Q8 -> 0.015 | S8: =+R8 -> 0.015 | ... V8: =+U8 -> 0.015
D9: (*) se considera ipc trimestral acumulado

Sheet Unyc
A2: Facturación Bonos Mayo 2025
A3: Cli_id | B3: Laboratorio | C3: MES
C4: 45802
C5: Cantidad | D5: $ Unitario | E5: $ Total
A6: 5070 | B6: BIU COSMECEUTICALS BONOS | C6: 69 | D6: 286.48 | E6: 19767.4
A7: TOTAL | E7: 19767.4
A9: Facturación Bonos Junio 2025
A10: Cli_id | B10: Laboratorio | C10: MES
C11: 45833
C12: Cantidad | D12: $ Unitario | E12: $ Total
A13: 5070 | B13: BIU COSMECEUTICALS BONOS | C13: 49 | D13: 304.02 | E13: 14896.98 | F13: =+D13/D6 -> 1.0612259
A14: TOTAL | E14: 14896.98
A16: Facturación Bonos Julio 2025
